Workbook

Sheet AUG24
B1: Opening balance | C1: Purchases | D1: Debit Notes | E1: Inventory Write-offs | F1: Sales | G1: Credit Note | H1: Closing balance
A2: MI0001 - 4515-Wx Hendred Brake Lining | B2: 138.25 | C2: 1292 | D2: 0 | E2: 0 | F2: -211.75 | G2: 0 | H2: 1218.5
A3: MI0002 - MP31 | B3: 0.25 | C3: 0 | D3: 0 | E3: 0 | F3: 0 | G3: 0 | H3: 0.25
A4: MI0003 - MP32 | B4: -3 | C4: 26 | D4: 0 | E4: 0 | F4: -4 | G4: 0 | H4: 19
A5: MI0004 - MP36 | B5: 172.75 | C5: 64 | D5: 0 | E5: 0 | F5: -5 | G5: 0 | H5: 231.75
A6: MI0005 - BC36 | B6: 258.25 | C6: 0 | D6: 0 | E6: -0.125 | F6: -19.5 | G6: 0 | H6: 238.625
A7: MI0008 - 996075-K AIRBAG VOLVO O/M 1076076 | B7: 2 | C7: 0 | D7: 0 | E7: 0 | F7: 0 | G7: 0 | H7: 2
A8: MI0009 - 994713-K AIRBAG VOLVO O/M 1076595 | B8: 1 | C8: 0 | D8: 0 | E8: 0 | F8: 0 | G8: 0 | H8: 1
A9: MI0010 - 994913-K AIRBAG SCA 124 DIFF / 9881 | B9: 17 | C9: 0 | D9: 0 | E9: 0 | F9: 0 | G9: 0 | H9: 17
A10: MI0011 - 999780-K AIRBAG FREIGHTLINER METAL | B10: 76 | C10: 0 | D10: 0 | E10: 0 | F10: -4 | G10: 0 | H10: 72
A11: MI0018 - BPW SPRING LONG | B11: 5 | C11: 0 | D11: 0 | E11: 0 | F11: 0 | G11: 0 | H11: 5
A12: MI0019 - OIL SEAL 125 X 150 X 13 | B12: 40 | C12: 0 | D12: 0 | E12: 0 | F12: 0 | G12: 0 | H12: 40
A13: MI0021 - H24W05 | B13: 7 | C13: 0 | D13: 0 | E13: 0 | F13: 0 | G13: 0 | H13: 7
... A482: MI0645 - TIP INJECTOR FAW | B482: 0 | C482: 0 | D482: 0 | E482: 0 | F482: -6 | G482: 0 | H482: -6
A483: MI0646 - 530W SOLAR PANEL - SLR | B483: 0 | C483: 40 | D483: 0 | E483: 0 | F483: 27/Nov/99 | G483: 0 | H483: 7
A484: MI0647 - 525W SOLAR PANEL - SLR | B484: 0 | C484: 67 | D484: 0 | E484: 0 | F484: 0 | G484: 0 | H484: 67
B486: 49100.75 | C486: 13289 | D486: 27/Dec/99 | E486: 20/Dec/99 | F486: 3/Apr/69 | G486: 51 | H486: 51200.375

Sheet SEP24
A1: .
A2: Inventory Quantity Summary
A3: For the period from 01.09.2024 to 30.09.2024
B4: Opening balance | C4: Purchases | D4: Debit Notes | E4: Inventory Write-offs | F4: Sales | G4: Credit Note | H4: Closing balance
A6: MI0001 - 4515-Wx Hendred Brake Lining | B6: 1212.5 | C6: 0 | D6: 0 | E6: 0 | F6: -132.75 | G6: 0 | H6: 1079.75
A7: MI0002 - MP31 | B7: 0.25 | C7: 0 | D7: 0 | E7: 0 | F7: 0 | G7: 0 | H7: 0.25
A8: MI0003 - MP32 | B8: 17 | C8: 0 | D8: 0 | E8: -2 | F8: -10 | G8: 0 | H8: 5
A9: MI0004 - MP36 | B9: 231.75 | C9: 0 | D9: 0 | E9: 0 | F9: -6 | G9: 0 | H9: 225.75
A10: MI0005 - BC36 | B10: 235.625 | C10: 0 | D10: 0 | E10: -3.5 | F10: -19 | G10: 0 | H10: 213.125
A11: MI0008 - 996075-K AIRBAG VOLVO O/M 1076076 | B11: 2 | C11: 0 | D11: 0 | E11: 0 | F11: 0 | G11: 0 | H11: 2
A12: MI0009 - 994713-K AIRBAG VOLVO O/M 1076595 | B12: 1 | C12: 0 | D12: 0 | E12: 0 | F12: 0 | G12: 0 | H12: 1
A13: MI0010 - 994913-K AIRBAG SCA 124 DIFF / 9881 | B13: 17 | C13: 0 | D13: 0 | E13: 0 | F13: -1 | G13: 0 | H13: 16
A14: MI0011 - 999780-K AIRBAG FREIGHTLINER METAL | B14: 72 | C14: 0 | D14: 0 | E14: 0 | F14: -1 | G14: 0 | H14: 71
A15: MI0018 - BPW SPRING LONG | B15: 5 | C15: 0 | D15: 0 | E15: 0 | F15: 0 | G15: 0 | H15: 5
A16: MI0019 - OIL SEAL 125 X 150 X 13 | B16: 40 | C16: 0 | D16: 0 | E16: 0 | F16: 0 | G16: 0 | H16: 40
A17: MI0021 - H24W05 | B17: 7 | C17: 0 | D17: 0 | E17: 0 | F17: 0 | G17: 0 | H17: 7
... A492: MI0657 - LITHIUM BATTERY 12V 100AH - SLR | B492: 0 | C492: 12 | D492: 0 | E492: 0 | F492: -6 | G492: 0 | H492: 6
B494: 51136.375 | C494: 15237 | D494: -17 | E494: -39.5 | F494: -8994.25 | G494: 41 | H494: 57363.625

Sheet OCT24
A1: .
A2: Inventory Quantity Summary
A3: For the period from 01.10.2024 to 31.10.2024
B4: Opening balance | C4: Purchases | D4: Debit Notes | E4: Inventory Write-offs | F4: Sales | G4: Credit Note | H4: Closing balance
A6: MI0001 - 4515-Wx Hendred Brake Lining | B6: 1079.75 | C6: 0 | D6: 0 | E6: 0 | F6: -188.5 | G6: 0 | H6: 891.25
A7: MI0002 - MP31 | B7: 0.25 | C7: 0 | D7: 0 | E7: 0 | F7: 0 | G7: 0 | H7: 0.25
A8: MI0003 - MP32 | B8: 5 | C8: 0 | D8: 0 | E8: 0 | F8: -6 | G8: 0 | H8: -1
A9: MI0004 - MP36 | B9: 225.75 | C9: 0 | D9: 0 | E9: 0 | F9: -4 | G9: 0 | H9: 221.75
A10: MI0005 - BC36 | B10: 213.125 | C10: 0 | D10: 0 | E10: 0 | F10: -30.5 | G10: 0 | H10: 182.625
A11: MI0008 - 996075-K AIRBAG VOLVO O/M 1076076 | B11: 2 | C11: 0 | D11: 0 | E11: 0 | F11: 0 | G11: 0 | H11: 2
A12: MI0009 - 994713-K AIRBAG VOLVO O/M 1076595 | B12: 1 | C12: 0 | D12: 0 | E12: 0 | F12: -1 | G12: 0 | H12: 0
A13: MI0010 - 994913-K AIRBAG SCA 124 DIFF / 9881 | B13: 16 | C13: 0 | D13: 0 | E13: 0 | F13: 0 | G13: 0 | H13: 16
A14: MI0011 - 999780-K AIRBAG FREIGHTLINER METAL | B14: 71 | C14: 0 | D14: 0 | E14: 0 | F14: -9 | G14: 0 | H14: 62
A15: MI0018 - BPW SPRING LONG | B15: 5 | C15: 0 | D15: 0 | E15: 0 | F15: 0 | G15: 0 | H15: 5
A16: MI0019 - OIL SEAL 125 X 150 X 13 | B16: 40 | C16: 0 | D16: 0 | E16: 0 | F16: 0 | G16: 0 | H16: 40
A17: MI0021 - H24W05 | B17: 7 | C17: 0 | D17: 0 | E17: 0 | F17: 0 | G17: 0 | H17: 7
... A490: MI0660 - 410W SOLAR PANEL - SLR | B490: 0 | C490: 0 | D490: 0 | E490: 0 | F490: -1 | G490: 0 | H490: -1
B492: 57363.625 | C492: 6823 | D492: -11 | E492: -6 | F492: -11374.75 | G492: 12 | H492: 52806.875

Sheet NOV24
A1: .
A2: Inventory Quantity Summary
A3: For the period from 01.11.2024 to 30.11.2024
B4: Opening balance | C4: Purchases | D4: Debit Notes | E4: Inventory Write-offs | F4: Sales | G4: Credit Note | H4: Closing balance
A6: MI0001 - 4515-Wx Hendred Brake Lining | B6: 891.25 | C6: 1308 | D6: 0 | E6: -0.125 | F6: -228.75 | G6: 0 | H6: 1970.375
A7: MI0002 - MP31 | B7: 0.25 | C7: 0 | D7: 0 | E7: 0 | F7: 0 | G7: 0 | H7: 0.25
A8: MI0003 - MP32 | B8: -1 | C8: 52 | D8: 0 | E8: 0 | F8: -12 | G8: 0 | H8: 39
A9: MI0004 - MP36 | B9: 221.75 | C9: 0 | D9: 0 | E9: 0 | F9: -7 | G9: 0 | H9: 214.75
A10: MI0005 - BC36 | B10: 182.625 | C10: 0 | D10: 0 | E10: 0 | F10: -38.5 | G10: 0 | H10: 144.125
A11: MI0008 - 996075-K AIRBAG VOLVO O/M 1076076 | B11: 2 | C11: 0 | D11: 0 | E11: 0 | F11: 0 | G11: 0 | H11: 2
A12: MI0009 - 994713-K AIRBAG VOLVO O/M 1076595 | B12: 1 | C12: 0 | D12: 0 | E12: 0 | F12: 0 | G12: 0 | H12: 1
A13: MI0010 - 994913-K AIRBAG SCA 124 DIFF / 9881 | B13: 16 | C13: 0 | D13: 0 | E13: 0 | F13: 0 | G13: 0 | H13: 16
A14: MI0011 - 999780-K AIRBAG FREIGHTLINER METAL | B14: 62 | C14: 0 | D14: 0 | E14: 0 | F14: -22 | G14: 0 | H14: 40
A15: MI0018 - BPW SPRING LONG | B15: 5 | C15: 100 | D15: 0 | E15: 0 | F15: -2 | G15: 0 | H15: 103
A16: MI0019 - OIL SEAL 125 X 150 X 13 | B16: 40 | C16: 0 | D16: 0 | E16: 0 | F16: 0 | G16: 0 | H16: 40
A17: MI0021 - H24W05 | B17: 7 | C17: 0 | D17: 0 | E17: 0 | F17: 0 | G17: 0 | H17: 7
... A506: MI0674 - L11 RIVET | B506: 0 | C506: 20000 | D506: 0 | E506: 0 | F506: 0 | G506: 0 | H506: 20000
B508: 52849.125 | C508: 39940 | D508: -1 | E508: -9.375 | F508: -10200.75 | G508: 21 | H508: 82599

Sheet DEC24
A1: .
A2: Inventory Quantity Summary
A3: For the period from 01.12.2024 to 31.12.2024
B4: Opening balance | C4: Purchases | D4: Inventory Write-offs | E4: Sales | F4: Credit Note | G4: Closing balance
A6: MI0001 - 4515-Wx Hendred Brake Lining | B6: 1970.375 | C6: 0 | D6: 0 | E6: -169.5 | F6: 0 | G6: 1800.875
A7: MI0002 - MP31 | B7: 0.25 | C7: 0 | D7: 0 | E7: 0 | F7: 0 | G7: 0.25
A8: MI0003 - MP32 | B8: 39 | C8: 0 | D8: -2.5 | E8: -27.75 | F8: 0 | G8: 8.75
A9: MI0004 - MP36 | B9: 214.75 | C9: 0 | D9: -0.125 | E9: -2.5 | F9: 0 | G9: 212.125
A10: MI0005 - BC36 | B10: 144.125 | C10: 0 | D10: 0 | E10: -32.75 | F10: 0 | G10: 111.375
A11: MI0008 - 996075-K AIRBAG VOLVO O/M 1076076 | B11: 2 | C11: 0 | D11: 0 | E11: 0 | F11: 0 | G11: 2
A12: MI0009 - 994713-K AIRBAG VOLVO O/M 1076595 | B12: 1 | C12: 0 | D12: 0 | E12: 0 | F12: 0 | G12: 1
A13: MI0010 - 994913-K AIRBAG SCA 124 DIFF / 9881 | B13: 16 | C13: 0 | D13: 0 | E13: -1 | F13: 0 | G13: 15
A14: MI0011 - 999780-K AIRBAG FREIGHTLINER METAL | B14: 40 | C14: 0 | D14: 0 | E14: -18 | F14: 0 | G14: 22
A15: MI0018 - BPW SPRING LONG | B15: 103 | C15: 0 | D15: 0 | E15: 0 | F15: 0 | G15: 103
A16: MI0019 - OIL SEAL 125 X 150 X 13 | B16: 40 | C16: 0 | D16: 0 | E16: 0 | F16: 0 | G16: 40
A17: MI0021 - H24W05 | B17: 7 | C17: 0 | D17: 0 | E17: 0 | F17: 0 | G17: 7
... A509: MI0682 - 225/45R19 PCR TYRE | B509: 0 | C509: 100 | D509: 0 | E509: 0 | F509: 0 | G509: 100
B511: 82610 | C511: 8321 | D511: -9.625 | E511: -12722.875 | F511: 13 | G511: 78211.5

Sheet JAN25
A1: For the period from 01.01.2025 to 31.01.2025 | B1: Opening balance | C1: Purchases | D1: Inventory Write-offs | E1: Sales | F1: Credit Note | G1: Closing balance
A2: MI0001 - 4515-Wx Hendred Brake Lining | B2: 1800.875 | C2: 0 | D2: 0 | E2: -189.75 | F2: 0 | G2: 1611.125
A3: MI0002 - MP31 | B3: 0.25 | C3: 0 | D3: 0 | E3: 0 | F3: 0 | G3: 0.25
A4: MI0003 - MP32 | B4: 8.75 | C4: 4 | D4: 0 | E4: -5 | F4: 0 | G4: 7.75
A5: MI0004 - MP36 | B5: 212.125 | C5: 0 | D5: 0 | E5: -13.25 | F5: 0 | G5: 198.875
A6: MI0005 - BC36 | B6: 111.375 | C6: 0 | D6: 0 | E6: -35.75 | F6: 0 | G6: 75.625
A7: MI0008 - 996075-K AIRBAG VOLVO O/M 1076076 | B7: 2 | C7: 0 | D7: 0 | E7: 0 | F7: 0 | G7: 2
A8: MI0009 - 994713-K AIRBAG VOLVO O/M 1076595 | B8: 1 | C8: 0 | D8: 0 | E8: 0 | F8: 0 | G8: 1
A9: MI0010 - 994913-K AIRBAG SCA 124 DIFF / 9881 | B9: 15 | C9: 0 | D9: 0 | E9: 0 | F9: 0 | G9: 15
A10: MI0011 - 999780-K AIRBAG FREIGHTLINER METAL | B10: 22 | C10: 0 | D10: 0 | E10: -13 | F10: 0 | G10: 9
A11: MI0018 - BPW SPRING LONG | B11: 103 | C11: 200 | D11: 0 | E11: -26 | F11: 0 | G11: 277
A12: MI0019 - OIL SEAL 125 X 150 X 13 | B12: 40 | C12: 0 | D12: 0 | E12: 0 | F12: 0 | G12: 40
A13: MI0021 - H24W05 | B13: 7 | C13: 0 | D13: 0 | E13: 0 | F13: 0 | G13: 7
... A517: MI0697 - 24Volt 2500 Solar-Hybrid Inverter Sukam | B517: 0 | C517: 3 | D517: 0 | E517: -1 | F517: 0 | G517: 2
B519: 78211.5 | C519: 17261 | D519: -12 | E519: -10635.75 | F519: 60 | G519: 84884.75

Sheet FEB25
A1: For the period from 01.02.2025 to 28.02.2025 | B1: Opening balance | C1: Purchases | D1: Inventory Write-offs | E1: Sales | F1: Credit Note | G1: Closing balance
A2: MI0001 - 4515-Wx Hendred Brake Lining | B2: 1608.125 | C2: 0 | D2: 0 | E2: -220 | F2: 0 | G2: 1388.125
A3: MI0002 - MP31 | B3: 0.25 | C3: 0 | D3: 0 | E3: 0 | F3: 0 | G3: 0.25
A4: MI0003 - MP32 | B4: 7.75 | C4: 10 | D4: 0 | E4: -11.25 | F4: 0 | G4: 6.5
A5: MI0004 - MP36 | B5: 198.875 | C5: 0 | D5: 0 | E5: -20.5 | F5: 0 | G5: 178.375
A6: MI0005 - BC36 | B6: 75.625 | C6: 0 | D6: 0 | E6: -27 | F6: 0 | G6: 48.625
A7: MI0008 - 996075-K AIRBAG VOLVO O/M 1076076 | B7: 2 | C7: 0 | D7: 0 | E7: 0 | F7: 0 | G7: 2
A8: MI0009 - 994713-K AIRBAG VOLVO O/M 1076595 | B8: 1 | C8: 0 | D8: 0 | E8: 0 | F8: 0 | G8: 1
A9: MI0010 - 994913-K AIRBAG SCA 124 DIFF / 9881 | B9: 15 | C9: 0 | D9: 0 | E9: 0 | F9: 0 | G9: 15
A10: MI0011 - 999780-K AIRBAG FREIGHTLINER METAL | B10: 9 | C10: 0 | D10: 0 | E10: 0 | F10: 0 | G10: 9
A11: MI0018 - BPW SPRING LONG | B11: 277 | C11: 0 | D11: 0 | E11: -1 | F11: 0 | G11: 276
A12: MI0019 - OIL SEAL 125 X 150 X 13 | B12: 40 | C12: 0 | D12: 0 | E12: 0 | F12: 0 | G12: 40
A13: MI0021 - H24W05 | B13: 7 | C13: 0 | D13: 0 | E13: 0 | F13: 0 | G13: 7
... A512: MI0698 - 285/60R18 PCR TYRE | B512: 0 | C512: 100 | D512: 0 | E512: 0 | F512: 0 | G512: 100
B514: 84779.75 | C514: 14610 | D514: -33 | E514: -12531.25 | F514: 10 | G514: 86835.5

Sheet MAR25
A1: For the period from 01.03.2025 to 31.03.2025 | B1: Opening balance | C1: Purchases | D1: Inventory Write-offs | E1: Sales | F1: Credit Note | G1: Closing balance
A2: MI0001 - 4515-Wx Hendred Brake Lining | B2: 1412.875 | C2: 0 | D2: 0 | E2: -272 | F2: 0 | G2: 1140.875
A3: MI0002 - MP31 | B3: 0.25 | C3: 0 | D3: 0 | E3: 0 | F3: 0 | G3: 0.25
A4: MI0003 - MP32 | B4: 6.5 | C4: 1 | D4: 0 | E4: -6.5 | F4: 0 | G4: 1
A5: MI0004 - MP36 | B5: 178.375 | C5: 0 | D5: 0 | E5: 0 | F5: 0 | G5: 178.375
A6: MI0005 - BC36 | B6: 48.625 | C6: 0 | D6: 0 | E6: -11.875 | F6: 0 | G6: 36.75
A7: MI0008 - 996075-K AIRBAG VOLVO O/M 1076076 | B7: 2 | C7: 0 | D7: 0 | E7: 0 | F7: 0 | G7: 2
A8: MI0009 - 994713-K AIRBAG VOLVO O/M 1076595 | B8: 1 | C8: 20 | D8: 0 | E8: -2 | F8: 0 | G8: 19
A9: MI0010 - 994913-K AIRBAG SCA 124 DIFF / 9881 | B9: 15 | C9: 2 | D9: 0 | E9: -2 | F9: 0 | G9: 15
A10: MI0011 - 999780-K AIRBAG FREIGHTLINER METAL | B10: 9 | C10: 10 | D10: 0 | E10: -5 | F10: 0 | G10: 14
A11: MI0013 - 994183-24K AIRBAG BENZ | B11: 0 | C11: 0 | D11: 0 | E11: -14 | F11: 0 | G11: -14
A12: MI0018 - BPW SPRING LONG | B12: 276 | C12: 0 | D12: 0 | E12: -20 | F12: 0 | G12: 256
A13: MI0019 - OIL SEAL 125 X 150 X 13 | B13: 40 | C13: 0 | D13: 0 | E13: 0 | F13: 0 | G13: 40
... A520: MI0701 - P255/50R19 | B520: 0 | C520: 50 | D520: 0 | E520: 0 | F520: 0 | G520: 50
B522: 88493.25 | C522: 9564 | D522: -5 | E522: -13783.125 | F522: 84 | G522: 84353.125

Sheet APR25
A1: For the period from 01.04.2025 to 30.04.2025 | B1: Opening balance | C1: Purchases | D1: Inventory Write-offs | E1: Sales | F1: Credit Note | G1: Closing balance
A2: MI0001 - 4515-Wx Hendred Brake Lining | B2: 1138.125 | C2: 0 | D2: 0 | E2: -245.25 | F2: 0 | G2: 892.875
A3: MI0002 - MP31 | B3: 0.25 | C3: 0 | D3: 0 | E3: 0 | F3: 0 | G3: 0.25
A4: MI0003 - MP32 | B4: 1 | C4: 6 | D4: 0 | E4: -5 | F4: 0 | G4: 2
A5: MI0004 - MP36 | B5: 178.375 | C5: 0 | D5: 0 | E5: -3.5 | F5: 0 | G5: 174.875
A6: MI0005 - BC36 | B6: 36.75 | C6: 0 | D6: -3.5 | E6: -9 | F6: 0 | G6: 24.25
A7: MI0008 - 996075-K AIRBAG VOLVO O/M 1076076 | B7: 2 | C7: 0 | D7: 0 | E7: 0 | F7: 0 | G7: 2
A8: MI0009 - 994713-K AIRBAG VOLVO O/M 1076595 | B8: 19 | C8: 0 | D8: 0 | E8: 0 | F8: 0 | G8: 19
A9: MI0010 - 994913-K AIRBAG SCA 124 DIFF / 9881 | B9: 15 | C9: 0 | D9: 0 | E9: 0 | F9: 0 | G9: 15
A10: MI0011 - 999780-K AIRBAG FREIGHTLINER METAL | B10: 14 | C10: 10 | D10: 0 | E10: -15 | F10: 0 | G10: 9
A11: MI0013 - 994183-24K AIRBAG BENZ | B11: -14 | C11: 0 | D11: 0 | E11: 0 | F11: 0 | G11: -14
A12: MI0018 - BPW SPRING LONG | B12: 256 | C12: 0 | D12: 0 | E12: -1 | F12: 0 | G12: 255
A13: MI0019 - OIL SEAL 125 X 150 X 13 | B13: 40 | C13: 0 | D13: 0 | E13: 0 | F13: 0 | G13: 40
... A526: MI0702 - JY-12.00R20 DIFF TYRE JD681 | B526: 50 | C526: 0 | D526: 0 | E526: 0 | F526: 0 | G526: 50
B528: 85032.375 | C528: 4347 | D528: -6.5 | E528: -13192.5 | F528: 47 | G528: 76227.375

Sheet MAY25
A1: For the period from 01.05.2025 to 31.05.2025 | B1: Opening balance | C1: Purchases | D1: Inventory Write-offs | E1: Sales | F1: Credit Note | G1: Closing balance
A2: MI0001 - 4515-Wx Hendred Brake Lining | B2: 892.875 | C2: 0 | D2: 0 | E2: -257.25 | F2: 0 | G2: 635.625
A3: MI0002 - MP31 | B3: 0.25 | C3: 0 | D3: 0 | E3: 0 | F3: 0 | G3: 0.25
A4: MI0003 - MP32 | B4: 2 | C4: 8 | D4: 0 | E4: -8 | F4: 0 | G4: 2
A5: MI0004 - MP36 | B5: 174.875 | C5: 0 | D5: 0 | E5: -17 | F5: 0 | G5: 157.875
A6: MI0005 - BC36 | B6: 24.25 | C6: 26 | D6: 0 | E6: -20.5 | F6: 0 | G6: 29.75
A7: MI0008 - 996075-K AIRBAG VOLVO O/M 1076076 | B7: 2 | C7: 0 | D7: 0 | E7: 0 | F7: 0 | G7: 2
A8: MI0009 - 994713-K AIRBAG VOLVO O/M 1076595 | B8: 19 | C8: 0 | D8: 0 | E8: -6 | F8: 0 | G8: 13
A9: MI0010 - 994913-K AIRBAG SCA 124 DIFF / 9881 | B9: 15 | C9: 0 | D9: 0 | E9: -1 | F9: 0 | G9: 14
A10: MI0011 - 999780-K AIRBAG FREIGHTLINER METAL | B10: 9 | C10: 0 | D10: 0 | E10: -7 | F10: 0 | G10: 2
A11: MI0013 - 994183-24K AIRBAG BENZ | B11: -14 | C11: 0 | D11: 0 | E11: 0 | F11: 0 | G11: -14
A12: MI0018 - BPW SPRING LONG | B12: 255 | C12: 0 | D12: 0 | E12: 0 | F12: 0 | G12: 255
A13: MI0019 - OIL SEAL 125 X 150 X 13 | B13: 40 | C13: 0 | D13: 0 | E13: 0 | F13: 0 | G13: 40
... A536: MI0711 - TYRE LASER MACHINE | B536: 0 | C536: 1 | D536: 0 | E536: 0 | F536: 0 | G536: 1
B538: 76253.375 | C538: 9153 | D538: -5 | E538: -15928.75 | F538: 113 | G538: 69585.625

Sheet JUNE25
A1: For the period from 01.06.2025 to 30.06.2025 | B1: Opening balance | C1: Purchases | D1: Inventory Write-offs | E1: Sales | F1: Credit Note | G1: Closing balance
A2: MI0001 - 4515-Wx Hendred Brake Lining | B2: 635.625 | C2: 680 | D2: 0 | E2: -257 | F2: 20 | G2: 1078.625
A3: MI0002 - MP31 | B3: 0.25 | C3: 0 | D3: 0 | E3: 0 | F3: 0 | G3: 0.25
A4: MI0003 - MP32 | B4: 2 | C4: 128 | D4: 0 | E4: -1.25 | F4: 0 | G4: 128.75
A5: MI0004 - MP36 | B5: 157.875 | C5: 0 | D5: 0 | E5: -34.25 | F5: 0 | G5: 123.625
A6: MI0005 - BC36 | B6: 29.75 | C6: 300 | D6: -0.125 | E6: -10 | F6: 0 | G6: 319.625
A7: MI0008 - 996075-K AIRBAG VOLVO O/M 1076076 | B7: 2 | C7: 0 | D7: 0 | E7: 0 | F7: 0 | G7: 2
A8: MI0009 - 994713-K AIRBAG VOLVO O/M 1076595 | B8: 13 | C8: 0 | D8: 0 | E8: -6 | F8: 0 | G8: 7
A9: MI0010 - 994913-K AIRBAG SCA 124 DIFF / 9881 | B9: 14 | C9: 0 | D9: 0 | E9: -2 | F9: 0 | G9: 12
A10: MI0011 - 999780-K AIRBAG FREIGHTLINER METAL | B10: 2 | C10: 50 | D10: 0 | E10: -1 | F10: 0 | G10: 51
A11: MI0013 - 994183-24K AIRBAG BENZ | B11: -14 | C11: 0 | D11: 0 | E11: 0 | F11: 0 | G11: -14
A12: MI0018 - BPW SPRING LONG | B12: 255 | C12: 0 | D12: 0 | E12: -2 | F12: 0 | G12: 253
A13: MI0019 - OIL SEAL 125 X 150 X 13 | B13: 40 | C13: 0 | D13: 0 | E13: -4 | F13: 0 | G13: 36
... A559: MI0732 - W01M58-8619 BPW 6 HOLE AIRBAG 37941-C | B559: 0 | C559: 10 | D559: 0 | E559: -2 | F559: 0 | G559: 8
B561: 69585.625 | C561: 23329 | D561: -22.125 | E561: -13980 | F561: 82 | G561: 78994.5

Sheet JULY25
A1: For the period from 01.07.2025 to 31.07.2025 | B1: Opening balance | C1: Purchases | D1: Inventory Write-offs | E1: Sales | F1: Credit Note | G1: Closing balance
A2: MI0001 - 4515-Wx Hendred Brake Lining | B2: 1078.625 | C2: 0 | D2: 0 | E2: -211.75 | F2: 0 | G2: 866.875
A3: MI0002 - MP31 | B3: 0.25 | C3: 0 | D3: 0 | E3: 0 | F3: 0 | G3: 0.25
A4: MI0003 - MP32 | B4: 128.75 | C4: 0 | D4: 0 | E4: -15 | F4: 0 | G4: 113.75
A5: MI0004 - MP36 | B5: 123.625 | C5: 0 | D5: 0 | E5: -26 | F5: 0 | G5: 97.625
A6: MI0005 - BC36 | B6: 319.625 | C6: 0 | D6: 0 | E6: -27.25 | F6: 0 | G6: 292.375
A7: MI0008 - 996075-K AIRBAG VOLVO O/M 1076076 | B7: 2 | C7: 0 | D7: 0 | E7: 0 | F7: 0 | G7: 2
A8: MI0009 - 994713-K AIRBAG VOLVO O/M 1076595 | B8: 7 | C8: 0 | D8: 0 | E8: -2 | F8: 0 | G8: 5
A9: MI0010 - 994913-K AIRBAG SCA 124 DIFF / 9881 | B9: 12 | C9: 0 | D9: 0 | E9: -1 | F9: 0 | G9: 11
A10: MI0011 - 999780-K AIRBAG FREIGHTLINER METAL | B10: 51 | C10: 0 | D10: 0 | E10: -11 | F10: 0 | G10: 40
A11: MI0013 - 994183-24K AIRBAG BENZ | B11: -14 | C11: 0 | D11: 0 | E11: 0 | F11: 0 | G11: -14
A12: MI0018 - BPW SPRING LONG | B12: 253 | C12: 0 | D12: 0 | E12: 0 | F12: 0 | G12: 253
A13: MI0019 - OIL SEAL 125 X 150 X 13 | B13: 36 | C13: 0 | D13: 0 | E13: -1 | F13: 0 | G13: 35
... A558: MI0738 - SOLAR LED LIGHT 1000W | B558: 0 | C558: 138 | D558: 0 | E558: -13 | F558: 0 | G558: 125
B560: 78993.5 | C560: 6214 | D560: -14 | E560: -12349.5 | F560: 4 | G560: 72848

Sheet AUG25
A1: For the period from 01.08.2025 to 31.08.2025 | B1: Opening balance | C1: Purchases | D1: Inventory Write-offs | E1: Sales | F1: Credit Note | G1: Closing balance
A2: MI0001 - 4515-Wx Hendred Brake Lining | B2: 866.875 | C2: 0 | D2: 0 | E2: -145.25 | F2: 0 | G2: 721.625
A3: MI0002 - MP31 | B3: 0.25 | C3: 0 | D3: 0 | E3: 0 | F3: 0 | G3: 0.25
A4: MI0003 - MP32 | B4: 113.75 | C4: 0 | D4: 0 | E4: -21.25 | F4: 0 | G4: 92.5
A5: MI0004 - MP36 | B5: 97.625 | C5: 0 | D5: 0 | E5: -10.625 | F5: 0 | G5: 87
A6: MI0005 - BC36 | B6: 292.375 | C6: 0 | D6: 0 | E6: -29.25 | F6: 0 | G6: 263.125
A7: MI0008 - 996075-K AIRBAG VOLVO O/M 1076076 | B7: 2 | C7: 0 | D7: 0 | E7: 0 | F7: 0 | G7: 2
A8: MI0009 - 994713-K AIRBAG VOLVO O/M 1076595 | B8: 5 | C8: 0 | D8: 0 | E8: 0 | F8: 0 | G8: 5
A9: MI0010 - 994913-K AIRBAG SCA 124 DIFF / 9881 | B9: 11 | C9: 0 | D9: 0 | E9: -2 | F9: 0 | G9: 9
A10: MI0011 - 999780-K AIRBAG FREIGHTLINER METAL | B10: 40 | C10: 0 | D10: 0 | E10: -2 | F10: 0 | G10: 38
A11: MI0013 - 994183-24K AIRBAG BENZ | B11: -14 | C11: 0 | D11: 0 | E11: 0 | F11: 0 | G11: -14
A12: MI0018 - BPW SPRING LONG | B12: 253 | C12: 0 | D12: 0 | E12: -18 | F12: 0 | G12: 235
A13: MI0019 - OIL SEAL 125 X 150 X 13 | B13: 35 | C13: 0 | D13: 0 | E13: -5 | F13: 0 | G13: 30
... A560: MI0744 - 12KW INVERTER - SLR | B560: 0 | C560: 1 | D560: 0 | E560: 0 | F560: 0 | G560: 1
B562: 72848 | C562: 27335 | D562: -12 | E562: -15673.625 | F562: 17 | G562: 84514.375

Sheet SEP25
B1: Opening balance | C1: Purchases | D1: Debit Notes | E1: Inventory Write-offs | F1: Sales | G1: Credit Note | H1: Closing balance
A2: MI0001 - 4515-Wx Hendred Brake Lining | B2: 721.625 | C2: 902 | D2: - | E2: -3 | F2: -228.25 | G2: - | H2: 1392.375
A3: MI0002 - MP31 | B3: 0.25 | C3: - | D3: - | E3: - | F3: - | G3: - | H3: 0.25
A4: MI0003 - MP32 | B4: 92.5 | C4: - | D4: - | E4: - | F4: -15.75 | G4: - | H4: 76.75
A5: MI0004 - MP36 | B5: 87 | C5: - | D5: - | E5: - | F5: -9 | G5: - | H5: 78
A6: MI0005 - BC36 | B6: 263.125 | C6: - | D6: - | E6: - | F6: -28 | G6: - | H6: 235.125
A7: MI0008 - 996075-K AIRBAG VOLVO O/M 1076076 | B7: 2 | C7: - | D7: - | E7: - | F7: - | G7: - | H7: 2
A8: MI0009 - 994713-K AIRBAG VOLVO O/M 1076595 | B8: 5 | C8: - | D8: - | E8: - | F8: - | G8: - | H8: 5
A9: MI0010 - 994913-K AIRBAG SCA 124 DIFF / 9881 | B9: 9 | C9: - | D9: - | E9: - | F9: -3 | G9: - | H9: 6
A10: MI0011 - 999780-K AIRBAG FREIGHTLINER METAL | B10: 38 | C10: - | D10: - | E10: - | F10: -9 | G10: - | H10: 29
A11: MI0013 - 994183-24K AIRBAG BENZ | B11: -14 | C11: - | D11: - | E11: - | F11: - | G11: - | H11: -14
A12: MI0018 - BPW SPRING LONG | B12: 235 | C12: - | D12: - | E12: - | F12: -1 | G12: - | H12: 234
A13: MI0019 - OIL SEAL 125 X 150 X 13 | B13: 30 | C13: - | D13: - | E13: - | F13: -1 | G13: - | H13: 29
A14: MI0021 - H24W05 | B14: 7 | C14: - | D14: - | E14: - | F14: - | G14: - | H14: 7
A15: MI00218 - HENDRED ROLLER BIG | B15: -109 | C15: - | D15: - | E15: - | F15: -12 | G15: - | H15: -121
A16: MI0027 - FILTER 8193841 WATER SEPERATOR | B16: -6 | C16: - | D16: - | E16: - | F16: - | G16: - | H16: -6
A17: MI0029 - BOLT WITH NUT SCANIA REAR | B17: 7 | C17: - | D17: - | E17: - | F17: - | G17: - | H17: 7
A18: MI0035 - 0683578 WATER PUMP DAF | B18: 3 | C18: - | D18: - | E18: - | F18: -1 | G18: - | H18: 2
A19: MI0043 - L2320 PRESSURE PLATE SCANIA | B19: 1 | C19: - | D19: - | E19: - | F19: - | G19: - | H19: 1
A20: MI0045 - 4801030160 VALVE BENZ | B20: 1 | C20: - | D20: - | E20: - | F20: - | G20: - | H20: 1
A21: MI0047 - RL3530EA23-E BRAKE BOOSTER 24/30 TRAILER | B21: 7 | C21: - | D21: - | E21: - | F21: -5 | G21: - | H21: 2
A22: MI0048 - HTP-NFH002R-R HEAD LAMP LENS RIGHT VOLVO | B22: 7 | C22: - | D22: - | E22: - | F22: - | G22: - | H22: 7
A23: MI0049 - HTP-NFH002R-L HEAD LAMP LENS LEFT VOLVO | B23: 7 | C23: - | D23: - | E23: - | F23: - | G23: - | H23: 7
A24: MI0052 - SV41 BRAKE LINING SCA | B24: 12 | C24: - | D24: - | E24: - | F24: - | G24: - | H24: 12
A25: MI0053 - SV42 BRAKE LINING SCANIA | B25: 89.75 | C25: - | D25: - | E25: - | F25: - | G25: - | H25: 89.75
A26: MI0054 - VL87 BRAKE LINING VOLVO | B26: 36 | C26: - | D26: - | E26: - | F26: -5.25 | G26: - | H26: 30.75
A27: MI0055 - VL88 BRAKE LINING VOLVO | B27: 107.5 | C27: - | D27: - | E27: - | F27: -5 | G27: - | H27: 102.5
A28: MI0056 - VL89 BRAKE LINING VOLVO | B28: 0.5 | C28: - | D28: - | E28: - | F28: - | G28: - | H28: 0.5
A29: MI0057 - BC37 BRAKE LINING BPW 8" | B29: 308 | C29: 468 | D29: - | E29: - | F29: -23 | G29: - | H29: 753
A30: MI0059 - RIVETING MACHINE | B30: 5 | C30: - | D30: - | E30: - | F30: - | G30: - | H30: 5
A31: MI0060 - W01M586364 AIRBAG 5813K | B31: 173 | C31: - | D31: - | E31: - | F31: -60 | G31: - | H31: 113
A32: MI0061 - WVA29124 BRAKE PAD ROR | B32: 1 | C32: - | D32: - | E32: - | F32: - | G32: - | H32: 1
A33: MI0064 - BRAKE SHOE BC36 | B33: 19 | C33: - | D33: - | E33: - | F33: -4 | G33: - | H33: 15
A34: MI0065 - 4515 BRAKE SHOE COMP OR HENDRED | B34: -49 | C34: - | D34: - | E34: - | F34: -2 | G34: - | H34: -51
A35: MI0066 - W01-M58-8966 | B35: 85 | C35: - | D35: - | E35: - | F35: -35 | G35: - | H35: 50
A36: MI0067 - HENDRED BRAKE SHOE SPRING LONG | B36: -176 | C36: - | D36: - | E36: - | F36: -29 | G36: - | H36: -205
A37: MI0068 - HENDRED BRAKE SHOE SPRING SHORT | B37: -278 | C37: - | D37: - | E37: - | F37: -79 | G37: - | H37: -357
A38: MI0069 - BRAKE SHOE ROLLER BPW | B38: -6 | C38: - | D38: - | E38: - | F38: - | G38: - | H38: -6
A39: MI0070 - BRAKE SHOE ROLLER LOCK | B39: -306 | C39: - | D39: - | E39: - | F39: - | G39: - | H39: -306
A40: MI0073 - 4707 BRAKE LINING | B40: 191.5 | C40: - | D40: - | E40: - | F40: -2 | G40: - | H40: 189.5
A41: MI0081 - W01M587074 AIRBAG | B41: 78 | C41: - | D41: - | E41: - | F41: -49 | G41: - | H41: 29
A42: MI0082 - MMCB BUS FRONT | B42: 38 | C42: - | D42: - | E42: - | F42: - | G42: - | H42: 38
A43: MI0083 - MMCB BUS REAR | B43: 4 | C43: - | D43: - | E43: - | F43: - | G43: - | H43: 4
A44: MI0084 - 315/80 R22.5 UNIVERSAL | B44: 3362 | C44: 890 | D44: - | E44: - | F44: -1383 | G44: 2 | H44: 2871
A45: MI0085 - 315/80 R22.5 20PR STEER | B45: 681 | C45: 235 | D45: - | E45: - | F45: -177 | G45: 1 | H45: 740
A46: MI0086 - 315/80 R22.5 20PR DIFF | B46: 920 | C46: 545 | D46: - | E46: - | F46: -427 | G46: 2 | H46: 1040
A47: MI0087 - 385/65 R22.5 20PR SUPER SINGLE | B47: 714 | C47: 635 | D47: - | E47: - | F47: -250 | G47: 2 | H47: 1101
A48: MI0088 - W01M58-9880 AIRBAG | B48: 6 | C48: - | D48: - | E48: - | F48: -2 | G48: - | H48: 4
A49: MI0089 - W01M58-8683 AIRBAG | B49: 6 | C49: - | D49: - | E49: - | F49: -3 | G49: - | H49: 3
A50: MI0091 - 32 x 33 WHEEL SPANNER | B50: 10 | C50: - | D50: - | E50: - | F50: -8 | G50: - | H50: 2
A51: MI0093 - HOWO 14 HOLE BRAKE LINING | B51: 0.25 | C51: - | D51: - | E51: - | F51: - | G51: - | H51: 0.25
A52: MI0094 - FAW REAR BRAKE LINING | B52: 104.375 | C52: - | D52: - | E52: - | F52: -18 | G52: - | H52: 86.375
A53: MI0095 - SUZY PIPE RED | B53: 123 | C53: 200 | D53: - | E53: - | F53: -60 | G53: 4 | H53: 267
A54: MI0096 - SUZY PIPE YELLOW | B54: 140 | C54: 200 | D54: - | E54: - | F54: -70 | G54: 8 | H54: 278
A55: MI0097 - BC37 BRAKE SHOE | B55: 15 | C55: - | D55: - | E55: - | F55: - | G55: - | H55: 15
A56: MI0099 - TRAILER SHOCK UP SHORT | B56: 34 | C56: - | D56: - | E56: - | F56: -1 | G56: - | H56: 33
A57: MI0102 - PRESSURE PLATE BENZ AXOR | B57: 1 | C57: - | D57: - | E57: - | F57: - | G57: - | H57: 1
A58: MI0103 - RL3519DA4 BRAKE BOOSTER SMALL | B58: 35 | C58: 1 | D58: - | E58: - | F58: -10 | G58: - | H58: 26
A59: MI0104 - 20744939 WATER PUMP VOLVO | B59: 4 | C59: - | D59: - | E59: - | F59: - | G59: - | H59: 4
A60: MI0105 - RELEASE BEARING SCANIA 113 | B60: 1 | C60: - | D60: - | E60: - | F60: - | G60: - | H60: 1
A61: MI0106 - TRAILER VALVE BSA | B61: 1 | C61: - | D61: - | E61: - | F61: - | G61: - | H61: 1
A62: MI0107 - CABIN PUMP | B62: 1 | C62: - | D62: - | E62: - | F62: - | G62: - | H62: 1
A63: MI0108 - AIR DRIER FILTER DAF | B63: 2 | C63: - | D63: - | E63: - | F63: - | G63: - | H63: 2
A64: MI0109 - 0022950706 | B64: 1 | C64: - | D64: - | E64: - | F64: - | G64: - | H64: 1
A65: MI0110 - M30X250 PIN LONG | B65: 165 | C65: - | D65: - | E65: - | F65: -4 | G65: - | H65: 161
A66: MI0111 - M30X200 PIN SHORT | B66: 263 | C66: - | D66: - | E66: - | F66: -112 | G66: - | H66: 151
A67: MI0112 - 070.063 BUSH SMALL | B67: 159 | C67: 400 | D67: - | E67: - | F67: -170 | G67: - | H67: 389
A68: MI0114 - CLUTCH PLATE SINO | B68: -1 | C68: - | D68: - | E68: - | F68: - | G68: - | H68: -1
A69: MI0115 - H701WK WATER FILTER BENZ | B69: 1 | C69: - | D69: - | E69: - | F69: - | G69: - | H69: 1
A70: MI0118 - W01M586251 | B70: 1 | C70: - | D70: - | E70: - | F70: -1 | G70: - | H70: -
A71: MI0119 - WVA29244 | B71: - | C71: - | D71: - | E71: - | F71: -1 | G71: - | H71: -1
A72: MI0120 - WVA29246 | B72: 30 | C72: - | D72: - | E72: - | F72: -1 | G72: - | H72: 29
A73: MI0121 - BRAKE LINING HOWO A+B | B73: 40.75 | C73: - | D73: - | E73: - | F73: - | G73: - | H73: 40.75
A74: MI0122 - W013589121 | B74: 118 | C74: - | D74: - | E74: - | F74: -13 | G74: - | H74: 105
A75: MI0126 - W01M589361 AIRBAG - 54156-15KPP | B75: 24 | C75: - | D75: - | E75: - | F75: -8 | G75: - | H75: 16
A76: MI0127 - FU/4/5/1 BRAKE LINING | B76: 121 | C76: 160 | D76: - | E76: - | F76: -5 | G76: - | H76: 276
A77: MI0128 - BC37XX BRAKE LINING | B77: 63.25 | C77: - | D77: - | E77: - | F77: - | G77: - | H77: 63.25
A78: MI0129 - TATA SM1 BRAKE LINING | B78: 5 | C78: - | D78: - | E78: - | F78: - | G78: - | H78: 5
A79: MI0131 - WVA4709 BRAKE LINING | B79: 7.75 | C79: - | D79: - | E79: - | F79: - | G79: - | H79: 7.75
A80: MI0132 - FAW 16 HOLE BRAKE LINING | B80: 147.75 | C80: 316 | D80: - | E80: - | F80: -50.5 | G80: - | H80: 413.25
A81: MI0136 - WVA29162 | B81: 3 | C81: - | D81: - | E81: - | F81: -1 | G81: - | H81: 2
A82: MI0137 - WVA29125 | B82: 15 | C82: - | D82: - | E82: - | F82: - | G82: - | H82: 15
A83: MI0138 - WVA29177 | B83: 60 | C83: - | D83: - | E83: - | F83: -5 | G83: - | H83: 55
A84: MI0139 - 1878002732 | B84: 1 | C84: - | D84: - | E84: - | F84: - | G84: - | H84: 1
A85: MI0141 - 1878063231 | B85: 2 | C85: - | D85: - | E85: - | F85: - | G85: - | H85: 2
A86: MI0142 - W01M588609-5940K | B86: 82 | C86: - | D86: - | E86: - | F86: -31 | G86: - | H86: 51
A87: MI0143 - W01M588535 | B87: 1 | C87: - | D87: - | E87: - | F87: - | G87: - | H87: 1
A88: MI0144 - W01M586297/54157-04KPP | B88: 7 | C88: - | D88: - | E88: - | F88: - | G88: - | H88: 7
A89: MI0149 - 1421186 | B89: 1 | C89: - | D89: - | E89: - | F89: - | G89: - | H89: 1
A90: MI0151 - 1479576 RELEASE BEARING SCANIA R420 | B90: 2 | C90: - | D90: - | E90: - | F90: - | G90: - | H90: 2
A91: MI0154 - 033488501 | B91: 1 | C91: - | D91: - | E91: - | F91: - | G91: - | H91: 1
A92: MI0155 - 360200004 RH | B92: 34 | C92: - | D92: - | E92: - | F92: -2 | G92: - | H92: 32
A93: MI0156 - 360200005 LH | B93: 1 | C93: - | D93: - | E93: - | F93: - | G93: - | H93: 1
A94: MI0158 - W02M588009-FRONT | B94: 1 | C94: - | D94: - | E94: - | F94: - | G94: - | H94: 1
A95: MI0159 - W02M588007-REAR | B95: 6 | C95: - | D95: - | E95: - | F95: - | G95: - | H95: 6
A96: MI0162 - 21707133 | B96: 17 | C96: - | D96: - | E96: - | F96: -14 | G96: - | H96: 3
A97: MI0163 - 20976003 | B97: 3 | C97: - | D97: - | E97: - | F97: - | G97: - | H97: 3
A98: MI0165 - H200W02 | B98: 3 | C98: - | D98: - | E98: - | F98: - | G98: - | H98: 3
A99: MI0167 - 21707132 | B99: 234 | C99: - | D99: - | E99: - | F99: -1 | G99: - | H99: 233
A100: MI0168 - E500KP02D36 | B100: 1 | C100: - | D100: - | E100: - | F100: - | G100: - | H100: 1
...

Sheet OCT25
A1: 1st oct 2025 to 31 oct 2025 | B1: Opening balance | C1: Purchases | D1: Inventory Write-offs | E1: Sales | F1: Credit Note | G1: Closing balance
A2: MI0001 - 4515-Wx Hendred Brake Lining | B2: 1392.38 | C2: - | D2: - | E2: -331.25 | F2: - | G2: 1061.13
A3: MI0002 - MP31 | B3: 0.25 | C3: - | D3: - | E3: - | F3: - | G3: 0.25
A4: MI0003 - MP32 | B4: 76.75 | C4: - | D4: - | E4: -8.5 | F4: - | G4: 68.25
A5: MI0004 - MP36 | B5: 78 | C5: 4.5 | D5: - | E5: -11 | F5: - | G5: 71.5
A6: MI0005 - BC36 | B6: 235.125 | C6: - | D6: - | E6: -45.5 | F6: - | G6: 189.625
A7: MI0008 - 996075-K AIRBAG VOLVO O/M 1076076 | B7: 2 | C7: - | D7: - | E7: - | F7: - | G7: 2
A8: MI0009 - 994713-K AIRBAG VOLVO O/M 1076595 | B8: 5 | C8: - | D8: - | E8: - | F8: - | G8: 5
A9: MI0010 - 994913-K AIRBAG SCA 124 DIFF / 9881 | B9: 6 | C9: 1 | D9: - | E9: -3 | F9: - | G9: 4
A10: MI0011 - 999780-K AIRBAG FREIGHTLINER METAL | B10: 29 | C10: - | D10: - | E10: -1 | F10: - | G10: 28
A11: MI0013 - 994183-24K AIRBAG BENZ | B11: -14 | C11: - | D11: - | E11: - | F11: - | G11: -14
A12: MI0018 - BPW SPRING LONG | B12: 234 | C12: 200 | D12: - | E12: -7 | F12: - | G12: 427
A13: MI0019 - OIL SEAL 125 X 150 X 13 | B13: 29 | C13: - | D13: - | E13: -6 | F13: - | G13: 23
A14: MI0021 - H24W05 | B14: 7 | C14: - | D14: - | E14: - | F14: - | G14: 7
A15: MI00218 - HENDRED ROLLER BIG | B15: -121 | C15: - | D15: - | E15: -31 | F15: - | G15: -152
A16: MI0027 - FILTER 8193841 WATER SEPERATOR | B16: -6 | C16: - | D16: - | E16: - | F16: - | G16: -6
A17: MI0029 - BOLT WITH NUT SCANIA REAR | B17: 7 | C17: - | D17: - | E17: - | F17: - | G17: 7
A18: MI0035 - 0683578 WATER PUMP DAF | B18: 2 | C18: - | D18: - | E18: - | F18: - | G18: 2
A19: MI0043 - L2320 PRESSURE PLATE SCANIA | B19: 1 | C19: - | D19: - | E19: - | F19: - | G19: 1
A20: MI0045 - 4801030160 VALVE BENZ | B20: 1 | C20: - | D20: - | E20: - | F20: - | G20: 1
A21: MI0047 - RL3530EA23-E BRAKE BOOSTER 24/30 TRAILER | B21: 2 | C21: 120 | D21: -1 | E21: -121 | F21: 1 | G21: 1
A22: MI0048 - HTP-NFH002R-R HEAD LAMP LENS RIGHT VOLVO | B22: 7 | C22: - | D22: - | E22: - | F22: - | G22: 7
A23: MI0049 - HTP-NFH002R-L HEAD LAMP LENS LEFT VOLVO | B23: 7 | C23: - | D23: - | E23: - | F23: - | G23: 7
A24: MI0052 - SV41 BRAKE LINING SCA | B24: 12 | C24: - | D24: - | E24: - | F24: - | G24: 12
A25: MI0053 - SV42 BRAKE LINING SCANIA | B25: 89.75 | C25: - | D25: - | E25: - | F25: - | G25: 89.75
A26: MI0054 - VL87 BRAKE LINING VOLVO | B26: 30.75 | C26: - | D26: - | E26: -4 | F26: - | G26: 26.75
A27: MI0055 - VL88 BRAKE LINING VOLVO | B27: 102.5 | C27: - | D27: - | E27: -4 | F27: - | G27: 98.5
A28: MI0056 - VL89 BRAKE LINING VOLVO | B28: 0.5 | C28: - | D28: - | E28: - | F28: - | G28: 0.5
A29: MI0057 - BC37 BRAKE LINING BPW 8" | B29: 753 | C29: - | D29: - | E29: -125.5 | F29: - | G29: 627.5
A30: MI0059 - RIVETING MACHINE | B30: 5 | C30: - | D30: - | E30: - | F30: - | G30: 5
A31: MI0060 - W01M586364 AIRBAG 5813K | B31: 113 | C31: 8 | D31: - | E31: -24 | F31: - | G31: 97
A32: MI0061 - WVA29124 BRAKE PAD ROR | B32: 1 | C32: - | D32: - | E32: - | F32: - | G32: 1
A33: MI0064 - BRAKE SHOE BC36 | B33: 15 | C33: 36 | D33: - | E33: -2 | F33: - | G33: 49
A34: MI0065 - 4515 BRAKE SHOE COMP OR HENDRED | B34: -51 | C34: 150 | D34: - | E34: -34 | F34: - | G34: 65
A35: MI0066 - W01-M58-8966 | B35: 50 | C35: 15 | D35: - | E35: -38 | F35: - | G35: 27
A36: MI0067 - HENDRED BRAKE SHOE SPRING LONG | B36: -205 | C36: 500 | D36: - | E36: -8 | F36: - | G36: 287
A37: MI0068 - HENDRED BRAKE SHOE SPRING SHORT | B37: -357 | C37: 1000 | D37: - | E37: -93 | F37: - | G37: 550
A38: MI0069 - BRAKE SHOE ROLLER BPW | B38: -6 | C38: - | D38: - | E38: - | F38: - | G38: -6
A39: MI0070 - BRAKE SHOE ROLLER LOCK | B39: -306 | C39: - | D39: - | E39: - | F39: - | G39: -306
A40: MI0073 - 4707 BRAKE LINING | B40: 189.5 | C40: - | D40: - | E40: -3 | F40: - | G40: 186.5
A41: MI0081 - W01M587074 AIRBAG | B41: 29 | C41: 10 | D41: - | E41: -20 | F41: - | G41: 19
A42: MI0082 - MMCB BUS FRONT | B42: 38 | C42: - | D42: - | E42: - | F42: - | G42: 38
A43: MI0083 - MMCB BUS REAR | B43: 4 | C43: - | D43: - | E43: - | F43: - | G43: 4
A44: MI0084 - 315/80 R22.5 UNIVERSAL | B44: 2871 | C44: - | D44: -1 | E44: -1392 | F44: - | G44: 1478
A45: MI0085 - 315/80 R22.5 20PR STEER | B45: 740 | C45: - | D45: - | E45: -296 | F45: - | G45: 444
A46: MI0086 - 315/80 R22.5 20PR DIFF | B46: 1040 | C46: - | D46: - | E46: -709 | F46: - | G46: 331
A47: MI0087 - 385/65 R22.5 20PR SUPER SINGLE | B47: 1101 | C47: 50 | D47: - | E47: -445 | F47: - | G47: 706
A48: MI0088 - W01M58-9880 AIRBAG | B48: 4 | C48: - | D48: - | E48: - | F48: - | G48: 4
A49: MI0089 - W01M58-8683 AIRBAG | B49: 2 | C49: - | D49: - | E49: -1 | F49: - | G49: 1
A50: MI0091 - 32 x 33 WHEEL SPANNER | B50: 2 | C50: - | D50: - | E50: -2 | F50: - | G50: -
A51: MI0093 - HOWO 14 HOLE BRAKE LINING | B51: 0.25 | C51: - | D51: - | E51: - | F51: - | G51: 0.25
A52: MI0094 - FAW REAR BRAKE LINING | B52: 86.375 | C52: - | D52: - | E52: -38.5 | F52: - | G52: 47.875
A53: MI0095 - SUZY PIPE RED | B53: 267 | C53: - | D53: - | E53: -88 | F53: - | G53: 179
A54: MI0096 - SUZY PIPE YELLOW | B54: 278 | C54: - | D54: - | E54: -76 | F54: - | G54: 202
A55: MI0097 - BC37 BRAKE SHOE | B55: 15 | C55: 36 | D55: - | E55: -24 | F55: - | G55: 27
A56: MI0099 - TRAILER SHOCK UP SHORT | B56: 33 | C56: - | D56: - | E56: -13 | F56: - | G56: 20
A57: MI0102 - PRESSURE PLATE BENZ AXOR | B57: 1 | C57: - | D57: - | E57: - | F57: - | G57: 1
A58: MI0103 - RL3519DA4 BRAKE BOOSTER SMALL | B58: 26 | C58: 50 | D58: - | E58: -17 | F58: - | G58: 59
A59: MI0104 - 20744939 WATER PUMP VOLVO | B59: 4 | C59: - | D59: - | E59: - | F59: - | G59: 4
A60: MI0105 - RELEASE BEARING SCANIA 113 | B60: 1 | C60: - | D60: - | E60: - | F60: - | G60: 1
A61: MI0106 - TRAILER VALVE BSA | B61: 1 | C61: - | D61: - | E61: - | F61: - | G61: 1
A62: MI0107 - CABIN PUMP | B62: 1 | C62: - | D62: - | E62: - | F62: - | G62: 1
A63: MI0108 - AIR DRIER FILTER DAF | B63: 2 | C63: - | D63: - | E63: - | F63: - | G63: 2
A64: MI0109 - 0022950706 | B64: 1 | C64: - | D64: - | E64: - | F64: - | G64: 1
A65: MI0110 - M30X250 PIN LONG | B65: 161 | C65: - | D65: - | E65: -11 | F65: - | G65: 150
A66: MI0111 - M30X200 PIN SHORT | B66: 151 | C66: 200 | D66: - | E66: -117 | F66: - | G66: 234
A67: MI0112 - 070.063 BUSH SMALL | B67: 389 | C67: - | D67: - | E67: -107 | F67: - | G67: 282
A68: MI0114 - CLUTCH PLATE SINO | B68: -1 | C68: - | D68: - | E68: - | F68: - | G68: -1
A69: MI0115 - H701WK WATER FILTER BENZ | B69: 1 | C69: - | D69: - | E69: - | F69: - | G69: 1
A70: MI0119 - WVA29244 | B70: -1 | C70: - | D70: - | E70: - | F70: - | G70: -1
A71: MI0120 - WVA29246 | B71: 29 | C71: 1 | D71: - | E71: - | F71: - | G71: 30
A72: MI0121 - BRAKE LINING HOWO A+B | B72: 40.75 | C72: - | D72: - | E72: -1.5 | F72: - | G72: 39.25
A73: MI0122 - W013589121 | B73: 105 | C73: - | D73: - | E73: -20 | F73: - | G73: 85
A74: MI0126 - W01M589361 AIRBAG - 54156-15KPP | B74: 16 | C74: - | D74: - | E74: -4 | F74: - | G74: 12
A75: MI0127 - FU/4/5/1 BRAKE LINING | B75: 276 | C75: - | D75: - | E75: -6.5 | F75: - | G75: 269.5
A76: MI0128 - BC37XX BRAKE LINING | B76: 63.25 | C76: - | D76: - | E76: - | F76: - | G76: 63.25
A77: MI0129 - TATA SM1 BRAKE LINING | B77: 5 | C77: - | D77: - | E77: - | F77: - | G77: 5
A78: MI0131 - WVA4709 BRAKE LINING | B78: 7.75 | C78: - | D78: - | E78: - | F78: - | G78: 7.75
A79: MI0132 - FAW 16 HOLE BRAKE LINING | B79: 413.25 | C79: - | D79: -2 | E79: -62.5 | F79: - | G79: 348.75
A80: MI0136 - WVA29162 | B80: 2 | C80: - | D80: - | E80: - | F80: - | G80: 2
A81: MI0137 - WVA29125 | B81: 15 | C81: - | D81: - | E81: - | F81: - | G81: 15
A82: MI0138 - WVA29177 | B82: 55 | C82: - | D82: - | E82: -16 | F82: - | G82: 39
A83: MI0139 - 1878002732 | B83: 1 | C83: - | D83: - | E83: - | F83: - | G83: 1
A84: MI0141 - 1878063231 | B84: 2 | C84: - | D84: - | E84: - | F84: - | G84: 2
A85: MI0142 - W01M588609-5940K | B85: 51 | C85: - | D85: - | E85: -50 | F85: - | G85: 1
A86: MI0143 - W01M588535 | B86: 1 | C86: - | D86: - | E86: - | F86: - | G86: 1
A87: MI0144 - W01M586297/54157-04KPP | B87: 7 | C87: 15 | D87: -1 | E87: -1 | F87: - | G87: 20
A88: MI0149 - 1421186 | B88: 1 | C88: - | D88: - | E88: - | F88: - | G88: 1
A89: MI0151 - 1479576 RELEASE BEARING SCANIA R420 | B89: 2 | C89: - | D89: - | E89: - | F89: - | G89: 2
A90: MI0154 - 033488501 | B90: 1 | C90: - | D90: - | E90: - | F90: - | G90: 1
A91: MI0155 - 360200004 RH | B91: 32 | C91: - | D91: - | E91: - | F91: - | G91: 32
A92: MI0156 - 360200005 LH | B92: 1 | C92: - | D92: - | E92: - | F92: - | G92: 1
A93: MI0158 - W02M588009-FRONT | B93: 1 | C93: - | D93: - | E93: -2 | F93: - | G93: -1
A94: MI0159 - W02M588007-REAR | B94: 6 | C94: - | D94: - | E94: - | F94: - | G94: 6
A95: MI0162 - 21707133 | B95: 3 | C95: - | D95: - | E95: - | F95: - | G95: 3
A96: MI0163 - 20976003 | B96: 3 | C96: - | D96: - | E96: - | F96: - | G96: 3
A97: MI0165 - H200W02 | B97: 3 | C97: - | D97: - | E97: - | F97: - | G97: 3
A98: MI0167 - 21707132 | B98: 233 | C98: - | D98: - | E98: - | F98: - | G98: 233
A99: MI0168 - E500KP02D36 | B99: 1 | C99: - | D99: - | E99: - | F99: - | G99: 1
A100: MI0169 - E175HD129 | B100: 7 | C100: - | D100: - | E100: - | F100: - | G100: 7
...

Sheet NOV25
C1: Opening balance | D1: Purchases | E1: Inventory Write-offs | F1: Sales | G1: Credit Note | H1: Journal Entries | I1: Closing balance
A2: 0 | B2: MI0001 - 4515-Wx Hendred Brake Lining | C2: 1061.125 | D2: - | E2: -0.25 | F2: -234.75 | G2: 12 | H2: - | I2: 838.125
A3: 0 | B3: MI0002 - MP31 | C3: 0.25 | D3: - | E3: - | F3: - | G3: - | H3: - | I3: 0.25
A4: 0 | B4: MI0003 - MP32 | C4: 68.25 | D4: - | E4: - | F4: -10.5 | G4: - | H4: - | I4: 57.75
A5: 0 | B5: MI0004 - MP36 | C5: 71.5 | D5: 3.125 | E5: - | F5: -13 | G5: - | H5: - | I5: 61.625
A6: 0 | B6: MI0005 - BC36 | C6: 189.625 | D6: - | E6: -0.25 | F6: -58.75 | G6: - | H6: - | I6: 130.625
A7: 0 | B7: MI0008 - 996075-K AIRBAG VOLVO O/M 1076076 | C7: 2 | D7: - | E7: - | F7: - | G7: - | H7: - | I7: 2
A8: 0 | B8: MI0009 - 994713-K AIRBAG VOLVO O/M 1076595 | C8: 5 | D8: - | E8: - | F8: - | G8: - | H8: - | I8: 5
A9: 0 | B9: MI0010 - 994913-K AIRBAG SCA 124 DIFF / 9881 | C9: 4 | D9: - | E9: - | F9: -3 | G9: - | H9: - | I9: 1
A10: 0 | B10: MI0011 - 999780-K AIRBAG FREIGHTLINER METAL | C10: 28 | D10: 50 | E10: - | F10: -8 | G10: - | H10: - | I10: 70
A11: 0 | B11: MI0013 - 994183-24K AIRBAG BENZ | C11: -14 | D11: - | E11: - | F11: - | G11: - | H11: - | I11: -14
A12: 0 | B12: MI0018 - BPW SPRING LONG | C12: 427 | D12: - | E12: - | F12: -26 | G12: - | H12: - | I12: 401
A13: 0 | B13: MI0019 - OIL SEAL 125 X 150 X 13 | C13: 23 | D13: - | E13: - | F13: - | G13: - | H13: - | I13: 23
A14: 0 | B14: MI0021 - H24W05 | C14: 7 | D14: - | E14: - | F14: - | G14: - | H14: - | I14: 7
A15: 0 | B15: MI00218 - HENDRED ROLLER BIG | C15: -152 | D15: - | E15: - | F15: - | G15: - | H15: - | I15: -152
A16: 0 | B16: MI0027 - FILTER 8193841 WATER SEPERATOR | C16: -6 | D16: - | E16: - | F16: - | G16: - | H16: - | I16: -6
A17: 0 | B17: MI0029 - BOLT WITH NUT SCANIA REAR | C17: 7 | D17: - | E17: - | F17: - | G17: - | H17: - | I17: 7
A18: 0 | B18: MI0035 - 0683578 WATER PUMP DAF | C18: 2 | D18: - | E18: - | F18: - | G18: - | H18: - | I18: 2
A19: 0 | B19: MI0043 - L2320 PRESSURE PLATE SCANIA | C19: 1 | D19: - | E19: - | F19: - | G19: - | H19: - | I19: 1
A20: 0 | B20: MI0045 - 4801030160 VALVE BENZ | C20: 1 | D20: - | E20: - | F20: - | G20: - | H20: - | I20: 1
A21: 0 | B21: MI0047 - RL3530EA23-E BRAKE BOOSTER 24/30 TRAILER | C21: 1 | D21: 300 | E21: - | F21: -34 | G21: 8 | H21: - | I21: 275
A22: 0 | B22: MI0048 - HTP-NFH002R-R HEAD LAMP LENS RIGHT VOLVO | C22: 7 | D22: - | E22: - | F22: - | G22: - | H22: - | I22: 7
A23: 0 | B23: MI0049 - HTP-NFH002R-L HEAD LAMP LENS LEFT VOLVO | C23: 7 | D23: - | E23: - | F23: - | G23: - | H23: - | I23: 7
A24: 0 | B24: MI0052 - SV41 BRAKE LINING SCA | C24: 12 | D24: - | E24: - | F24: - | G24: - | H24: - | I24: 12
A25: 0 | B25: MI0053 - SV42 BRAKE LINING SCANIA | C25: 89.75 | D25: - | E25: - | F25: - | G25: - | H25: - | I25: 89.75
A26: 0 | B26: MI0054 - VL87 BRAKE LINING VOLVO | C26: 26.75 | D26: - | E26: - | F26: -3.75 | G26: - | H26: - | I26: 23
A27: 0 | B27: MI0055 - VL88 BRAKE LINING VOLVO | C27: 98.5 | D27: - | E27: - | F27: -11.5 | G27: - | H27: - | I27: 87
A28: 0 | B28: MI0056 - VL89 BRAKE LINING VOLVO | C28: 0.5 | D28: - | E28: - | F28: - | G28: - | H28: - | I28: 0.5
A29: 0 | B29: MI0057 - BC37 BRAKE LINING BPW 8" | C29: 627.5 | D29: - | E29: - | F29: -58.25 | G29: - | H29: - | I29: 569.25
A30: 0 | B30: MI0059 - RIVETING MACHINE | C30: 5 | D30: - | E30: - | F30: - | G30: - | H30: - | I30: 5
A31: 0 | B31: MI0060 - W01M586364 AIRBAG 5813K | C31: 97 | D31: 180 | E31: - | F31: -24 | G31: 3 | H31: - | I31: 256
A32: 0 | B32: MI0061 - WVA29124 BRAKE PAD ROR | C32: 1 | D32: - | E32: - | F32: - | G32: - | H32: - | I32: 1
A33: 0 | B33: MI0064 - BRAKE SHOE BC36 | C33: 49 | D33: - | E33: - | F33: -1 | G33: - | H33: - | I33: 48
A34: 0 | B34: MI0065 - 4515 BRAKE SHOE COMP OR HENDRED | C34: 65 | D34: 51 | E34: - | F34: -49 | G34: 10 | H34: - | I34: 77
A35: 0 | B35: MI0066 - W01-M58-8966 | C35: 27 | D35: 120 | E35: - | F35: -33 | G35: - | H35: - | I35: 114
A36: 0 | B36: MI0067 - HENDRED BRAKE SHOE SPRING LONG | C36: 287 | D36: 400 | E36: - | F36: -65 | G36: - | H36: - | I36: 622
A37: 0 | B37: MI0068 - HENDRED BRAKE SHOE SPRING SHORT | C37: 550 | D37: 500 | E37: - | F37: -106 | G37: - | H37: - | I37: 944
A38: 0 | B38: MI0069 - BRAKE SHOE ROLLER BPW | C38: -6 | D38: - | E38: - | F38: - | G38: - | H38: - | I38: -6
A39: 0 | B39: MI0070 - BRAKE SHOE ROLLER LOCK | C39: -306 | D39: - | E39: - | F39: -8 | G39: - | H39: - | I39: -314
A40: 0 | B40: MI0073 - 4707 BRAKE LINING | C40: 186.5 | D40: - | E40: - | F40: -7.25 | G40: - | H40: - | I40: 179.25
A41: 0 | B41: MI0081 - W01M587074 AIRBAG | C41: 19 | D41: 20 | E41: - | F41: -17 | G41: 4 | H41: - | I41: 26
A42: 0 | B42: MI0082 - MMCB BUS FRONT | C42: 38 | D42: - | E42: - | F42: - | G42: - | H42: - | I42: 38
A43: 0 | B43: MI0083 - MMCB BUS REAR | C43: 4 | D43: - | E43: - | F43: - | G43: - | H43: - | I43: 4
A44: 0 | B44: MI0084 - 315/80 R22.5 UNIVERSAL | C44: 1478 | D44: 265 | E44: - | F44: -1181 | G44: - | H44: - | I44: 562
A45: 0 | B45: MI0085 - 315/80 R22.5 20PR STEER | C45: 444 | D45: - | E45: - | F45: -274 | G45: - | H45: - | I45: 170
A46: 0 | B46: MI0086 - 315/80 R22.5 20PR DIFF | C46: 331 | D46: - | E46: - | F46: -295 | G46: - | H46: - | I46: 36
A47: 0 | B47: MI0087 - 385/65 R22.5 20PR SUPER SINGLE | C47: 706 | D47: - | E47: - | F47: -293 | G47: - | H47: - | I47: 413
A48: 0 | B48: MI0088 - W01M58-9880 AIRBAG | C48: 4 | D48: - | E48: - | F48: -1 | G48: - | H48: - | I48: 3
A49: 0 | B49: MI0089 - W01M58-8683 AIRBAG | C49: 1 | D49: - | E49: - | F49: - | G49: - | H49: - | I49: 1
A50: 0 | B50: MI0091 - 32 x 33 WHEEL SPANNER | C50: - | D50: 30 | E50: - | F50: - | G50: - | H50: - | I50: 30
A51: 0 | B51: MI0093 - HOWO 14 HOLE BRAKE LINING | C51: 0.25 | D51: - | E51: - | F51: - | G51: - | H51: - | I51: 0.25
A52: 0 | B52: MI0094 - FAW REAR BRAKE LINING | C52: 47.875 | D52: - | E52: - | F52: -15 | G52: 4 | H52: - | I52: 36.875
A53: 0 | B53: MI0095 - SUZY PIPE RED | C53: 179 | D53: - | E53: - | F53: -77 | G53: 6 | H53: - | I53: 108
A54: 0 | B54: MI0096 - SUZY PIPE YELLOW | C54: 202 | D54: - | E54: - | F54: -76 | G54: 6 | H54: - | I54: 132
A55: 0 | B55: MI0097 - BC37 BRAKE SHOE | C55: 27 | D55: - | E55: - | F55: -2 | G55: - | H55: - | I55: 25
A56: 0 | B56: MI0099 - TRAILER SHOCK UP SHORT | C56: 20 | D56: 40 | E56: - | F56: - | G56: - | H56: - | I56: 60
A57: 0 | B57: MI0102 - PRESSURE PLATE BENZ AXOR | C57: 1 | D57: - | E57: - | F57: - | G57: - | H57: - | I57: 1
A58: 0 | B58: MI0103 - RL3519DA4 BRAKE BOOSTER SMALL | C58: 59 | D58: - | E58: - | F58: -24 | G58: - | H58: - | I58: 35
A59: 0 | B59: MI0104 - 20744939 WATER PUMP VOLVO | C59: 4 | D59: - | E59: - | F59: - | G59: - | H59: - | I59: 4
A60: 0 | B60: MI0105 - RELEASE BEARING SCANIA 113 | C60: 1 | D60: - | E60: - | F60: - | G60: - | H60: - | I60: 1
A61: 0 | B61: MI0106 - TRAILER VALVE BSA | C61: 1 | D61: - | E61: - | F61: - | G61: - | H61: - | I61: 1
A62: 0 | B62: MI0107 - CABIN PUMP | C62: 1 | D62: - | E62: - | F62: - | G62: - | H62: - | I62: 1
A63: 0 | B63: MI0108 - AIR DRIER FILTER DAF | C63: 2 | D63: - | E63: - | F63: - | G63: - | H63: - | I63: 2
A64: 0 | B64: MI0109 - 0022950706 | C64: 1 | D64: - | E64: - | F64: - | G64: - | H64: - | I64: 1
A65: 0 | B65: MI0110 - M30X250 PIN LONG | C65: 150 | D65: - | E65: - | F65: -32 | G65: - | H65: - | I65: 118
A66: 0 | B66: MI0111 - M30X200 PIN SHORT | C66: 234 | D66: - | E66: - | F66: -76 | G66: 12 | H66: - | I66: 170
A67: 0 | B67: MI0112 - 070.063 BUSH SMALL | C67: 282 | D67: 240 | E67: - | F67: -122 | G67: 7 | H67: - | I67: 407
A68: 0 | B68: MI0114 - CLUTCH PLATE SINO | C68: -1 | D68: 10 | E68: - | F68: -2 | G68: - | H68: - | I68: 7
A69: 0 | B69: MI0115 - H701WK WATER FILTER BENZ | C69: 1 | D69: - | E69: - | F69: - | G69: - | H69: - | I69: 1
A70: 0 | B70: MI0119 - WVA29244 | C70: -1 | D70: - | E70: - | F70: - | G70: - | H70: - | I70: -1
A71: 0 | B71: MI0120 - WVA29246 | C71: 30 | D71: - | E71: - | F71: - | G71: - | H71: - | I71: 30
A72: 0 | B72: MI0121 - BRAKE LINING HOWO A+B | C72: 39.25 | D72: - | E72: - | F72: -1 | G72: - | H72: - | I72: 38.25
A73: 0 | B73: MI0122 - W013589121 | C73: 85 | D73: 50 | E73: - | F73: -38 | G73: - | H73: - | I73: 97
A74: 0 | B74: MI0126 - W01M589361 AIRBAG - 54156-15KPP | C74: 12 | D74: - | E74: - | F74: -4 | G74: - | H74: - | I74: 8
A75: 0 | B75: MI0127 - FU/4/5/1 BRAKE LINING | C75: 269.5 | D75: - | E75: - | F75: -5 | G75: - | H75: - | I75: 264.5
A76: 0 | B76: MI0128 - BC37XX BRAKE LINING | C76: 63.25 | D76: - | E76: - | F76: - | G76: 16 | H76: - | I76: 79.25
A77: 0 | B77: MI0129 - TATA SM1 BRAKE LINING | C77: 5 | D77: - | E77: - | F77: - | G77: - | H77: - | I77: 5
A78: 0 | B78: MI0131 - WVA4709 BRAKE LINING | C78: 7.75 | D78: - | E78: - | F78: - | G78: - | H78: - | I78: 7.75
A79: 0 | B79: MI0132 - FAW 16 HOLE BRAKE LINING | C79: 348.75 | D79: - | E79: - | F79: -37.5 | G79: 4 | H79: - | I79: 315.25
A80: 0 | B80: MI0136 - WVA29162 | C80: 2 | D80: - | E80: - | F80: - | G80: - | H80: - | I80: 2
A81: 0 | B81: MI0137 - WVA29125 | C81: 15 | D81: - | E81: - | F81: - | G81: - | H81: - | I81: 15
A82: 0 | B82: MI0138 - WVA29177 | C82: 39 | D82: - | E82: - | F82: -18 | G82: - | H82: - | I82: 21
A83: 0 | B83: MI0139 - 1878002732 | C83: 1 | D83: - | E83: - | F83: - | G83: - | H83: - | I83: 1
A84: 0 | B84: MI0141 - 1878063231 | C84: 2 | D84: - | E84: - | F84: - | G84: - | H84: - | I84: 2
A85: 0 | B85: MI0142 - W01M588609-5940K | C85: 1 | D85: 100 | E85: - | F85: -41 | G85: - | H85: - | I85: 60
A86: 0 | B86: MI0143 - W01M588535 | C86: 1 | D86: - | E86: - | F86: - | G86: - | H86: - | I86: 1
A87: 0 | B87: MI0144 - W01M586297/54157-04KPP | C87: 20 | D87: 40 | E87: - | F87: -7 | G87: - | H87: - | I87: 53
A88: 0 | B88: MI0149 - 1421186 | C88: 1 | D88: - | E88: - | F88: - | G88: - | H88: - | I88: 1
A89: 0 | B89: MI0151 - 1479576 RELEASE BEARING SCANIA R420 | C89: 2 | D89: - | E89: - | F89: - | G89: - | H89: - | I89: 2
A90: 0 | B90: MI0154 - 033488501 | C90: 1 | D90: - | E90: - | F90: - | G90: - | H90: - | I90: 1
A91: 0 | B91: MI0155 - 360200004 RH | C91: 32 | D91: - | E91: - | F91: - | G91: - | H91: - | I91: 32
A92: AALMAX | B92: MI0156 - 360200005 LH | C92: 1 | D92: - | E92: - | F92: - | G92: - | H92: - | I92: 1
A93: AALMAX | B93: MI0158 - W02M588009-FRONT | C93: -1 | D93: - | E93: - | F93: - | G93: - | H93: - | I93: -1
A94: AALMAX | B94: MI0159 - W02M588007-REAR | C94: 6 | D94: - | E94: - | F94: - | G94: - | H94: - | I94: 6
A95: AALMAX | B95: MI0162 - 21707133 | C95: 3 | D95: - | E95: - | F95: - | G95: - | H95: - | I95: 3
A96: AALMAX | B96: MI0163 - 20976003 | C96: 3 | D96: - | E96: - | F96: - | G96: - | H96: - | I96: 3
A97: AIRBAGS | B97: MI0165 - H200W02 | C97: 3 | D97: - | E97: - | F97: - | G97: - | H97: - | I97: 3
A98: AIRBAGS | B98: MI0167 - 21707132 | C98: 233 | D98: - | E98: - | F98: - | G98: - | H98: - | I98: 233
A99: AIRBAGS | B99: MI0168 - E500KP02D36 | C99: 1 | D99: - | E99: - | F99: - | G99: - | H99: - | I99: 1
A100: AIRBAGS | B100: MI0169 - E175HD129 | C100: 7 | D100: - | E100: - | F100: - | G100: - | H100: - | I100: 7
...

Sheet DEC25
B1: Opening balance | C1: Purchases | D1: Inventory Write-offs | E1: Sales | F1: Credit Note | G1: Journal Entries | H1: Closing balance
A2: MI0001 - 4515-Wx Hendred Brake Lining | B2: 838.125 | C2: 1360 | D2: - | E2: -256 | F2: 4.5 | G2: - | H2: 1946.63
A3: MI0002 - MP31 | B3: 0.25 | C3: - | D3: - | E3: - | F3: - | G3: - | H3: 0.25
A4: MI0003 - MP32 | B4: 57.75 | C4: - | D4: - | E4: -8 | F4: - | G4: - | H4: 49.75
A5: MI0004 - MP36 | B5: 61.625 | C5: 1.5 | D5: - | E5: -7.5 | F5: - | G5: - | H5: 55.625
A6: MI0005 - BC36 | B6: 130.625 | C6: - | D6: - | E6: -25.5 | F6: - | G6: - | H6: 105.125
A7: MI0008 - 996075-K AIRBAG VOLVO O/M 1076076 | B7: 2 | C7: - | D7: - | E7: - | F7: - | G7: - | H7: 2
A8: MI0009 - 994713-K AIRBAG VOLVO O/M 1076595 | B8: 5 | C8: - | D8: - | E8: - | F8: - | G8: - | H8: 5
A9: MI0010 - 994913-K AIRBAG SCA 124 DIFF / 9881 | B9: 1 | C9: 5 | D9: - | E9: -2 | F9: - | G9: - | H9: 4
A10: MI0011 - 999780-K AIRBAG FREIGHTLINER METAL | B10: 70 | C10: - | D10: - | E10: -5 | F10: - | G10: - | H10: 65
A11: MI0013 - 994183-24K AIRBAG BENZ | B11: -14 | C11: - | D11: - | E11: - | F11: - | G11: - | H11: -14
A12: MI0018 - BPW SPRING LONG | B12: 401 | C12: - | D12: - | E12: -5 | F12: - | G12: - | H12: 396
A13: MI0019 - OIL SEAL 125 X 150 X 13 | B13: 23 | C13: - | D13: - | E13: -1 | F13: - | G13: - | H13: 22
A14: MI0021 - H24W05 | B14: 7 | C14: - | D14: - | E14: - | F14: - | G14: - | H14: 7
A15: MI00218 - HENDRED ROLLER BIG | B15: -152 | C15: - | D15: - | E15: -8 | F15: - | G15: - | H15: -160
A16: MI0027 - FILTER 8193841 WATER SEPERATOR | B16: -6 | C16: - | D16: - | E16: - | F16: - | G16: - | H16: -6
A17: MI0029 - BOLT WITH NUT SCANIA REAR | B17: 7 | C17: - | D17: - | E17: - | F17: - | G17: - | H17: 7
A18: MI0035 - 0683578 WATER PUMP DAF | B18: 2 | C18: - | D18: - | E18: - | F18: - | G18: - | H18: 2
A19: MI0043 - L2320 PRESSURE PLATE SCANIA | B19: 1 | C19: - | D19: - | E19: - | F19: - | G19: - | H19: 1
A20: MI0045 - 4801030160 VALVE BENZ | B20: 1 | C20: - | D20: - | E20: - | F20: - | G20: - | H20: 1
A21: MI0047 - RL3530EA23-E BRAKE BOOSTER 24/30 TRAILER | B21: 275 | C21: - | D21: - | E21: -101 | F21: - | G21: - | H21: 174
A22: MI0048 - HTP-NFH002R-R HEAD LAMP LENS RIGHT VOLVO | B22: 7 | C22: - | D22: - | E22: - | F22: - | G22: - | H22: 7
A23: MI0049 - HTP-NFH002R-L HEAD LAMP LENS LEFT VOLVO | B23: 7 | C23: - | D23: - | E23: - | F23: - | G23: - | H23: 7
A24: MI0052 - SV41 BRAKE LINING SCA | B24: 12 | C24: - | D24: - | E24: -2 | F24: - | G24: - | H24: 10
A25: MI0053 - SV42 BRAKE LINING SCANIA | B25: 89.75 | C25: - | D25: - | E25: - | F25: - | G25: - | H25: 89.75
A26: MI0054 - VL87 BRAKE LINING VOLVO | B26: 23 | C26: - | D26: - | E26: -5 | F26: - | G26: - | H26: 18
A27: MI0055 - VL88 BRAKE LINING VOLVO | B27: 87 | C27: - | D27: - | E27: -15.75 | F27: - | G27: - | H27: 71.25
A28: MI0056 - VL89 BRAKE LINING VOLVO | B28: 0.5 | C28: - | D28: - | E28: - | F28: - | G28: - | H28: 0.5
A29: MI0057 - BC37 BRAKE LINING BPW 8" | B29: 569.25 | C29: 442 | D29: - | E29: -20 | F29: - | G29: - | H29: 991.25
A30: MI0059 - RIVETING MACHINE | B30: 6 | C30: - | D30: - | E30: - | F30: - | G30: - | H30: 6
A31: MI0060 - W01M586364 AIRBAG 5813K | B31: 256 | C31: 100 | D31: - | E31: -49 | F31: - | G31: - | H31: 307
A32: MI0061 - WVA29124 BRAKE PAD ROR | B32: 1 | C32: - | D32: - | E32: - | F32: - | G32: - | H32: 1
A33: MI0064 - BRAKE SHOE BC36 | B33: 48 | C33: - | D33: -2 | E33: - | F33: - | G33: - | H33: 46
A34: MI0065 - 4515 BRAKE SHOE COMP OR HENDRED | B34: 77 | C34: 100 | D34: - | E34: -27 | F34: - | G34: - | H34: 150
A35: MI0066 - W01-M58-8966 | B35: 114 | C35: 100 | D35: - | E35: -53 | F35: - | G35: - | H35: 161
A36: MI0067 - HENDRED BRAKE SHOE SPRING LONG | B36: 622 | C36: 20 | D36: - | E36: -238 | F36: - | G36: - | H36: 404
A37: MI0068 - HENDRED BRAKE SHOE SPRING SHORT | B37: 944 | C37: - | D37: - | E37: -330 | F37: - | G37: - | H37: 614
A38: MI0069 - BRAKE SHOE ROLLER BPW | B38: -6 | C38: - | D38: - | E38: - | F38: - | G38: - | H38: -6
A39: MI0070 - BRAKE SHOE ROLLER LOCK | B39: -314 | C39: - | D39: - | E39: - | F39: - | G39: - | H39: -314
A40: MI0073 - 4707 BRAKE LINING | B40: 179.25 | C40: - | D40: - | E40: -2.5 | F40: 0.5 | G40: - | H40: 177.25
A41: MI0081 - W01M587074 AIRBAG | B41: 26 | C41: 90 | D41: - | E41: -30 | F41: - | G41: - | H41: 86
A42: MI0082 - MMCB BUS FRONT | B42: 38 | C42: - | D42: - | E42: - | F42: - | G42: - | H42: 38
A43: MI0083 - MMCB BUS REAR | B43: 4 | C43: - | D43: - | E43: - | F43: - | G43: - | H43: 4
A44: MI0084 - 315/80 R22.5 UNIVERSAL | B44: 562 | C44: 100 | D44: - | E44: -642 | F44: 8 | G44: - | H44: 28
A45: MI0085 - 315/80 R22.5 20PR STEER | B45: 170 | C45: - | D45: - | E45: -136 | F45: - | G45: - | H45: 34
A46: MI0086 - 315/80 R22.5 20PR DIFF | B46: 36 | C46: 36 | D46: - | E46: -60 | F46: 5 | G46: - | H46: 17
A47: MI0087 - 385/65 R22.5 20PR SUPER SINGLE | B47: 413 | C47: - | D47: - | E47: -217 | F47: - | G47: - | H47: 196
A48: MI0088 - W01M58-9880 AIRBAG | B48: 3 | C48: 5 | D48: - | E48: - | F48: - | G48: - | H48: 8
A49: MI0089 - W01M58-8683 AIRBAG | B49: 1 | C49: 5 | D49: - | E49: -1 | F49: - | G49: - | H49: 5
A50: MI0091 - 32 x 33 WHEEL SPANNER | B50: 30 | C50: - | D50: - | E50: -18 | F50: - | G50: - | H50: 12
A51: MI0093 - HOWO 14 HOLE BRAKE LINING | B51: 0.25 | C51: - | D51: - | E51: - | F51: - | G51: - | H51: 0.25
A52: MI0094 - FAW REAR BRAKE LINING | B52: 36.875 | C52: 4 | D52: - | E52: -6.5 | F52: - | G52: - | H52: 34.375
A53: MI0095 - SUZY PIPE RED | B53: 108 | C53: 250 | D53: - | E53: -55 | F53: - | G53: - | H53: 303
A54: MI0096 - SUZY PIPE YELLOW | B54: 132 | C54: 250 | D54: - | E54: -33 | F54: - | G54: - | H54: 349
A55: MI0097 - BC37 BRAKE SHOE | B55: 25 | C55: - | D55: - | E55: - | F55: - | G55: - | H55: 25
A56: MI0099 - TRAILER SHOCK UP SHORT | B56: 60 | C56: 60 | D56: - | E56: -12 | F56: - | G56: - | H56: 108
A57: MI0102 - PRESSURE PLATE BENZ AXOR | B57: 1 | C57: - | D57: - | E57: - | F57: - | G57: - | H57: 1
A58: MI0103 - RL3519DA4 BRAKE BOOSTER SMALL | B58: 35 | C58: - | D58: - | E58: -15 | F58: - | G58: - | H58: 20
A59: MI0104 - 20744939 WATER PUMP VOLVO | B59: 4 | C59: - | D59: - | E59: -1 | F59: - | G59: - | H59: 3
A60: MI0105 - RELEASE BEARING SCANIA 113 | B60: 1 | C60: - | D60: - | E60: -1 | F60: - | G60: - | H60: -
A61: MI0106 - TRAILER VALVE BSA | B61: 1 | C61: - | D61: - | E61: - | F61: - | G61: - | H61: 1
A62: MI0107 - CABIN PUMP | B62: 1 | C62: - | D62: - | E62: - | F62: - | G62: - | H62: 1
A63: MI0108 - AIR DRIER FILTER DAF | B63: 2 | C63: - | D63: - | E63: - | F63: - | G63: - | H63: 2
A64: MI0109 - 0022950706 | B64: 1 | C64: - | D64: - | E64: - | F64: - | G64: - | H64: 1
A65: MI0110 - M30X250 PIN LONG | B65: 118 | C65: - | D65: - | E65: -55 | F65: - | G65: - | H65: 63
A66: MI0111 - M30X200 PIN SHORT | B66: 170 | C66: - | D66: - | E66: -176 | F66: - | G66: - | H66: -6
A67: MI0112 - 070.063 BUSH SMALL | B67: 407 | C67: - | D67: - | E67: -196 | F67: 4 | G67: - | H67: 215
A68: MI0114 - CLUTCH PLATE SINO | B68: 7 | C68: - | D68: - | E68: -5 | F68: - | G68: - | H68: 2
A69: MI0115 - H701WK WATER FILTER BENZ | B69: 1 | C69: - | D69: - | E69: - | F69: - | G69: - | H69: 1
A70: MI0119 - WVA29244 | B70: -1 | C70: - | D70: - | E70: - | F70: - | G70: - | H70: -1
A71: MI0120 - WVA29246 | B71: 30 | C71: - | D71: - | E71: - | F71: - | G71: - | H71: 30
A72: MI0121 - BRAKE LINING HOWO A+B | B72: 38.25 | C72: - | D72: - | E72: -1 | F72: - | G72: - | H72: 37.25
A73: MI0122 - W013589121 | B73: 97 | C73: 50 | D73: - | E73: -3 | F73: - | G73: - | H73: 144
A74: MI0124 - 24407 BPW SHOCKUP | B74: - | C74: 30 | D74: - | E74: - | F74: - | G74: - | H74: 30
A75: MI0126 - W01M589361 AIRBAG - 54156-15KPP | B75: 8 | C75: - | D75: - | E75: - | F75: - | G75: - | H75: 8
A76: MI0127 - FU/4/5/1 BRAKE LINING | B76: 264.5 | C76: - | D76: - | E76: - | F76: - | G76: - | H76: 264.5
A77: MI0128 - BC37XX BRAKE LINING | B77: 79.25 | C77: - | D77: - | E77: - | F77: - | G77: - | H77: 79.25
A78: MI0129 - TATA SM1 BRAKE LINING | B78: 5 | C78: - | D78: - | E78: - | F78: - | G78: - | H78: 5
A79: MI0130 - CLUTCH FAN FAW380 | B79: - | C79: - | D79: - | E79: -2 | F79: - | G79: - | H79: -2
A80: MI0131 - WVA4709 BRAKE LINING | B80: 7.75 | C80: - | D80: - | E80: - | F80: - | G80: - | H80: 7.75
A81: MI0132 - FAW 16 HOLE BRAKE LINING | B81: 315.25 | C81: 314 | D81: - | E81: -26.5 | F81: - | G81: - | H81: 602.75
A82: MI0136 - WVA29162 | B82: 2 | C82: - | D82: - | E82: - | F82: - | G82: - | H82: 2
A83: MI0137 - WVA29125 | B83: 15 | C83: - | D83: - | E83: -2 | F83: - | G83: - | H83: 13
A84: MI0138 - WVA29177 | B84: 21 | C84: - | D84: - | E84: -5 | F84: - | G84: - | H84: 16
A85: MI0139 - 1878002732 | B85: 1 | C85: - | D85: - | E85: - | F85: - | G85: - | H85: 1
A86: MI0141 - 1878063231 | B86: 2 | C86: - | D86: - | E86: - | F86: - | G86: - | H86: 2
A87: MI0142 - W01M588609-5940K | B87: 60 | C87: 100 | D87: - | E87: -48 | F87: - | G87: - | H87: 112
A88: MI0143 - W01M588535 | B88: 1 | C88: - | D88: - | E88: - | F88: - | G88: - | H88: 1
A89: MI0144 - W01M586297/54157-04KPP | B89: 53 | C89: - | D89: - | E89: - | F89: - | G89: - | H89: 53
A90: MI0149 - 1421186 | B90: 1 | C90: - | D90: - | E90: - | F90: - | G90: - | H90: 1
A91: MI0151 - 1479576 RELEASE BEARING SCANIA R420 | B91: 2 | C91: - | D91: - | E91: - | F91: - | G91: - | H91: 2
A92: MI0154 - 033488501 | B92: 1 | C92: - | D92: - | E92: - | F92: - | G92: - | H92: 1
A93: MI0155 - 360200004 RH | B93: 32 | C93: - | D93: - | E93: -1 | F93: - | G93: - | H93: 31
A94: MI0156 - 360200005 LH | B94: 1 | C94: - | D94: - | E94: -1 | F94: - | G94: - | H94: -
A95: MI0158 - W02M588009-FRONT | B95: -1 | C95: - | D95: - | E95: - | F95: - | G95: - | H95: -1
A96: MI0159 - W02M588007-REAR | B96: 6 | C96: - | D96: - | E96: - | F96: - | G96: - | H96: 6
A97: MI0162 - 21707133 | B97: 3 | C97: - | D97: - | E97: -2 | F97: - | G97: - | H97: 1
A98: MI0163 - 20976003 | B98: 3 | C98: - | D98: - | E98: - | F98: - | G98: - | H98: 3
A99: MI0165 - H200W02 | B99: 3 | C99: - | D99: - | E99: - | F99: - | G99: - | H99: 3
A100: MI0167 - 21707132 | B100: 233 | C100: - | D100: - | E100: -1 | F100: - | G100: - | H100: 232
...

Sheet JAN26
B1: Opening balance | C1: Purchases | D1: Debit Notes | E1: Inventory Write-offs | F1: Sales | G1: Credit Note | H1: Closing balance
A2: MI0001 - 4515-Wx Hendred Brake Lining | B2: 1946.625 | C2: - | D2: - | E2: - | F2: -349 | G2: - | H2: 1597.625
A3: MI0002 - MP31 | B3: 0.25 | C3: - | D3: - | E3: - | F3: - | G3: - | H3: 0.25
A4: MI0003 - MP32 | B4: 49.75 | C4: - | D4: - | E4: - | F4: -19 | G4: - | H4: 30.75
A5: MI0004 - MP36 | B5: 55.625 | C5: 3 | D5: - | E5: - | F5: -15.125 | G5: - | H5: 43.5
A6: MI0005 - BC36 | B6: 105.125 | C6: - | D6: - | E6: -2 | F6: -39.75 | G6: - | H6: 63.375
A7: MI0008 - 996075-K AIRBAG VOLVO O/M 1076076 | B7: 2 | C7: - | D7: - | E7: - | F7: - | G7: - | H7: 2
A8: MI0009 - 994713-K AIRBAG VOLVO O/M 1076595 | B8: 5 | C8: - | D8: - | E8: - | F8: - | G8: - | H8: 5
A9: MI0010 - 994913-K AIRBAG SCA 124 DIFF / 9881 | B9: 4 | C9: - | D9: - | E9: - | F9: -2 | G9: - | H9: 2
A10: MI0011 - 999780-K AIRBAG FREIGHTLINER METAL | B10: 65 | C10: - | D10: - | E10: - | F10: -1 | G10: - | H10: 64
A11: MI00117 - Z SPRING BPW | B11: - | C11: 25 | D11: - | E11: - | F11: - | G11: - | H11: 25
A12: MI0013 - 994183-24K AIRBAG BENZ | B12: -14 | C12: 14 | D12: - | E12: - | F12: - | G12: - | H12: -
A13: MI0018 - BPW SPRING LONG | B13: 396 | C13: - | D13: - | E13: - | F13: -11 | G13: - | H13: 385
A14: MI0019 - OIL SEAL 125 X 150 X 13 | B14: 22 | C14: - | D14: - | E14: - | F14: - | G14: - | H14: 22
A15: MI0021 - H24W05 | B15: 7 | C15: - | D15: - | E15: - | F15: - | G15: - | H15: 7
A16: MI00218 - HENDRED ROLLER BIG | B16: -160 | C16: 362 | D16: - | E16: - | F16: -41 | G16: - | H16: 161
A17: MI0027 - FILTER 8193841 WATER SEPERATOR | B17: -6 | C17: - | D17: - | E17: - | F17: - | G17: - | H17: -6
A18: MI0029 - BOLT WITH NUT SCANIA REAR | B18: 7 | C18: - | D18: - | E18: - | F18: - | G18: - | H18: 7
A19: MI0035 - 0683578 WATER PUMP DAF | B19: 2 | C19: - | D19: - | E19: - | F19: -1 | G19: - | H19: 1
A20: MI0043 - L2320 PRESSURE PLATE SCANIA | B20: 1 | C20: - | D20: - | E20: - | F20: - | G20: - | H20: 1
A21: MI0045 - 4801030160 VALVE BENZ | B21: 1 | C21: - | D21: - | E21: - | F21: - | G21: - | H21: 1
A22: MI0047 - RL3530EA23-E BRAKE BOOSTER 24/30 TRAILER | B22: 174 | C22: 350 | D22: - | E22: - | F22: -96 | G22: - | H22: 428
A23: MI0048 - HTP-NFH002R-R HEAD LAMP LENS RIGHT VOLVO | B23: 7 | C23: - | D23: - | E23: - | F23: - | G23: - | H23: 7
A24: MI0049 - HTP-NFH002R-L HEAD LAMP LENS LEFT VOLVO | B24: 7 | C24: - | D24: - | E24: - | F24: - | G24: - | H24: 7
A25: MI0052 - SV41 BRAKE LINING SCA | B25: 10 | C25: - | D25: - | E25: - | F25: - | G25: - | H25: 10
A26: MI0053 - SV42 BRAKE LINING SCANIA | B26: 89.75 | C26: - | D26: - | E26: - | F26: -1 | G26: - | H26: 88.75
A27: MI0054 - VL87 BRAKE LINING VOLVO | B27: 18 | C27: - | D27: - | E27: - | F27: -1 | G27: - | H27: 17
A28: MI0055 - VL88 BRAKE LINING VOLVO | B28: 71.25 | C28: - | D28: - | E28: - | F28: -14.25 | G28: - | H28: 57
A29: MI0056 - VL89 BRAKE LINING VOLVO | B29: 0.5 | C29: - | D29: - | E29: - | F29: - | G29: - | H29: 0.5
A30: MI0057 - BC37 BRAKE LINING BPW 8" | B30: 991.25 | C30: - | D30: - | E30: - | F30: -53.25 | G30: - | H30: 938
A31: MI0059 - RIVETING MACHINE | B31: 6 | C31: - | D31: - | E31: - | F31: - | G31: - | H31: 6
A32: MI0060 - W01M586364 AIRBAG 5813K | B32: 307 | C32: - | D32: - | E32: - | F32: -20 | G32: - | H32: 287
A33: MI0061 - WVA29124 BRAKE PAD ROR | B33: 1 | C33: - | D33: - | E33: - | F33: - | G33: - | H33: 1
A34: MI0064 - BRAKE SHOE BC36 | B34: 46 | C34: - | D34: - | E34: - | F34: - | G34: - | H34: 46
A35: MI0065 - 4515 BRAKE SHOE COMP OR HENDRED | B35: 150 | C35: - | D35: - | E35: - | F35: -47 | G35: - | H35: 103
A36: MI0066 - W01-M58-8966 | B36: 161 | C36: - | D36: - | E36: - | F36: -40 | G36: - | H36: 121
A37: MI0067 - HENDRED BRAKE SHOE SPRING LONG | B37: 404 | C37: 981 | D37: - | E37: - | F37: -177 | G37: - | H37: 1208
A38: MI0068 - HENDRED BRAKE SHOE SPRING SHORT | B38: 614 | C38: 1362 | D38: - | E38: - | F38: -331 | G38: - | H38: 1645
A39: MI0069 - BRAKE SHOE ROLLER BPW | B39: -6 | C39: - | D39: - | E39: - | F39: - | G39: - | H39: -6
A40: MI0070 - BRAKE SHOE ROLLER LOCK | B40: -314 | C40: 362 | D40: - | E40: - | F40: - | G40: - | H40: 48
A41: MI0073 - 4707 BRAKE LINING | B41: 177.25 | C41: - | D41: - | E41: - | F41: -4 | G41: - | H41: 173.25
A42: MI0081 - W01M587074 AIRBAG | B42: 86 | C42: - | D42: - | E42: - | F42: -38 | G42: - | H42: 48
A43: MI0082 - MMCB BUS FRONT | B43: 38 | C43: - | D43: - | E43: - | F43: - | G43: - | H43: 38
A44: MI0083 - MMCB BUS REAR | B44: 4 | C44: - | D44: - | E44: - | F44: - | G44: - | H44: 4
A45: MI0084 - 315/80 R22.5 UNIVERSAL | B45: 28 | C45: 1526 | D45: - | E45: - | F45: -910 | G45: - | H45: 644
A46: MI0085 - 315/80 R22.5 20PR STEER | B46: 34 | C46: 100 | D46: - | E46: - | F46: -83 | G46: - | H46: 51
A47: MI0086 - 315/80 R22.5 20PR DIFF | B47: 17 | C47: 430 | D47: - | E47: - | F47: -296 | G47: - | H47: 151
A48: MI0087 - 385/65 R22.5 20PR SUPER SINGLE | B48: 198 | C48: 36 | D48: - | E48: - | F48: -140 | G48: - | H48: 94
A49: MI0088 - W01M58-9880 AIRBAG | B49: 8 | C49: - | D49: - | E49: - | F49: - | G49: - | H49: 8
A50: MI0089 - W01M58-8683 AIRBAG | B50: 5 | C50: - | D50: - | E50: - | F50: -2 | G50: - | H50: 3
A51: MI0091 - 32 x 33 WHEEL SPANNER | B51: 12 | C51: - | D51: - | E51: - | F51: -11 | G51: - | H51: 1
A52: MI0093 - HOWO 14 HOLE BRAKE LINING | B52: 0.25 | C52: - | D52: - | E52: - | F52: - | G52: - | H52: 0.25
A53: MI0094 - FAW REAR BRAKE LINING | B53: 34.375 | C53: - | D53: - | E53: - | F53: -5.75 | G53: - | H53: 28.625
A54: MI0095 - SUZY PIPE RED | B54: 303 | C54: - | D54: - | E54: - | F54: -66 | G54: - | H54: 237
A55: MI0096 - SUZY PIPE YELLOW | B55: 349 | C55: - | D55: - | E55: - | F55: -53 | G55: - | H55: 296
A56: MI0097 - BC37 BRAKE SHOE | B56: 25 | C56: - | D56: - | E56: - | F56: - | G56: - | H56: 25
A57: MI0099 - TRAILER SHOCK UP SHORT | B57: 108 | C57: 60 | D57: - | E57: - | F57: -9 | G57: - | H57: 159
A58: MI0102 - PRESSURE PLATE BENZ AXOR | B58: 1 | C58: - | D58: - | E58: - | F58: - | G58: - | H58: 1
A59: MI0103 - RL3519DA4 BRAKE BOOSTER SMALL | B59: 20 | C59: - | D59: - | E59: - | F59: -10 | G59: - | H59: 10
A60: MI0104 - 20744939 WATER PUMP VOLVO | B60: 3 | C60: - | D60: - | E60: - | F60: - | G60: - | H60: 3
A61: MI0106 - TRAILER VALVE BSA | B61: 1 | C61: - | D61: - | E61: - | F61: - | G61: - | H61: 1
A62: MI0107 - CABIN PUMP | B62: 1 | C62: - | D62: - | E62: - | F62: - | G62: - | H62: 1
A63: MI0108 - AIR DRIER FILTER DAF | B63: 2 | C63: - | D63: - | E63: - | F63: - | G63: - | H63: 2
A64: MI0109 - 0022950706 | B64: 1 | C64: - | D64: - | E64: - | F64: - | G64: - | H64: 1
A65: MI0110 - M30X250 PIN LONG | B65: 63 | C65: - | D65: - | E65: - | F65: -3 | G65: - | H65: 60
A66: MI0111 - M30X200 PIN SHORT | B66: -6 | C66: 250 | D66: -1 | E66: - | F66: -39 | G66: 2 | H66: 206
A67: MI0112 - 070.063 BUSH SMALL | B67: 215 | C67: 100 | D67: - | E67: - | F67: -23 | G67: - | H67: 292
A68: MI0114 - CLUTCH PLATE SINO | B68: 2 | C68: 90 | D68: - | E68: - | F68: -3 | G68: - | H68: 89
A69: MI0115 - H701WK WATER FILTER BENZ | B69: 1 | C69: - | D69: - | E69: - | F69: - | G69: - | H69: 1
A70: MI0119 - WVA29244 | B70: -1 | C70: - | D70: - | E70: - | F70: - | G70: - | H70: -1
A71: MI0120 - WVA29246 | B71: 30 | C71: - | D71: - | E71: - | F71: - | G71: - | H71: 30
A72: MI0121 - BRAKE LINING HOWO A+B | B72: 37.25 | C72: - | D72: - | E72: - | F72: - | G72: - | H72: 37.25
A73: MI0122 - W013589121 | B73: 144 | C73: - | D73: - | E73: - | F73: -47 | G73: - | H73: 97
A74: MI0124 - 24407 BPW SHOCKUP | B74: 30 | C74: 30 | D74: - | E74: - | F74: - | G74: - | H74: 60
A75: MI0126 - W01M589361 AIRBAG - 54156-15KPP | B75: 8 | C75: - | D75: - | E75: - | F75: -1 | G75: - | H75: 7
A76: MI0127 - FU/4/5/1 BRAKE LINING | B76: 264.5 | C76: - | D76: - | E76: - | F76: -55.5 | G76: - | H76: 209
A77: MI0128 - BC37XX BRAKE LINING | B77: 79.25 | C77: - | D77: - | E77: - | F77: - | G77: - | H77: 79.25
A78: MI0129 - TATA SM1 BRAKE LINING | B78: 5 | C78: - | D78: - | E78: - | F78: - | G78: - | H78: 5
A79: MI0130 - CLUTCH FAN FAW380 | B79: -2 | C79: 3 | D79: - | E79: - | F79: -1 | G79: - | H79: -
A80: MI0131 - WVA4709 BRAKE LINING | B80: 7.75 | C80: - | D80: - | E80: - | F80: - | G80: - | H80: 7.75
A81: MI0132 - FAW 16 HOLE BRAKE LINING | B81: 602.75 | C81: - | D81: - | E81: - | F81: -29 | G81: - | H81: 573.75
A82: MI0136 - WVA29162 | B82: 2 | C82: - | D82: - | E82: - | F82: - | G82: - | H82: 2
A83: MI0137 - WVA29125 | B83: 13 | C83: - | D83: - | E83: - | F83: - | G83: - | H83: 13
A84: MI0138 - WVA29177 | B84: 16 | C84: - | D84: - | E84: - | F84: -8 | G84: - | H84: 8
A85: MI0139 - 1878002732 | B85: 1 | C85: - | D85: - | E85: - | F85: - | G85: - | H85: 1
A86: MI0141 - 1878063231 | B86: 2 | C86: - | D86: - | E86: - | F86: - | G86: - | H86: 2
A87: MI0142 - W01M588609-5940K | B87: 112 | C87: - | D87: - | E87: -1 | F87: -43 | G87: - | H87: 68
A88: MI0143 - W01M588535 | B88: 1 | C88: - | D88: - | E88: - | F88: - | G88: - | H88: 1
A89: MI0144 - W01M586297/54157-04KPP | B89: 53 | C89: - | D89: - | E89: - | F89: -19 | G89: - | H89: 34
A90: MI0149 - 1421186 | B90: 1 | C90: - | D90: - | E90: - | F90: - | G90: - | H90: 1
A91: MI0151 - 1479576 RELEASE BEARING SCANIA R420 | B91: 2 | C91: - | D91: - | E91: - | F91: - | G91: - | H91: 2
A92: MI0154 - 033488501 | B92: 1 | C92: - | D92: - | E92: - | F92: - | G92: - | H92: 1
A93: MI0155 - 360200004 RH | B93: 31 | C93: - | D93: - | E93: - | F93: -3 | G93: - | H93: 28
A94: MI0156 - 360200005 LH | B94: - | C94: - | D94: - | E94: - | F94: -2 | G94: - | H94: -2
A95: MI0158 - W02M588009-FRONT | B95: -1 | C95: - | D95: - | E95: - | F95: - | G95: - | H95: -1
A96: MI0159 - W02M588007-REAR | B96: 6 | C96: - | D96: - | E96: - | F96: - | G96: - | H96: 6
A97: MI0162 - 21707133 | B97: 1 | C97: - | D97: - | E97: - | F97: - | G97: - | H97: 1
A98: MI0163 - 20976003 | B98: 3 | C98: - | D98: - | E98: - | F98: - | G98: - | H98: 3
A99: MI0165 - H200W02 | B99: 3 | C99: - | D99: - | E99: - | F99: - | G99: - | H99: 3
A100: MI0167 - 21707132 | B100: 232 | C100: - | D100: - | E100: - | F100: - | G100: - | H100: 232
...

Sheet AVE
A1: CAT | B1: ITEMS | C1: AVERAGE | D1: 44774 | E1: 44805 | F1: 44835 | G1: 44866 | H1: 44896 | I1: 44927 | J1: 44958 | K1: 44986 | L1: 45017 | M1: 45047 | N1: 45078 | O1: 45108 | P1: 45139 | Q1: 45170 | R1: 45200 | S1: 45231 | T1: 45261 | U1: 45292 | V1: 45323 | W1: 45352 | X1: 45383 | Y1: 45413 | Z1: 45444 | AA1: 45474 | AB1: 45505 | AC1: 45536 | AD1: 45566 | AE1: 45597 | AF1: 45627 | AG1: 45658 | AH1: 45689 | AI1: 45717 | AJ1: 45748 | AK1: 45778 | AL1: 45833 | AM1: 45863 | AN1: 45894 | AO1: 45925 | AP1: 45955 | AQ1: 45986 | AR1: 46016 | AS1: JAN
A2: GWI | B2: MI0001 - 4515-Wx Hendred Brake Lining | C2: =-AVERAGE(AL2:AV2) -> 251.65625 | D2: -234.75 | E2: -208.25 | F2: -213.25 | G2: -112 | H2: -127.5 | I2: -224.5 | J2: -237.25 | K2: -254.25 | L2: -119 | M2: -153.25 | N2: -203 | O2: -121.75 | P2: -205.75 | Q2: -139.25 | R2: -158 | S2: -187.25 | T2: -215.25 | U2: -194.25 | V2: -257 | W2: -176.75 | X2: -216.75 | Y2: -187.5 | Z2: -137.25 | AA2: -129.25 | AB2: -211.75 | AC2: -132.75 | AD2: =VLOOKUP(B2,'OCT24'!$A$1:H1173,6,0) -> -188.5 | AE2: =VLOOKUP(B2,'NOV24'!$A$1:H558,6,0) -> -228.75 | AF2: =VLOOKUP(B2,'DEC24'!$A$1:$H$914,5,0) -> -169.5 | AG2: =VLOOKUP(B2,'JAN25'!$A$1:G629,5,0) -> -189.75 | AH2: =VLOOKUP(B2,'FEB25'!A$1:G1063,5,0) -> -220 | AI2: =VLOOKUP(B2,'MAR25'!$A$1:G896,5,0) -> -272 | AJ2: =VLOOKUP(B2,'APR25'!$A$1:G525,5,0) -> -245.25 | AK2: =VLOOKUP(B2,'MAY25'!$A$1:G918,5,0) -> -257.25 | AL2: =VLOOKUP(B2,JUNE25!$A$1:G621,5,0) -> -257 | AM2: =VLOOKUP(B2, JULY25!$A$1:$E$544, 5, FALSE) -> -211.75 | AN2: =VLOOKUP(B2, 'AUG25'!$A$1:$E$540, 5, FALSE) -> -145.25 | AO2: =VLOOKUP(B2, 'SEP25'!$A$1:$F$520, 6, FALSE) -> -228.25 | AP2: =VLOOKUP(B2, 'OCT25'!$A$1:$F$520, 5, FALSE) -> -331.25 | AQ2: =VLOOKUP(B2, 'NOV25'!$B$1:$I$616, 5, FALSE) -> -234.75 | AR2: =VLOOKUP(B2, 'DEC25'!$A$1:$I$611, 5, FALSE) -> -256 | AS2: =VLOOKUP(B2, 'JAN26'!$A$1:$I$607, 6, FALSE) -> -349
A3: GWI | B3: MI0002 - MP31 | C3: =-AVERAGE(AL3:AV3) -> 0 | D3: 0 | E3: 0 | F3: 0 | G3: 0 | H3: 0 | I3: -1 | J3: -1 | K3: 0 | L3: 0 | M3: 0 | N3: 0 | O3: 0 | P3: 0 | Q3: 0 | R3: 0 | S3: 0 | T3: 0 | U3: 0 | V3: 0 | W3: 0 | X3: 0 | Y3: 0 | Z3: 0 | AA3: 0 | AB3: 0 | AC3: 0 | AD3: =VLOOKUP(B3,'OCT24'!$A$1:H1174,6,0) -> 0 | AE3: =VLOOKUP(B3,'NOV24'!$A$1:H559,6,0) -> 0 | AF3: =VLOOKUP(B3,'DEC24'!$A$1:$H$914,5,0) -> 0 | AG3: =VLOOKUP(B3,'JAN25'!$A$1:G630,5,0) -> 0 | AH3: =VLOOKUP(B3,'FEB25'!A$1:G1064,5,0) -> 0 | AI3: =VLOOKUP(B3,'MAR25'!$A$1:G897,5,0) -> 0 | AJ3: =VLOOKUP(B3,'APR25'!$A$1:G526,5,0) -> 0 | AK3: =VLOOKUP(B3,'MAY25'!$A$1:G919,5,0) -> 0 | AL3: =VLOOKUP(B3,JUNE25!$A$1:G622,5,0) -> 0 | AM3: =VLOOKUP(B3, JULY25!$A$1:$E$544, 5, FALSE) -> 0 | AN3: =VLOOKUP(B3, 'AUG25'!$A$1:$E$540, 5, FALSE) -> 0 | AO3: =VLOOKUP(B3, 'SEP25'!$A$1:$F$520, 6, FALSE) -> - | AP3: =VLOOKUP(B3, 'OCT25'!$A$1:$F$520, 5, FALSE) -> - | AQ3: =VLOOKUP(B3, 'NOV25'!$B$1:$I$616, 5, FALSE) -> - | AR3: =VLOOKUP(B3, 'DEC25'!$A$1:$I$611, 5, FALSE) -> - | AS3: =VLOOKUP(B3, 'JAN26'!$A$1:$I$607, 6, FALSE) -> -
A4: GWI | B4: MI0003 - MP32 | C4: =-AVERAGE(AL4:AV4) -> 12.40625 | D4: 0 | E4: 0 | F4: 0 | G4: 0 | H4: 0 | I4: 0 | J4: 0 | K4: 0 | L4: 0 | M4: 0 | N4: 0 | O4: 0 | P4: 0 | Q4: 0 | R4: 0 | S4: -2 | T4: 0 | U4: 0 | V4: -2 | W4: -14 | X4: -8 | Y4: -9 | Z4: 0 | AA4: -3 | AB4: -4 | AC4: -10 | AD4: =VLOOKUP(B4,'OCT24'!$A$1:H1175,6,0) -> -6 | AE4: =VLOOKUP(B4,'NOV24'!$A$1:H560,6,0) -> -12 | AF4: =VLOOKUP(B4,'DEC24'!$A$1:$H$914,5,0) -> -27.75 | AG4: =VLOOKUP(B4,'JAN25'!$A$1:G631,5,0) -> -5 | AH4: =VLOOKUP(B4,'FEB25'!A$1:G1065,5,0) -> -11.25 | AI4: =VLOOKUP(B4,'MAR25'!$A$1:G898,5,0) -> -6.5 | AJ4: =VLOOKUP(B4,'APR25'!$A$1:G527,5,0) -> -5 | AK4: =VLOOKUP(B4,'MAY25'!$A$1:G920,5,0) -> -8 | AL4: =VLOOKUP(B4,JUNE25!$A$1:G623,5,0) -> -1.25 | AM4: =VLOOKUP(B4, JULY25!$A$1:$E$544, 5, FALSE) -> -15 | AN4: =VLOOKUP(B4, 'AUG25'!$A$1:$E$540, 5, FALSE) -> -21.25 | AO4: =VLOOKUP(B4, 'SEP25'!$A$1:$F$520, 6, FALSE) -> -15.75 | AP4: =VLOOKUP(B4, 'OCT25'!$A$1:$F$520, 5, FALSE) -> -8.5 | AQ4: =VLOOKUP(B4, 'NOV25'!$B$1:$I$616, 5, FALSE) -> -10.5 | AR4: =VLOOKUP(B4, 'DEC25'!$A$1:$I$611, 5, FALSE) -> -8 | AS4: =VLOOKUP(B4, 'JAN26'!$A$1:$I$607, 6, FALSE) -> -19
A5: GWI | B5: MI0004 - MP36 | C5: =-AVERAGE(AL5:AV5) -> 15.8125 | D5: -1.75 | E5: -4 | I5: -12.5 | J5: -10.25 | K5: -22.75 | L5: -33 | M5: -61.25 | N5: -37.75 | O5: -38.5 | P5: -6.5 | Q5: -27.75 | R5: -17.5 | S5: -15.5 | T5: -0.75 | U5: -2 | V5: -3.5 | W5: -6.5 | X5: -26.5 | Y5: -1.75 | Z5: -0.25 | AA5: -20.75 | AB5: -5 | AC5: -6 | AD5: =VLOOKUP(B5,'OCT24'!$A$1:H1176,6,0) -> -4 | AE5: =VLOOKUP(B5,'NOV24'!$A$1:H561,6,0) -> -7 | AF5: =VLOOKUP(B5,'DEC24'!$A$1:$H$914,5,0) -> -2.5 | AG5: =VLOOKUP(B5,'JAN25'!$A$1:G632,5,0) -> -13.25 | AH5: =VLOOKUP(B5,'FEB25'!A$1:G1066,5,0) -> -20.5 | AI5: =VLOOKUP(B5,'MAR25'!$A$1:G899,5,0) -> 0 | AJ5: =VLOOKUP(B5,'APR25'!$A$1:G528,5,0) -> -3.5 | AK5: =VLOOKUP(B5,'MAY25'!$A$1:G921,5,0) -> -17 | AL5: =VLOOKUP(B5,JUNE25!$A$1:G624,5,0) -> -34.25 | AM5: =VLOOKUP(B5, JULY25!$A$1:$E$544, 5, FALSE) -> -26 | AN5: =VLOOKUP(B5, 'AUG25'!$A$1:$E$540, 5, FALSE) -> -10.625 | AO5: =VLOOKUP(B5, 'SEP25'!$A$1:$F$520, 6, FALSE) -> -9 | AP5: =VLOOKUP(B5, 'OCT25'!$A$1:$F$520, 5, FALSE) -> -11 | AQ5: =VLOOKUP(B5, 'NOV25'!$B$1:$I$616, 5, FALSE) -> -13 | AR5: =VLOOKUP(B5, 'DEC25'!$A$1:$I$611, 5, FALSE) -> -7.5 | AS5: =VLOOKUP(B5, 'JAN26'!$A$1:$I$607, 6, FALSE) -> -15.125
A6: GWI | B6: MI0005 - BC36 | C6: =-AVERAGE(AL6:AV6) -> 33 | D6: -12 | E6: -27.75 | F6: -20 | G6: -12.25 | H6: -21.25 | I6: -11.5 | J6: -2 | K6: -23.75 | L6: -15.25 | M6: -4.5 | N6: -30.75 | O6: -13.25 | P6: -3.75 | Q6: -2 | R6: -8.75 | S6: -30 | T6: -3 | U6: -8 | V6: -24.25 | W6: -16.75 | X6: -17.5 | Y6: -5.5 | AA6: -22.25 | AD6: =VLOOKUP(B6,'OCT24'!$A$1:H1177,6,0) -> -30.5 | AE6: =VLOOKUP(B6,'NOV24'!$A$1:H562,6,0) -> -38.5 | AF6: =VLOOKUP(B6,'DEC24'!$A$1:$H$914,5,0) -> -32.75 | AG6: =VLOOKUP(B6,'JAN25'!$A$1:G633,5,0) -> -35.75 | AH6: =VLOOKUP(B6,'FEB25'!A$1:G1067,5,0) -> -27 | AJ6: =VLOOKUP(B6,'APR25'!$A$1:G529,5,0) -> -9 | AK6: =VLOOKUP(B6,'MAY25'!$A$1:G922,5,0) -> -20.5 | AL6: =VLOOKUP(B6,JUNE25!$A$1:G625,5,0) -> -10 | AM6: =VLOOKUP(B6, JULY25!$A$1:$E$544, 5, FALSE) -> -27.25 | AN6: =VLOOKUP(B6, 'AUG25'!$A$1:$E$540, 5, FALSE) -> -29.25 | AO6: =VLOOKUP(B6, 'SEP25'!$A$1:$F$520, 6, FALSE) -> -28 | AP6: =VLOOKUP(B6, 'OCT25'!$A$1:$F$520, 5, FALSE) -> -45.5 | AQ6: =VLOOKUP(B6, 'NOV25'!$B$1:$I$616, 5, FALSE) -> -58.75 | AR6: =VLOOKUP(B6, 'DEC25'!$A$1:$I$611, 5, FALSE) -> -25.5 | AS6: =VLOOKUP(B6, 'JAN26'!$A$1:$I$607, 6, FALSE) -> -39.75
A7: ALLMAX | B7: MI0006 - WVA29174 | C7: 0 | D7: 0 | E7: 0 | F7: 0 | G7: 0 | H7: 0 | I7: 0 | J7: 0 | K7: 0 | L7: 0 | M7: 0 | N7: 0 | O7: 0 | P7: 0 | Q7: 0 | R7: 0 | S7: 0 | T7: 0 | U7: 0 | V7: 0 | W7: 0 | X7: 0 | Y7: 0 | Z7: 0
A8: ALLMAX | B8: MI0007 - WVA29087-GOLD | C8: 0 | D8: 0 | E8: 0 | F8: 0 | G8: 0 | H8: 0 | I8: 0 | J8: 0 | K8: 0 | L8: 0 | M8: 0 | N8: 0 | O8: 0 | P8: 0 | Q8: 0 | R8: 0 | S8: 0 | T8: 0 | U8: 0 | V8: 0 | W8: 0 | X8: 0 | Y8: 0 | Z8: 0
A9: AIRBAGS | B9: MI0008 - 996075-K AIRBAG VOLVO O/M 1076076 | C9: =-AVERAGE(AL9:AV9) -> 0 | D9: 0 | E9: 0 | F9: 0 | G9: 0 | H9: 0 | I9: 0 | J9: 0 | K9: 0 | L9: 0 | M9: 0 | N9: 0 | O9: 0 | P9: 0 | Q9: 0 | R9: 0 | S9: 0 | T9: 0 | U9: 0 | V9: 0 | W9: 0 | X9: 0 | Y9: 0 | Z9: 0 | AA9: 0 | AB9: 0 | AC9: 0 | AD9: =VLOOKUP(B9,'OCT24'!$A$1:H1180,6,0) -> 0 | AE9: =VLOOKUP(B9,'NOV24'!$A$1:H565,6,0) -> 0 | AF9: =VLOOKUP(B9,'DEC24'!$A$1:$H$914,5,0) -> 0 | AG9: =VLOOKUP(B9,'JAN25'!$A$1:G636,5,0) -> 0 | AH9: =VLOOKUP(B9,'FEB25'!A$1:G1070,5,0) -> 0 | AI9: =VLOOKUP(B9,'MAR25'!$A$1:G903,5,0) -> 0 | AJ9: =VLOOKUP(B9,'APR25'!$A$1:G532,5,0) -> 0 | AK9: =VLOOKUP(B9,'MAY25'!$A$1:G925,5,0) -> 0 | AL9: =VLOOKUP(B9,JUNE25!$A$1:G628,5,0) -> 0 | AM9: =VLOOKUP(B9, JULY25!$A$1:$E$544, 5, FALSE) -> 0 | AN9: =VLOOKUP(B9, 'AUG25'!$A$1:$E$540, 5, FALSE) -> 0 | AO9: =VLOOKUP(B9, 'SEP25'!$A$1:$F$520, 6, FALSE) -> - | AP9: =VLOOKUP(B9, 'OCT25'!$A$1:$F$520, 5, FALSE) -> - | AQ9: =VLOOKUP(B9, 'NOV25'!$B$1:$I$616, 5, FALSE) -> - | AR9: =VLOOKUP(B9, 'DEC25'!$A$1:$I$611, 5, FALSE) -> - | AS9: =VLOOKUP(B9, 'JAN26'!$A$1:$I$607, 6, FALSE) -> -
A10: AIRBAGS | B10: MI0009 - 994713-K AIRBAG VOLVO O/M 1076595 | C10: =-AVERAGE(AL10:AV10) -> 2.6666667 | D10: -16 | E10: -1 | F10: -1 | G10: -6 | H10: 0 | I10: -3 | J10: 0 | K10: -19 | L10: 0 | M10: 0 | N10: -5 | O10: -11 | P10: -9 | Q10: -8 | R10: -8 | S10: -6 | T10: -1 | U10: -2 | V10: 0 | W10: 0 | X10: 0 | Y10: 0 | Z10: 0 | AA10: -1 | AB10: 0 | AC10: 0 | AD10: =VLOOKUP(B10,'OCT24'!$A$1:H1181,6,0) -> -1 | AE10: =VLOOKUP(B10,'NOV24'!$A$1:H566,6,0) -> 0 | AF10: =VLOOKUP(B10,'DEC24'!$A$1:$H$914,5,0) -> 0 | AG10: =VLOOKUP(B10,'JAN25'!$A$1:G637,5,0) -> 0 | AH10: =VLOOKUP(B10,'FEB25'!A$1:G1071,5,0) -> 0 | AI10: =VLOOKUP(B10,'MAR25'!$A$1:G904,5,0) -> -2 | AJ10: =VLOOKUP(B10,'APR25'!$A$1:G533,5,0) -> 0 | AK10: =VLOOKUP(B10,'MAY25'!$A$1:G926,5,0) -> -6 | AL10: =VLOOKUP(B10,JUNE25!$A$1:G629,5,0) -> -6 | AM10: =VLOOKUP(B10, JULY25!$A$1:$E$544, 5, FALSE) -> -2 | AN10: =VLOOKUP(B10, 'AUG25'!$A$1:$E$540, 5, FALSE) -> 0 | AO10: =VLOOKUP(B10, 'SEP25'!$A$1:$F$520, 6, FALSE) -> - | AP10: =VLOOKUP(B10, 'OCT25'!$A$1:$F$520, 5, FALSE) -> - | AQ10: =VLOOKUP(B10, 'NOV25'!$B$1:$I$616, 5, FALSE) -> - | AR10: =VLOOKUP(B10, 'DEC25'!$A$1:$I$611, 5, FALSE) -> - | AS10: =VLOOKUP(B10, 'JAN26'!$A$1:$I$607, 6, FALSE) -> -
A11: AIRBAGS | B11: MI0010 - 994913-K AIRBAG SCA 124 DIFF / 9881 | C11: =-AVERAGE(AL11:AV11) -> 2.25 | D11: 0 | E11: 0 | F11: -1 | G11: -16 | H11: -1 | I11: 0 | J11: -13 | K11: 0 | L11: 0 | M11: -8 | N11: -1 | O11: -1 | P11: -3 | Q11: -1 | R11: 0 | S11: 0 | T11: -1 | U11: 0 | V11: 0 | W11: 0 | X11: 0 | Y11: 0 | Z11: 0 | AA11: -4 | AB11: 0 | AC11: -1 | AD11: =VLOOKUP(B11,'OCT24'!$A$1:H1182,6,0) -> 0 | AE11: =VLOOKUP(B11,'NOV24'!$A$1:H567,6,0) -> 0 | AF11: =VLOOKUP(B11,'DEC24'!$A$1:$H$914,5,0) -> -1 | AG11: =VLOOKUP(B11,'JAN25'!$A$1:G638,5,0) -> 0 | AH11: =VLOOKUP(B11,'FEB25'!A$1:G1072,5,0) -> 0 | AI11: =VLOOKUP(B11,'MAR25'!$A$1:G905,5,0) -> -2 | AJ11: =VLOOKUP(B11,'APR25'!$A$1:G534,5,0) -> 0 | AK11: =VLOOKUP(B11,'MAY25'!$A$1:G927,5,0) -> -1 | AL11: =VLOOKUP(B11,JUNE25!$A$1:G630,5,0) -> -2 | AM11: =VLOOKUP(B11, JULY25!$A$1:$E$544, 5, FALSE) -> -1 | AN11: =VLOOKUP(B11, 'AUG25'!$A$1:$E$540, 5, FALSE) -> -2 | AO11: =VLOOKUP(B11, 'SEP25'!$A$1:$F$520, 6, FALSE) -> -3 | AP11: =VLOOKUP(B11, 'OCT25'!$A$1:$F$520, 5, FALSE) -> -3 | AQ11: =VLOOKUP(B11, 'NOV25'!$B$1:$I$616, 5, FALSE) -> -3 | AR11: =VLOOKUP(B11, 'DEC25'!$A$1:$I$611, 5, FALSE) -> -2 | AS11: =VLOOKUP(B11, 'JAN26'!$A$1:$I$607, 6, FALSE) -> -2
A12: AIRBAGS | B12: MI0011 - 999780-K AIRBAG FREIGHTLINER METAL | C12: =-AVERAGE(AL12:AV12) -> 4.75 | D12: -21 | E12: -34 | F12: -22 | G12: -17 | H12: -31 | I12: -27 | J12: -36 | K12: -16 | L12: -8 | M12: -18 | N12: -21 | O12: -22 | P12: -12 | Q12: -16 | R12: -13 | S12: -15 | T12: -3 | U12: 0 | V12: -5 | W12: 0 | X12: 0 | Y12: -5 | Z12: -2 | AA12: -1 | AB12: -4 | AC12: -1 | AD12: =VLOOKUP(B12,'OCT24'!$A$1:H1183,6,0) -> -9 | AE12: =VLOOKUP(B12,'NOV24'!$A$1:H568,6,0) -> -22 | AF12: =VLOOKUP(B12,'DEC24'!$A$1:$H$914,5,0) -> -18 | AG12: =VLOOKUP(B12,'JAN25'!$A$1:G639,5,0) -> -13 | AH12: =VLOOKUP(B12,'FEB25'!A$1:G1073,5,0) -> 0 | AI12: =VLOOKUP(B12,'MAR25'!$A$1:G906,5,0) -> -5 | AJ12: =VLOOKUP(B12,'APR25'!$A$1:G535,5,0) -> -15 | AK12: =VLOOKUP(B12,'MAY25'!$A$1:G928,5,0) -> -7 | AL12: =VLOOKUP(B12,JUNE25!$A$1:G631,5,0) -> -1 | AM12: =VLOOKUP(B12, JULY25!$A$1:$E$544, 5, FALSE) -> -11 | AN12: =VLOOKUP(B12, 'AUG25'!$A$1:$E$540, 5, FALSE) -> -2 | AO12: =VLOOKUP(B12, 'SEP25'!$A$1:$F$520, 6, FALSE) -> -9 | AP12: =VLOOKUP(B12, 'OCT25'!$A$1:$F$520, 5, FALSE) -> -1 | AQ12: =VLOOKUP(B12, 'NOV25'!$B$1:$I$616, 5, FALSE) -> -8 | AR12: =VLOOKUP(B12, 'DEC25'!$A$1:$I$611, 5, FALSE) -> -5 | AS12: =VLOOKUP(B12, 'JAN26'!$A$1:$I$607, 6, FALSE) -> -1
A13: SPARES | B13: MI00117 - Z SPRING BPW | C13: 0 | D13: 0 | E13: 0 | F13: 0 | G13: 0 | H13: 0 | I13: 0 | J13: 0 | K13: 0 | L13: 0 | M13: 0 | N13: 0 | O13: 0 | P13: 0 | Q13: 0 | R13: 0 | S13: 0 | T13: 0 | U13: 0 | V13: 0 | W13: 0 | X13: 0 | Y13: 0 | Z13: 0
A14: AIRBAGS | B14: MI0012 - 999780-K-PP AIRBAG FREIGHTLINER | C14: 0 | D14: 0 | E14: 0 | F14: 0 | G14: 0 | H14: 0 | I14: 0 | J14: 0 | K14: 0 | L14: 0 | M14: 0 | N14: 0 | O14: 0 | P14: 0 | Q14: 0 | R14: 0 | S14: 0 | T14: 0 | U14: 0 | V14: 0 | W14: 0 | X14: 0 | Y14: 0 | Z14: 0
A15: AIRBAGS | B15: MI0013 - 994183-24K AIRBAG BENZ | C15: =-AVERAGE(AL15:AV15) -> 0 | D15: 0 | E15: 0 | F15: 0 | G15: 0 | H15: 0 | I15: 0 | J15: 0 | K15: 0 | L15: 0 | M15: 0 | N15: 0 | O15: 0 | P15: 0 | Q15: 0 | R15: 0 | S15: 0 | T15: 0 | U15: 0 | V15: 0 | W15: 0 | X15: 0 | Y15: 0 | Z15: 0 | AI15: =VLOOKUP(B15,'MAR25'!$A$1:G909,5,0) -> -14 | AJ15: =VLOOKUP(B15,'APR25'!$A$1:G538,5,0) -> 0 | AK15: =VLOOKUP(B15,'MAY25'!$A$1:G931,5,0) -> 0 | AL15: =VLOOKUP(B15,JUNE25!$A$1:G634,5,0) -> 0 | AM15: =VLOOKUP(B15, JULY25!$A$1:$E$544, 5, FALSE) -> 0 | AN15: =VLOOKUP(B15, 'AUG25'!$A$1:$E$540, 5, FALSE) -> 0 | AO15: =VLOOKUP(B15, 'SEP25'!$A$1:$F$520, 6, FALSE) -> - | AP15: =VLOOKUP(B15, 'OCT25'!$A$1:$F$520, 5, FALSE) -> - | AQ15: =VLOOKUP(B15, 'NOV25'!$B$1:$I$616, 5, FALSE) -> - | AR15: =VLOOKUP(B15, 'DEC25'!$A$1:$I$611, 5, FALSE) -> - | AS15: =VLOOKUP(B15, 'JAN26'!$A$1:$I$607, 6, FALSE) -> -
A16: AIRBAGS | B16: MI0014 - 994757-02K AIRBAG BENZ | C16: 0 | D16: 0 | E16: 0 | F16: 0 | G16: 0 | H16: 0 | I16: 0 | J16: 0 | K16: 0 | L16: 0 | M16: 0 | N16: 0 | O16: 0 | P16: 0 | Q16: 0 | R16: 0 | S16: 0 | T16: 0 | U16: 0 | V16: 0 | W16: 0 | X16: 0 | Y16: 0 | Z16: 0
A17: AIRBAGS | B17: MI0015 - 346418K AIRBAG VOLVO N/M | C17: 0 | D17: 0 | E17: 0 | F17: 0 | G17: 0 | H17: 0 | I17: 0 | J17: 0 | K17: 0 | L17: 0 | M17: 0 | N17: 0 | O17: 0 | P17: 0 | Q17: 0 | R17: 0 | S17: 0 | T17: 0 | U17: 0 | V17: 0 | W17: 0 | X17: 0 | Y17: 0 | Z17: 0
A18: AIRBAGS | B18: MI0016 - 6356418-K AIRBAG VOLVO N/M | C18: 0 | D18: 0 | E18: 0 | F18: 0 | G18: 0 | H18: 0 | I18: 0 | J18: 0 | K18: 0 | L18: 0 | M18: 0 | N18: 0 | O18: 0 | P18: 0 | Q18: 0 | R18: 0 | S18: 0 | T18: 0 | U18: 0 | V18: 0 | W18: 0 | X18: 0 | Y18: 0 | Z18: 0
A19: AIRBAGS | B19: MI0017 - E10.7803.C AIRBAG VOLVO N/M | C19: 0 | D19: 0 | E19: 0 | F19: 0 | G19: 0 | H19: 0 | I19: 0 | J19: 0 | K19: 0 | L19: 0 | M19: 0 | N19: 0 | O19: 0 | P19: 0 | Q19: 0 | R19: 0 | S19: 0 | T19: 0 | U19: 0 | V19: 0 | W19: 0 | X19: 0 | Y19: 0 | Z19: 0
A20: SPARES | B20: MI0018 - BPW SPRING LONG | C20: =-AVERAGE(AL20:AV20) -> 8.75 | D20: -50 | E20: -12 | F20: -6 | G20: -6 | H20: -8 | I20: -37 | J20: -21 | K20: -62 | L20: -3 | M20: -6 | N20: -4 | O20: 0 | P20: 0 | Q20: 0 | R20: -20 | S20: 0 | T20: 0 | U20: -10 | V20: 0 | W20: -50 | X20: 0 | Y20: -115 | Z20: -23 | AA20: 0 | AB20: 0 | AC20: 0 | AD20: =VLOOKUP(B20,'OCT24'!$A$1:H1191,6,0) -> 0 | AE20: =VLOOKUP(B20,'NOV24'!$A$1:H576,6,0) -> -2 | AF20: =VLOOKUP(B20,'DEC24'!$A$1:$H$914,5,0) -> 0 | AG20: =VLOOKUP(B20,'JAN25'!$A$1:G647,5,0) -> -26 | AH20: =VLOOKUP(B20,'FEB25'!A$1:G1081,5,0) -> -1 | AI20: =VLOOKUP(B20,'MAR25'!$A$1:G914,5,0) -> -20 | AJ20: =VLOOKUP(B20,'APR25'!$A$1:G543,5,0) -> -1 | AK20: =VLOOKUP(B20,'MAY25'!$A$1:G936,5,0) -> 0 | AL20: =VLOOKUP(B20,JUNE25!$A$1:G639,5,0) -> -2 | AM20: =VLOOKUP(B20, JULY25!$A$1:$E$544, 5, FALSE) -> 0 | AN20: =VLOOKUP(B20, 'AUG25'!$A$1:$E$540, 5, FALSE) -> -18 | AO20: =VLOOKUP(B20, 'SEP25'!$A$1:$F$520, 6, FALSE) -> -1 | AP20: =VLOOKUP(B20, 'OCT25'!$A$1:$F$520, 5, FALSE) -> -7 | AQ20: =VLOOKUP(B20, 'NOV25'!$B$1:$I$616, 5, FALSE) -> -26 | AR20: =VLOOKUP(B20, 'DEC25'!$A$1:$I$611, 5, FALSE) -> -5 | AS20: =VLOOKUP(B20, 'JAN26'!$A$1:$I$607, 6, FALSE) -> -11
A21: SPARES | B21: MI0019 - OIL SEAL 125 X 150 X 13 | C21: =-AVERAGE(AL21:AV21) -> 3 | D21: 0 | E21: 0 | F21: 0 | G21: 0 | H21: 0 | I21: 0 | J21: 0 | K21: 0 | L21: 0 | M21: 0 | N21: 0 | O21: 0 | P21: 0 | Q21: 0 | R21: 0 | S21: 0 | T21: 0 | U21: 0 | V21: 0 | W21: 0 | X21: 0 | Y21: 0 | Z21: 0 | AA21: 0 | AB21: 0 | AC21: 0 | AD21: =VLOOKUP(B21,'OCT24'!$A$1:H1192,6,0) -> 0 | AE21: =VLOOKUP(B21,'NOV24'!$A$1:H577,6,0) -> 0 | AF21: =VLOOKUP(B21,'DEC24'!$A$1:$H$914,5,0) -> 0 | AG21: =VLOOKUP(B21,'JAN25'!$A$1:G648,5,0) -> 0 | AH21: =VLOOKUP(B21,'FEB25'!A$1:G1082,5,0) -> 0 | AI21: =VLOOKUP(B21,'MAR25'!$A$1:G915,5,0) -> 0 | AJ21: =VLOOKUP(B21,'APR25'!$A$1:G544,5,0) -> 0 | AK21: =VLOOKUP(B21,'MAY25'!$A$1:G937,5,0) -> 0 | AL21: =VLOOKUP(B21,JUNE25!$A$1:G640,5,0) -> -4 | AM21: =VLOOKUP(B21, JULY25!$A$1:$E$544, 5, FALSE) -> -1 | AN21: =VLOOKUP(B21, 'AUG25'!$A$1:$E$540, 5, FALSE) -> -5 | AO21: =VLOOKUP(B21, 'SEP25'!$A$1:$F$520, 6, FALSE) -> -1 | AP21: =VLOOKUP(B21, 'OCT25'!$A$1:$F$520, 5, FALSE) -> -6 | AQ21: =VLOOKUP(B21, 'NOV25'!$B$1:$I$616, 5, FALSE) -> - | AR21: =VLOOKUP(B21, 'DEC25'!$A$1:$I$611, 5, FALSE) -> -1 | AS21: =VLOOKUP(B21, 'JAN26'!$A$1:$I$607, 6, FALSE) -> -
B22: MI0020 - E500HD129 | C22: 0 | D22: 0 | E22: 0 | F22: 0 | G22: 0 | H22: 0 | I22: -2 | J22: 0 | K22: 0 | L22: 0 | M22: 0 | N22: 0 | O22: 0 | P22: 0 | Q22: 0 | R22: 0 | S22: 0 | T22: 0 | U22: 0 | V22: 0 | W22: 0 | X22: 0 | Y22: 0 | Z22: 0
B23: MI0021 - H24W05 | C23: =-AVERAGE(AL23:AV23) -> 0 | D23: 0 | E23: 0 | F23: 0 | G23: 0 | H23: 0 | I23: 0 | J23: 0 | K23: 0 | L23: 0 | M23: 0 | N23: 0 | O23: 0 | P23: 0 | Q23: 0 | R23: 0 | S23: 0 | T23: 0 | U23: 0 | V23: 0 | W23: 0 | X23: 0 | Y23: 0 | Z23: 0 | AA23: 0 | AB23: 0 | AC23: 0 | AD23: =VLOOKUP(B23,'OCT24'!$A$1:H1194,6,0) -> 0 | AE23: =VLOOKUP(B23,'NOV24'!$A$1:H579,6,0) -> 0 | AF23: =VLOOKUP(B23,'DEC24'!$A$1:$H$914,5,0) -> 0 | AG23: =VLOOKUP(B23,'JAN25'!$A$1:G650,5,0) -> 0 | AH23: =VLOOKUP(B23,'FEB25'!A$1:G1084,5,0) -> 0 | AI23: =VLOOKUP(B23,'MAR25'!$A$1:G917,5,0) -> 0 | AJ23: =VLOOKUP(B23,'APR25'!$A$1:G546,5,0) -> 0 | AK23: =VLOOKUP(B23,'MAY25'!$A$1:G939,5,0) -> 0 | AL23: =VLOOKUP(B23,JUNE25!$A$1:G642,5,0) -> 0 | AM23: =VLOOKUP(B23, JULY25!$A$1:$E$544, 5, FALSE) -> 0 | AN23: =VLOOKUP(B23, 'AUG25'!$A$1:$E$540, 5, FALSE) -> 0 | AO23: =VLOOKUP(B23, 'SEP25'!$A$1:$F$520, 6, FALSE) -> - | AP23: =VLOOKUP(B23, 'OCT25'!$A$1:$F$520, 5, FALSE) -> - | AQ23: =VLOOKUP(B23, 'NOV25'!$B$1:$I$616, 5, FALSE) -> - | AR23: =VLOOKUP(B23, 'DEC25'!$A$1:$I$611, 5, FALSE) -> - | AS23: =VLOOKUP(B23, 'JAN26'!$A$1:$I$607, 6, FALSE) -> -
A24: SPARES | B24: MI00218 - HENDRED ROLLER BIG | C24: =-AVERAGE(AL24:AV24) -> 20.571429 | D24: -10 | E24: -20 | F24: -55 | G24: -8 | H24: -18 | I24: -10 | J24: -12 | K24: -3 | L24: -4 | M24: -1 | N24: -44 | O24: -12 | P24: -22 | Q24: -4 | R24: -20 | S24: -20 | T24: -1 | U24: -63 | V24: -3 | W24: -35 | X24: -22 | Y24: -34 | Z24: -4 | AA24: -34 | AB24: 0 | AC24: -4 | AD24: =VLOOKUP(B24,'OCT24'!$A$1:H1195,6,0) -> 0 | AE24: =VLOOKUP(B24,'NOV24'!$A$1:H580,6,0) -> -27 | AF24: =VLOOKUP(B24,'DEC24'!$A$1:$H$914,5,0) -> -9 | AG24: =VLOOKUP(B24,'JAN25'!$A$1:G651,5,0) -> -15 | AH24: =VLOOKUP(B24,'FEB25'!A$1:G1085,5,0) -> -4 | AI24: =VLOOKUP(B24,'MAR25'!$A$1:G918,5,0) -> -76 | AJ24: =VLOOKUP(B24,'APR25'!$A$1:G547,5,0) -> -40 | AK24: =VLOOKUP(B24,'MAY25'!$A$1:G940,5,0) -> -82 | AL24: =VLOOKUP(B24,JUNE25!$A$1:G643,5,0) -> -48 | AM24: =VLOOKUP(B24, JULY25!$A$1:$E$544, 5, FALSE) -> -2 | AN24: =VLOOKUP(B24, 'AUG25'!$A$1:$E$540, 5, FALSE) -> -2 | AO24: =VLOOKUP(B24, 'SEP25'!$A$1:$F$520, 6, FALSE) -> -12 | AP24: =VLOOKUP(B24, 'OCT25'!$A$1:$F$520, 5, FALSE) -> -31 | AQ24: =VLOOKUP(B24, 'NOV25'!$B$1:$I$616, 5, FALSE) -> - | AR24: =VLOOKUP(B24, 'DEC25'!$A$1:$I$611, 5, FALSE) -> -8 | AS24: =VLOOKUP(B24, 'JAN26'!$A$1:$I$607, 6, FALSE) -> -41
B25: MI0022 - HEAD LAMP VOLVO RH | C25: 0 | D25: 0 | E25: 0 | F25: 0 | G25: 0 | H25: 0 | I25: 0 | J25: 0 | K25: 0 | L25: 0 | M25: 0 | N25: 0 | O25: 0 | P25: 0 | Q25: 0 | R25: 0 | S25: 0 | T25: 0 | U25: 0 | V25: 0 | W25: 0 | X25: 0 | Y25: 0 | Z25: 0
B26: MI0023 - AIR CLEANER ATEGO | C26: 0 | D26: 0 | E26: 0 | F26: 0 | G26: 0 | H26: 0 | I26: 0 | J26: 0 | K26: 0 | L26: 0 | M26: 0 | N26: 0 | O26: 0 | P26: 0 | Q26: 0 | R26: 0 | S26: 0 | T26: 0 | U26: 0 | V26: 0 | W26: 0 | X26: 0 | Y26: 0 | Z26: 0
B27: MI0024 - FILTER BYPSS 477556 | C27: 0 | D27: 0 | E27: 0 | F27: 0 | G27: 0 | H27: 0 | I27: 0 | J27: 0 | K27: 0 | L27: 0 | M27: 0 | N27: 0 | O27: 0 | P27: 0 | Q27: 0 | R27: 0 | S27: 0 | T27: 0 | U27: 0 | V27: 0 | W27: 0 | X27: 0 | Y27: 0 | Z27: 0
B28: MI0025 - FILTER 20430751 DIESEL | C28: 0 | D28: 0 | E28: 0 | F28: 0 | G28: 0 | H28: 0 | I28: 0 | J28: 0 | K28: 0 | L28: 0 | M28: 0 | N28: 0 | O28: 0 | P28: 0 | Q28: 0 | R28: 0 | S28: 0 | T28: 0 | U28: 0 | V28: 0 | W28: 0 | X28: 0 | Y28: 0 | Z28: 0
B29: MI0026 - FILTER 466634 OIL | C29: 0 | D29: 0 | E29: 0 | F29: 0 | G29: 0 | H29: 0 | I29: 0 | J29: 0 | K29: 0 | L29: 0 | M29: 0 | N29: 0 | O29: 0 | P29: 0 | Q29: 0 | R29: 0 | S29: 0 | T29: 0 | U29: 0 | V29: 0 | W29: 0 | X29: 0 | Y29: 0 | Z29: 0
B30: MI0027 - FILTER 8193841 WATER SEPERATOR | C30: =-AVERAGE(AL30:AV30) -> 0 | D30: 0 | E30: 0 | F30: 0 | G30: 0 | H30: 0 | I30: 0 | J30: 0 | K30: 0 | L30: 0 | M30: 0 | N30: 0 | O30: -1 | P30: 0 | Q30: 0 | R30: 0 | S30: 0 | T30: 0 | U30: -31 | V30: 0 | W30: -2 | X30: 0 | Y30: 0 | Z30: 0 | AA30: 0 | AB30: 0 | AC30: -1 | AD30: =VLOOKUP(B30,'OCT24'!$A$1:H1201,6,0) -> -3 | AE30: =VLOOKUP(B30,'NOV24'!$A$1:H586,6,0) -> 0 | AF30: =VLOOKUP(B30,'DEC24'!$A$1:$H$914,5,0) -> 0 | AG30: =VLOOKUP(B30,'JAN25'!$A$1:G657,5,0) -> 0 | AH30: =VLOOKUP(B30,'FEB25'!A$1:G1091,5,0) -> -4 | AI30: =VLOOKUP(B30,'MAR25'!$A$1:G924,5,0) -> 0 | AJ30: =VLOOKUP(B30,'APR25'!$A$1:G553,5,0) -> 0 | AK30: =VLOOKUP(B30,'MAY25'!$A$1:G946,5,0) -> 0 | AL30: =VLOOKUP(B30,JUNE25!$A$1:G649,5,0) -> 0 | AM30: =VLOOKUP(B30, JULY25!$A$1:$E$544, 5, FALSE) -> 0 | AN30: =VLOOKUP(B30, 'AUG25'!$A$1:$E$540, 5, FALSE) -> 0 | AO30: =VLOOKUP(B30, 'SEP25'!$A$1:$F$520, 6, FALSE) -> - | AP30: =VLOOKUP(B30, 'OCT25'!$A$1:$F$520, 5, FALSE) -> - | AQ30: =VLOOKUP(B30, 'NOV25'!$B$1:$I$616, 5, FALSE) -> - | AR30: =VLOOKUP(B30, 'DEC25'!$A$1:$I$611, 5, FALSE) -> - | AS30: =VLOOKUP(B30, 'JAN26'!$A$1:$I$607, 6, FALSE) -> -
B31: MI0029 - BOLT WITH NUT SCANIA REAR | C31: =-AVERAGE(AL31:AV31) -> 0 | D31: 0 | E31: 0 | F31: 0 | G31: 0 | H31: 0 | I31: 0 | J31: 0 | K31: 0 | L31: 0 | M31: 0 | N31: 0 | O31: 0 | P31: 0 | Q31: 0 | R31: 0 | S31: 0 | T31: 0 | U31: 0 | V31: 0 | W31: 0 | X31: 0 | Y31: 0 | Z31: 0 | AA31: 0 | AB31: 0 | AC31: 0 | AD31: =VLOOKUP(B31,'OCT24'!$A$1:H1203,6,0) -> 0 | AE31: =VLOOKUP(B31,'NOV24'!$A$1:H588,6,0) -> 0 | AF31: =VLOOKUP(B31,'DEC24'!$A$1:$H$914,5,0) -> 0 | AG31: =VLOOKUP(B31,'JAN25'!$A$1:G659,5,0) -> 0 | AH31: =VLOOKUP(B31,'FEB25'!A$1:G1093,5,0) -> 0 | AI31: =VLOOKUP(B31,'MAR25'!$A$1:G926,5,0) -> 0 | AJ31: =VLOOKUP(B31,'APR25'!$A$1:G555,5,0) -> 0 | AK31: =VLOOKUP(B31,'MAY25'!$A$1:G948,5,0) -> 0 | AL31: =VLOOKUP(B31,JUNE25!$A$1:G651,5,0) -> 0 | AM31: =VLOOKUP(B31, JULY25!$A$1:$E$544, 5, FALSE) -> 0 | AN31: =VLOOKUP(B31, 'AUG25'!$A$1:$E$540, 5, FALSE) -> 0 | AO31: =VLOOKUP(B31, 'SEP25'!$A$1:$F$520, 6, FALSE) -> - | AP31: =VLOOKUP(B31, 'OCT25'!$A$1:$F$520, 5, FALSE) -> - | AQ31: =VLOOKUP(B31, 'NOV25'!$B$1:$I$616, 5, FALSE) -> - | AR31: =VLOOKUP(B31, 'DEC25'!$A$1:$I$611, 5, FALSE) -> - | AS31: =VLOOKUP(B31, 'JAN26'!$A$1:$I$607, 6, FALSE) -> -
B32: MI0030 - RL3530AM55 AIR DRIER SCA 124 | C32: 0 | D32: 0 | E32: 0 | F32: 0 | G32: 0 | H32: 0 | I32: 0 | J32: 0 | K32: 0 | L32: 0 | M32: 0 | N32: 0 | O32: 0 | P32: 0 | Q32: 0 | R32: 0 | S32: 0 | T32: 0 | U32: 0 | V32: 0 | W32: 0 | X32: 0 | Y32: 0 | Z32: 0
B33: MI0031 - 1519631 SHOCK UP SCANIA | C33: 0 | D33: 0 | E33: 0 | F33: 0 | G33: 0 | H33: 0 | I33: 0 | J33: 0 | K33: 0 | L33: 0 | M33: 0 | N33: 0 | O33: 0 | P33: 0 | Q33: 0 | R33: 0 | S33: 0 | T33: 0 | U33: 0 | V33: 0 | W33: 0 | X33: 0 | Y33: 0 | Z33: 0
B34: MI0032 - 1628103 SHOCK UP VOLVO | C34: 0 | D34: 0 | E34: 0 | F34: 0 | G34: 0 | H34: 0 | I34: 0 | J34: 0 | K34: 0 | L34: 0 | M34: 0 | N34: 0 | O34: 0 | P34: 0 | Q34: 0 | R34: 0 | S34: 0 | T34: 0 | U34: 0 | V34: 0 | W34: 0 | X34: 0 | Y34: 0 | Z34: 0
B35: MI0033 - 20374546 SHOCK UP VOLVO | C35: 0 | D35: 0 | E35: 0 | F35: 0 | G35: 0 | H35: 0 | I35: 0 | J35: 0 | K35: 0 | L35: 0 | M35: 0 | N35: 0 | O35: 0 | P35: 0 | Q35: 0 | R35: 0 | S35: 0 | T35: 0 | U35: 0 | V35: 0 | W35: 0 | X35: 0 | Y35: 0 | Z35: 0
B36: MI0034 - TURBO CHARGER SCA R EURO 3 | C36: 0 | D36: 0 | E36: 0 | F36: 0 | G36: 0 | H36: 0 | I36: 0 | J36: 0 | K36: 0 | L36: 0 | M36: 0 | N36: 0 | O36: 0 | P36: 0 | Q36: 0 | R36: 0 | S36: 0 | T36: 0 | U36: 0 | V36: 0 | W36: 0 | X36: 0 | Y36: 0 | Z36: 0
A37: SPARES | B37: MI0035 - 0683578 WATER PUMP DAF | C37: =-AVERAGE(AL37:AV37) -> 0.4 | D37: 0 | E37: 0 | F37: 0 | G37: 0 | H37: 0 | I37: 0 | J37: 0 | K37: 0 | L37: 0 | M37: 0 | N37: 0 | O37: 0 | P37: 0 | Q37: 0 | R37: 0 | S37: 0 | T37: 0 | U37: 0 | V37: 0 | W37: 0 | X37: 0 | Y37: 0 | Z37: 0 | AA37: 0 | AB37: 0 | AC37: 0 | AD37: =VLOOKUP(B37,'OCT24'!$A$1:H1209,6,0) -> 0 | AE37: =VLOOKUP(B37,'NOV24'!$A$1:H594,6,0) -> 0 | AF37: =VLOOKUP(B37,'DEC24'!$A$1:$H$914,5,0) -> 0 | AG37: =VLOOKUP(B37,'JAN25'!$A$1:G665,5,0) -> 0 | AH37: =VLOOKUP(B37,'FEB25'!A$1:G1099,5,0) -> 0 | AI37: =VLOOKUP(B37,'MAR25'!$A$1:G932,5,0) -> 0 | AJ37: =VLOOKUP(B37,'APR25'!$A$1:G561,5,0) -> 0 | AK37: =VLOOKUP(B37,'MAY25'!$A$1:G954,5,0) -> 0 | AL37: =VLOOKUP(B37,JUNE25!$A$1:G657,5,0) -> 0 | AM37: =VLOOKUP(B37, JULY25!$A$1:$E$544, 5, FALSE) -> 0 | AN37: =VLOOKUP(B37, 'AUG25'!$A$1:$E$540, 5, FALSE) -> 0 | AO37: =VLOOKUP(B37, 'SEP25'!$A$1:$F$520, 6, FALSE) -> -1 | AP37: =VLOOKUP(B37, 'OCT25'!$A$1:$F$520, 5, FALSE) -> - | AQ37: =VLOOKUP(B37, 'NOV25'!$B$1:$I$616, 5, FALSE) -> - | AR37: =VLOOKUP(B37, 'DEC25'!$A$1:$I$611, 5, FALSE) -> - | AS37: =VLOOKUP(B37, 'JAN26'!$A$1:$I$607, 6, FALSE) -> -1
B38: MI0036 - 1353072 WATER PUMP SCA 124 | C38: 0 | D38: 0 | E38: 0 | F38: 0 | G38: 0 | H38: 0 | I38: 0 | J38: 0 | K38: 0 | L38: 0 | M38: 0 | N38: 0 | O38: 0 | P38: 0 | Q38: 0 | R38: 0 | S38: 0 | T38: 0 | U38: 0 | V38: 0 | W38: 0 | X38: 0 | Y38: 0 | Z38: 0
B39: MI0037 - 43410012500 PRESSURE LIMITING VALVE | C39: 0 | D39: 0 | E39: 0 | F39: 0 | G39: 0 | H39: 0 | I39: 0 | J39: 0 | K39: 0 | L39: 0 | M39: 0 | N39: 0 | O39: 0 | P39: 0 | Q39: 0 | R39: 0 | S39: 0 | T39: 0 | U39: 0 | V39: 0 | W39: 0 | X39: 0 | Y39: 0 | Z39: 0
B40: MI0038 - 759331510 BELT TENSIONER BENZ | C40: 0 | D40: 0 | E40: 0 | F40: 0 | G40: 0 | H40: 0 | I40: 0 | J40: 0 | K40: 0 | L40: 0 | M40: 0 | N40: 0 | O40: 0 | P40: 0 | Q40: 0 | R40: 0 | S40: 0 | T40: 0 | U40: 0 | V40: 0 | W40: 0 | X40: 0 | Y40: 0 | Z40: 0
B41: MI0039 - MFJ FFJ COUPLING | C41: 0 | D41: 0 | E41: 0 | F41: 0 | G41: 0 | H41: 0 | I41: 0 | J41: 0 | K41: 0 | L41: 0 | M41: 0 | N41: 0 | O41: 0 | P41: 0 | Q41: 0 | R41: 0 | S41: 0 | T41: 0 | U41: 0 | V41: 0 | W41: 0 | X41: 0 | Y41: 0 | Z41: 0
B42: MI0040 - 4729000530 SOLONOID VALVE | C42: 0 | D42: 0 | E42: 0 | F42: 0 | G42: 0 | H42: 0 | I42: 0 | J42: 0 | K42: 0 | L42: 0 | M42: 0 | N42: 0 | O42: 0 | P42: 0 | Q42: 0 | R42: 0 | S42: 0 | T42: 0 | U42: 0 | V42: 0 | W42: 0 | X42: 0 | Y42: 0 | Z42: 0
B43: MI0041 - 1235571 CROSS JOINT DAF | C43: 0 | D43: 0 | E43: 0 | F43: 0 | G43: 0 | H43: 0 | I43: 0 | J43: 0 | K43: 0 | L43: 0 | M43: 0 | N43: 0 | O43: 0 | P43: 0 | Q43: 0 | R43: 0 | S43: 0 | T43: 0 | U43: 0 | V43: 0 | W43: 0 | X43: 0 | Y43: 0 | Z43: 0
B44: MI0042 - INDICATOR LIGHT SCANIA | C44: 0 | D44: 0 | E44: 0 | F44: 0 | G44: 0 | H44: 0 | I44: 0 | J44: 0 | K44: 0 | L44: 0 | M44: 0 | N44: 0 | O44: 0 | P44: 0 | Q44: 0 | R44: 0 | S44: 0 | T44: 0 | U44: 0 | V44: 0 | W44: 0 | X44: 0 | Y44: 0 | Z44: 0
B45: MI0043 - L2320 PRESSURE PLATE SCANIA | C45: =-AVERAGE(AL45:AV45) -> 0 | D45: 0 | E45: 0 | F45: 0 | G45: 0 | H45: 0 | I45: 0 | J45: 0 | K45: 0 | L45: 0 | M45: 0 | N45: 0 | O45: 0 | P45: 0 | Q45: 0 | R45: 0 | S45: 0 | T45: 0 | U45: 0 | V45: 0 | W45: 0 | X45: 0 | Y45: 0 | Z45: 0 | AA45: 0 | AB45: 0 | AC45: 0 | AD45: =VLOOKUP(B45,'OCT24'!$A$1:H1217,6,0) -> 0 | AE45: =VLOOKUP(B45,'NOV24'!$A$1:H602,6,0) -> 0 | AF45: =VLOOKUP(B45,'DEC24'!$A$1:$H$914,5,0) -> 0 | AG45: =VLOOKUP(B45,'JAN25'!$A$1:G673,5,0) -> 0 | AH45: =VLOOKUP(B45,'FEB25'!A$1:G1107,5,0) -> 0 | AI45: =VLOOKUP(B45,'MAR25'!$A$1:G940,5,0) -> 0 | AJ45: =VLOOKUP(B45,'APR25'!$A$1:G569,5,0) -> 0 | AK45: =VLOOKUP(B45,'MAY25'!$A$1:G962,5,0) -> 0 | AL45: =VLOOKUP(B45,JUNE25!$A$1:G665,5,0) -> 0 | AM45: =VLOOKUP(B45, JULY25!$A$1:$E$544, 5, FALSE) -> 0 | AN45: =VLOOKUP(B45, 'AUG25'!$A$1:$E$540, 5, FALSE) -> 0 | AO45: =VLOOKUP(B45, 'SEP25'!$A$1:$F$520, 6, FALSE) -> - | AP45: =VLOOKUP(B45, 'OCT25'!$A$1:$F$520, 5, FALSE) -> - | AQ45: =VLOOKUP(B45, 'NOV25'!$B$1:$I$616, 5, FALSE) -> - | AR45: =VLOOKUP(B45, 'DEC25'!$A$1:$I$611, 5, FALSE) -> - | AS45: =VLOOKUP(B45, 'JAN26'!$A$1:$I$607, 6, FALSE) -> -
B46: MI0044 - TURNTABLE 1100MM | C46: 0 | D46: 0 | E46: 0 | F46: 0 | G46: 0 | H46: 0 | I46: 0 | J46: 0 | K46: 0 | L46: 0 | M46: 0 | N46: 0 | O46: 0 | P46: 0 | Q46: 0 | R46: 0 | S46: 0 | T46: 0 | U46: 0 | V46: 0 | W46: 0 | X46: 0 | Y46: 0 | Z46: 0
B47: MI0045 - 4801030160 VALVE BENZ | C47: =-AVERAGE(AL47:AV47) -> 0 | D47: 0 | E47: 0 | F47: 0 | G47: 0 | H47: 0 | I47: 0 | J47: 0 | K47: 0 | L47: 0 | M47: 0 | N47: 0 | O47: 0 | P47: 0 | Q47: 0 | R47: 0 | S47: 0 | T47: 0 | U47: 0 | V47: 0 | W47: 0 | X47: 0 | Y47: 0 | Z47: 0 | AA47: 0 | AB47: 0 | AC47: 0 | AD47: =VLOOKUP(B47,'OCT24'!$A$1:H1219,6,0) -> 0 | AE47: =VLOOKUP(B47,'NOV24'!$A$1:H604,6,0) -> 0 | AF47: =VLOOKUP(B47,'DEC24'!$A$1:$H$914,5,0) -> 0 | AG47: =VLOOKUP(B47,'JAN25'!$A$1:G675,5,0) -> 0 | AH47: =VLOOKUP(B47,'FEB25'!A$1:G1109,5,0) -> 0 | AI47: =VLOOKUP(B47,'MAR25'!$A$1:G942,5,0) -> 0 | AJ47: =VLOOKUP(B47,'APR25'!$A$1:G571,5,0) -> 0 | AK47: =VLOOKUP(B47,'MAY25'!$A$1:G964,5,0) -> 0 | AL47: =VLOOKUP(B47,JUNE25!$A$1:G667,5,0) -> 0 | AM47: =VLOOKUP(B47, JULY25!$A$1:$E$544, 5, FALSE) -> 0 | AN47: =VLOOKUP(B47, 'AUG25'!$A$1:$E$540, 5, FALSE) -> 0 | AO47: =VLOOKUP(B47, 'SEP25'!$A$1:$F$520, 6, FALSE) -> - | AP47: =VLOOKUP(B47, 'OCT25'!$A$1:$F$520, 5, FALSE) -> - | AQ47: =VLOOKUP(B47, 'NOV25'!$B$1:$I$616, 5, FALSE) -> - | AR47: =VLOOKUP(B47, 'DEC25'!$A$1:$I$611, 5, FALSE) -> - | AS47: =VLOOKUP(B47, 'JAN26'!$A$1:$I$607, 6, FALSE) -> -
B48: MI0046 - 1423017 DOOR HANDLE LH SCANIA | C48: 0 | D48: 0 | E48: 0 | F48: 0 | G48: 0 | H48: 0 | I48: 0 | J48: 0 | K48: 0 | L48: 0 | M48: 0 | N48: 0 | O48: 0 | P48: 0 | Q48: 0 | R48: 0 | S48: 0 | T48: 0 | U48: 0 | V48: 0 | W48: 0 | X48: 0 | Y48: 0 | Z48: 0
A49: SPARES | B49: MI0047 - RL3530EA23-E BRAKE BOOSTER 24/30 TRAILER | C49: =-AVERAGE(AL49:AV49) -> 79.875 | D49: -57 | E49: -57 | F49: -54 | G49: -34 | H49: -16 | I49: -53 | J49: -34 | K49: -71 | L49: -44 | M49: -73 | N49: -68 | O49: -89 | P49: -45 | Q49: -70 | R49: -43 | S49: -35 | T49: -26 | U49: -40 | V49: -83 | W49: -81 | X49: -56 | Y49: -94 | Z49: -117 | AA49: -45 | AB49: -64 | AC49: -54 | AD49: =VLOOKUP(B49,'OCT24'!$A$1:H1221,6,0) -> #N/A | AE49: =VLOOKUP(B49,'NOV24'!$A$1:H606,6,0) -> #N/A | AF49: =VLOOKUP(B49,'DEC24'!$A$1:$H$914,5,0) -> #N/A | AG49: =VLOOKUP(B49,'JAN25'!$A$1:G677,5,0) -> #N/A | AH49: -114 | AI49: -85 | AJ49: -89 | AK49: -67 | AL49: -78 | AM49: -109 | AN49: -85 | AO49: -15 | AP49: =VLOOKUP(B49, 'OCT25'!$A$1:$F$520, 5, FALSE) -> -121 | AQ49: =VLOOKUP(B49, 'NOV25'!$B$1:$I$616, 5, FALSE) -> -34 | AR49: =VLOOKUP(B49, 'DEC25'!$A$1:$I$611, 5, FALSE) -> -101 | AS49: =VLOOKUP(B49, 'JAN26'!$A$1:$I$607, 6, FALSE) -> -96
B50: MI0048 - HTP-NFH002R-R HEAD LAMP LENS RIGHT VOLVO | C50: =-AVERAGE(AL50:AV50) -> 0 | D50: 0 | E50: 0 | F50: 0 | G50: 0 | H50: 0 | I50: 0 | J50: 0 | K50: 0 | L50: 0 | M50: 0 | N50: 0 | O50: 0 | P50: 0 | Q50: 0 | R50: 0 | S50: 0 | T50: 0 | U50: 0 | V50: 0 | W50: 0 | X50: 0 | Y50: 0 | Z50: 0 | AA50: 0 | AB50: 0 | AC50: 0 | AD50: =VLOOKUP(B50,'OCT24'!$A$1:H1222,6,0) -> 0 | AE50: =VLOOKUP(B50,'NOV24'!$A$1:H607,6,0) -> 0 | AF50: =VLOOKUP(B50,'DEC24'!$A$1:$H$914,5,0) -> 0 | AG50: =VLOOKUP(B50,'JAN25'!$A$1:G678,5,0) -> 0 | AH50: =VLOOKUP(B50,'FEB25'!A$1:G1112,5,0) -> 0 | AI50: =VLOOKUP(B50,'MAR25'!$A$1:G945,5,0) -> 0 | AJ50: =VLOOKUP(B50,'APR25'!$A$1:G574,5,0) -> 0 | AK50: =VLOOKUP(B50,'MAY25'!$A$1:G967,5,0) -> 0 | AL50: =VLOOKUP(B50,JUNE25!$A$1:G670,5,0) -> 0 | AM50: =VLOOKUP(B50, JULY25!$A$1:$E$544, 5, FALSE) -> 0 | AN50: =VLOOKUP(B50, 'AUG25'!$A$1:$E$540, 5, FALSE) -> 0 | AO50: =VLOOKUP(B50, 'SEP25'!$A$1:$F$520, 6, FALSE) -> - | AP50: =VLOOKUP(B50, 'OCT25'!$A$1:$F$520, 5, FALSE) -> - | AQ50: =VLOOKUP(B50, 'NOV25'!$B$1:$I$616, 5, FALSE) -> - | AR50: =VLOOKUP(B50, 'DEC25'!$A$1:$I$611, 5, FALSE) -> - | AS50: =VLOOKUP(B50, 'JAN26'!$A$1:$I$607, 6, FALSE) -> -
B51: MI0049 - HTP-NFH002R-L HEAD LAMP LENS LEFT VOLVO | C51: =-AVERAGE(AL51:AV51) -> 0 | D51: 0 | E51: 0 | F51: 0 | G51: 0 | H51: 0 | I51: 0 | J51: 0 | K51: 0 | L51: 0 | M51: 0 | N51: 0 | O51: 0 | P51: 0 | Q51: 0 | R51: 0 | S51: 0 | T51: 0 | U51: 0 | V51: 0 | W51: 0 | X51: 0 | Y51: 0 | Z51: 0 | AA51: 0 | AB51: 0 | AC51: 0 | AD51: =VLOOKUP(B51,'OCT24'!$A$1:H1223,6,0) -> 0 | AE51: =VLOOKUP(B51,'NOV24'!$A$1:H608,6,0) -> 0 | AF51: =VLOOKUP(B51,'DEC24'!$A$1:$H$914,5,0) -> 0 | AG51: =VLOOKUP(B51,'JAN25'!$A$1:G679,5,0) -> 0 | AH51: =VLOOKUP(B51,'FEB25'!A$1:G1113,5,0) -> 0 | AI51: =VLOOKUP(B51,'MAR25'!$A$1:G946,5,0) -> 0 | AJ51: =VLOOKUP(B51,'APR25'!$A$1:G575,5,0) -> 0 | AK51: =VLOOKUP(B51,'MAY25'!$A$1:G968,5,0) -> 0 | AL51: =VLOOKUP(B51,JUNE25!$A$1:G671,5,0) -> 0 | AM51: =VLOOKUP(B51, JULY25!$A$1:$E$544, 5, FALSE) -> 0 | AN51: =VLOOKUP(B51, 'AUG25'!$A$1:$E$540, 5, FALSE) -> 0 | AO51: =VLOOKUP(B51, 'SEP25'!$A$1:$F$520, 6, FALSE) -> - | AP51: =VLOOKUP(B51, 'OCT25'!$A$1:$F$520, 5, FALSE) -> - | AQ51: =VLOOKUP(B51, 'NOV25'!$B$1:$I$616, 5, FALSE) -> - | AR51: =VLOOKUP(B51, 'DEC25'!$A$1:$I$611, 5, FALSE) -> - | AS51: =VLOOKUP(B51, 'JAN26'!$A$1:$I$607, 6, FALSE) -> -
B52: MI0050 - STR2352 STARTER MOTOR SCA 124 | C52: 0 | D52: 0 | E52: 0 | F52: 0 | G52: 0 | H52: 0 | I52: 0 | J52: 0 | K52: 0 | L52: 0 | M52: 0 | N52: 0 | O52: 0 | P52: 0 | Q52: 0 | R52: 0 | S52: 0 | T52: 0 | U52: 0 | V52: 0 | W52: 0 | X52: 0 | Y52: 0 | Z52: 0
B53: MI0051 - 21225115 BRAKE DISC ROR SMALL | C53: 0 | D53: 0 | E53: 0 | F53: 0 | G53: 0 | H53: 0 | I53: 0 | J53: 0 | K53: 0 | L53: 0 | M53: 0 | N53: 0 | O53: 0 | P53: 0 | Q53: 0 | R53: 0 | S53: 0 | T53: 0 | U53: 0 | V53: 0 | W53: 0 | X53: 0 | Y53: 0 | Z53: 0
A54: GWI | B54: MI0052 - SV41 BRAKE LINING SCA | C54: =-AVERAGE(AL54:AV54) -> 0.875 | D54: -55 | E54: -24.5 | F54: -13 | G54: -40.5 | H54: -25.5 | I54: -13 | J54: -1 | K54: -14 | L54: -13 | M54: -10.5 | N54: -31.75 | O54: -46 | P54: -42 | Q54: -44 | R54: -15 | S54: -11 | T54: -0.5 | U54: -1 | V54: -4.75 | W54: 0 | X54: -0.5 | Y54: -3 | Z54: 0 | AA54: 0 | AB54: -0.5 | AC54: -2.25 | AD54: =VLOOKUP(B54,'OCT24'!$A$1:H1226,6,0) -> -7.5 | AE54: =VLOOKUP(B54,'NOV24'!$A$1:H611,6,0) -> -4.5 | AF54: =VLOOKUP(B54,'DEC24'!$A$1:$H$914,5,0) -> -8 | AG54: =VLOOKUP(B54,'JAN25'!$A$1:G682,5,0) -> -2 | AH54: =VLOOKUP(B54,'FEB25'!A$1:G1116,5,0) -> 0 | AI54: =VLOOKUP(B54,'MAR25'!$A$1:G949,5,0) -> 0 | AJ54: =VLOOKUP(B54,'APR25'!$A$1:G578,5,0) -> -0.5 | AK54: =VLOOKUP(B54,'MAY25'!$A$1:G971,5,0) -> 0 | AL54: =VLOOKUP(B54,JUNE25!$A$1:G674,5,0) -> -0.25 | AM54: =VLOOKUP(B54, JULY25!$A$1:$E$544, 5, FALSE) -> -1.25 | AN54: =VLOOKUP(B54, 'AUG25'!$A$1:$E$540, 5, FALSE) -> 0 | AO54: =VLOOKUP(B54, 'SEP25'!$A$1:$F$520, 6, FALSE) -> - | AP54: =VLOOKUP(B54, 'OCT25'!$A$1:$F$520, 5, FALSE) -> - | AQ54: =VLOOKUP(B54, 'NOV25'!$B$1:$I$616, 5, FALSE) -> - | AR54: =VLOOKUP(B54, 'DEC25'!$A$1:$I$611, 5, FALSE) -> -2 | AS54: =VLOOKUP(B54, 'JAN26'!$A$1:$I$607, 6, FALSE) -> -
A55: GWI | B55: MI0053 - SV42 BRAKE LINING SCANIA | C55: =-AVERAGE(AL55:AV55) -> 0.8125 | D55: -31 | E55: -18.5 | F55: -10 | G55: -25 | H55: -16 | I55: -10 | J55: 0 | K55: -10 | L55: -8 | M55: -4.25 | N55: -13.25 | O55: -26 | P55: -15 | Q55: -10 | R55: -9 | S55: 0 | T55: 0 | U55: -12 | V55: 0 | W55: 0 | X55: 0 | Y55: 0 | Z55: -5 | AA55: 0 | AB55: -2 | AC55: -2.5 | AD55: =VLOOKUP(B55,'OCT24'!$A$1:H1227,6,0) -> -5.5 | AE55: =VLOOKUP(B55,'NOV24'!$A$1:H612,6,0) -> -2.5 | AF55: =VLOOKUP(B55,'DEC24'!$A$1:$H$914,5,0) -> -2.75 | AG55: =VLOOKUP(B55,'JAN25'!$A$1:G683,5,0) -> -1.5 | AH55: =VLOOKUP(B55,'FEB25'!A$1:G1117,5,0) -> -5 | AI55: =VLOOKUP(B55,'MAR25'!$A$1:G950,5,0) -> -5.5 | AJ55: =VLOOKUP(B55,'APR25'!$A$1:G579,5,0) -> 0 | AK55: =VLOOKUP(B55,'MAY25'!$A$1:G972,5,0) -> 0 | AL55: =VLOOKUP(B55,JUNE25!$A$1:G675,5,0) -> -0.25 | AM55: =VLOOKUP(B55, JULY25!$A$1:$E$544, 5, FALSE) -> -2 | AN55: =VLOOKUP(B55, 'AUG25'!$A$1:$E$540, 5, FALSE) -> 0 | AO55: =VLOOKUP(B55, 'SEP25'!$A$1:$F$520, 6, FALSE) -> - | AP55: =VLOOKUP(B55, 'OCT25'!$A$1:$F$520, 5, FALSE) -> - | AQ55: =VLOOKUP(B55, 'NOV25'!$B$1:$I$616, 5, FALSE) -> - | AR55: =VLOOKUP(B55, 'DEC25'!$A$1:$I$611, 5, FALSE) -> - | AS55: =VLOOKUP(B55, 'JAN26'!$A$1:$I$607, 6, FALSE) -> -1
A56: GWI | B56: MI0054 - VL87 BRAKE LINING VOLVO | C56: =-AVERAGE(AL56:AV56) -> 3.90625 | D56: -6 | E56: -10 | F56: -6 | G56: -8.25 | H56: -6.25 | I56: -8.25 | J56: -5 | K56: -3.5 | L56: -5.75 | M56: -6.5 | N56: -3.25 | O56: -5.5 | P56: -6.25 | Q56: -9.25 | R56: -4.25 | S56: -6 | T56: -1 | U56: -4 | V56: -5 | W56: -2 | X56: -3 | Y56: 0 | Z56: 0 | AA56: -1 | AD56: =VLOOKUP(B56,'OCT24'!$A$1:H1228,6,0) -> -6.5 | AE56: =VLOOKUP(B56,'NOV24'!$A$1:H613,6,0) -> -1 | AF56: =VLOOKUP(B56,'DEC24'!$A$1:$H$914,5,0) -> -4 | AG56: =VLOOKUP(B56,'JAN25'!$A$1:G684,5,0) -> -3.5 | AH56: =VLOOKUP(B56,'FEB25'!A$1:G1118,5,0) -> 0 | AI56: =VLOOKUP(B56,'MAR25'!$A$1:G951,5,0) -> -0.5 | AJ56: =VLOOKUP(B56,'APR25'!$A$1:G580,5,0) -> -2 | AK56: =VLOOKUP(B56,'MAY25'!$A$1:G973,5,0) -> -7.25 | AL56: =VLOOKUP(B56,JUNE25!$A$1:G676,5,0) -> -5 | AM56: =VLOOKUP(B56, JULY25!$A$1:$E$544, 5, FALSE) -> -2.75 | AN56: =VLOOKUP(B56, 'AUG25'!$A$1:$E$540, 5, FALSE) -> -4.5 | AO56: =VLOOKUP(B56, 'SEP25'!$A$1:$F$520, 6, FALSE) -> -5.25 | AP56: =VLOOKUP(B56, 'OCT25'!$A$1:$F$520, 5, FALSE) -> -4 | AQ56: =VLOOKUP(B56, 'NOV25'!$B$1:$I$616, 5, FALSE) -> -3.75 | AR56: =VLOOKUP(B56, 'DEC25'!$A$1:$I$611, 5, FALSE) -> -5 | AS56: =VLOOKUP(B56, 'JAN26'!$A$1:$I$607, 6, FALSE) -> -1
A57: GWI | B57: MI0055 - VL88 BRAKE LINING VOLVO | C57: =-AVERAGE(AL57:AV57) -> 8.71875 | D57: -17.5 | E57: -18.5 | F57: -7.25 | G57: -6.5 | H57: -4.25 | I57: -9.5 | J57: -6.75 | K57: -2.75 | L57: -12.5 | M57: -1.5 | N57: -9.5 | O57: -14 | P57: -17 | Q57: -21.75 | R57: -6.5 | S57: -6.5 | T57: -3.75 | U57: -9.5 | V57: -17.25 | W57: -8 | X57: -12.5 | Y57: -3 | Z57: 0 | AA57: 0 | AB57: -3 | AC57: -3 | AD57: =VLOOKUP(B57,'OCT24'!$A$1:H1229,6,0) -> -10.25 | AE57: =VLOOKUP(B57,'NOV24'!$A$1:H614,6,0) -> -4 | AF57: =VLOOKUP(B57,'DEC24'!$A$1:$H$914,5,0) -> -9.5 | AG57: =VLOOKUP(B57,'JAN25'!$A$1:G685,5,0) -> -1.25 | AH57: =VLOOKUP(B57,'FEB25'!A$1:G1119,5,0) -> 0 | AI57: =VLOOKUP(B57,'MAR25'!$A$1:G952,5,0) -> -1 | AJ57: =VLOOKUP(B57,'APR25'!$A$1:G581,5,0) -> -2.75 | AK57: =VLOOKUP(B57,'MAY25'!$A$1:G974,5,0) -> -3.75 | AL57: =VLOOKUP(B57,JUNE25!$A$1:G677,5,0) -> -1 | AM57: =VLOOKUP(B57, JULY25!$A$1:$E$544, 5, FALSE) -> -8.5 | AN57: =VLOOKUP(B57, 'AUG25'!$A$1:$E$540, 5, FALSE) -> -9.75 | AO57: =VLOOKUP(B57, 'SEP25'!$A$1:$F$520, 6, FALSE) -> -5 | AP57: =VLOOKUP(B57, 'OCT25'!$A$1:$F$520, 5, FALSE) -> -4 | AQ57: =VLOOKUP(B57, 'NOV25'!$B$1:$I$616, 5, FALSE) -> -11.5 | AR57: =VLOOKUP(B57, 'DEC25'!$A$1:$I$611, 5, FALSE) -> -15.75 | AS57: =VLOOKUP(B57, 'JAN26'!$A$1:$I$607, 6, FALSE) -> -14.25
B58: MI0056 - VL89 BRAKE LINING VOLVO | C58: =-AVERAGE(AL58:AV58) -> 0 | D58: 0 | E58: -0.5 | F58: 0 | G58: 0 | H58: 0 | I58: 0 | J58: 0 | K58: 0 | L58: 0 | M58: 0 | N58: 0 | O58: 0 | P58: -0.25 | Q58: 0 | R58: 0 | S58: 0 | T58: 0 | U58: 0 | V58: 0 | W58: 0 | X58: 0 | Y58: 0 | Z58: 0 | AA58: 0 | AB58: 0 | AC58: 0 | AD58: =VLOOKUP(B58,'OCT24'!$A$1:H1230,6,0) -> 0 | AE58: =VLOOKUP(B58,'NOV24'!$A$1:H615,6,0) -> 0 | AF58: =VLOOKUP(B58,'DEC24'!$A$1:$H$914,5,0) -> 0 | AG58: =VLOOKUP(B58,'JAN25'!$A$1:G686,5,0) -> 0 | AH58: =VLOOKUP(B58,'FEB25'!A$1:G1120,5,0) -> 0 | AI58: =VLOOKUP(B58,'MAR25'!$A$1:G953,5,0) -> 0 | AJ58: =VLOOKUP(B58,'APR25'!$A$1:G582,5,0) -> 0 | AK58: =VLOOKUP(B58,'MAY25'!$A$1:G975,5,0) -> 0 | AL58: =VLOOKUP(B58,JUNE25!$A$1:G678,5,0) -> 0 | AM58: =VLOOKUP(B58, JULY25!$A$1:$E$544, 5, FALSE) -> 0 | AN58: =VLOOKUP(B58, 'AUG25'!$A$1:$E$540, 5, FALSE) -> 0 | AO58: =VLOOKUP(B58, 'SEP25'!$A$1:$F$520, 6, FALSE) -> - | AP58: =VLOOKUP(B58, 'OCT25'!$A$1:$F$520, 5, FALSE) -> - | AQ58: =VLOOKUP(B58, 'NOV25'!$B$1:$I$616, 5, FALSE) -> - | AR58: =VLOOKUP(B58, 'DEC25'!$A$1:$I$611, 5, FALSE) -> - | AS58: =VLOOKUP(B58, 'JAN26'!$A$1:$I$607, 6, FALSE) -> -
A59: GWI | B59: MI0057 - BC37 BRAKE LINING BPW 8" | C59: =-AVERAGE(AL59:AV59) -> 61.34375 | D59: -13.75 | E59: -30.75 | F59: -22.25 | G59: -17.5 | H59: -15.5 | I59: -31.5 | J59: -18.5 | K59: -14 | L59: -11.5 | M59: -47.5 | N59: -42 | O59: -17 | P59: -8 | Q59: -18.25 | R59: -76.75 | S59: -29 | U59: -32.75 | V59: -37 | W59: -56.25 | X59: -40 | Y59: -97 | Z59: -63 | AA59: -85 | AC59: -68.5 | AD59: =VLOOKUP(B59,'OCT24'!$A$1:H1231,6,0) -> -69 | AF59: =VLOOKUP(B59,'DEC24'!$A$1:$H$914,5,0) -> -78.5 | AH59: =VLOOKUP(B59,'FEB25'!A$1:G1121,5,0) -> -71.25 | AI59: =VLOOKUP(B59,'MAR25'!$A$1:G954,5,0) -> -95.75 | AJ59: =VLOOKUP(B59,'APR25'!$A$1:G583,5,0) -> -69 | AL59: =VLOOKUP(B59,JUNE25!$A$1:G679,5,0) -> -78.5 | AM59: =VLOOKUP(B59, JULY25!$A$1:$E$544, 5, FALSE) -> -84 | AN59: =VLOOKUP(B59, 'AUG25'!$A$1:$E$540, 5, FALSE) -> -48.25 | AO59: =VLOOKUP(B59, 'SEP25'!$A$1:$F$520, 6, FALSE) -> -23 | AP59: =VLOOKUP(B59, 'OCT25'!$A$1:$F$520, 5, FALSE) -> -125.5 | AQ59: =VLOOKUP(B59, 'NOV25'!$B$1:$I$616, 5, FALSE) -> -58.25 | AR59: =VLOOKUP(B59, 'DEC25'!$A$1:$I$611, 5, FALSE) -> -20 | AS59: =VLOOKUP(B59, 'JAN26'!$A$1:$I$607, 6, FALSE) -> -53.25
B60: MI0058 - 29087-PREMIUM BRAKE PAD | C60: 0 | D60: 0 | E60: 0 | F60: 0 | G60: 0 | H60: 0 | I60: 0 | J60: 0 | K60: 0 | L60: 0 | M60: 0 | N60: 0 | O60: 0 | P60: 0 | Q60: 0 | R60: 0 | S60: 0 | T60: 0 | U60: 0 | V60: 0 | W60: 0 | X60: 0 | Y60: 0 | Z60: 0
B61: MI0059 - RIVETING MACHINE | C61: =-AVERAGE(AL61:AV61) -> 0 | D61: 0 | E61: 0 | F61: 0 | G61: 0 | H61: 0 | I61: 0 | J61: -1 | K61: 0 | L61: 0 | M61: 0 | N61: 0 | O61: 0 | P61: 0 | Q61: 0 | R61: 0 | S61: 0 | T61: 0 | U61: 0 | V61: 0 | W61: 0 | X61: -1 | Y61: 0 | Z61: 0 | AA61: 0 | AB61: 0 | AC61: 0 | AD61: =VLOOKUP(B61,'OCT24'!$A$1:H1233,6,0) -> -1 | AE61: =VLOOKUP(B61,'NOV24'!$A$1:H618,6,0) -> 0 | AF61: =VLOOKUP(B61,'DEC24'!$A$1:$H$914,5,0) -> 0 | AG61: =VLOOKUP(B61,'JAN25'!$A$1:G689,5,0) -> 0 | AH61: =VLOOKUP(B61,'FEB25'!A$1:G1123,5,0) -> 0 | AI61: =VLOOKUP(B61,'MAR25'!$A$1:G956,5,0) -> 0 | AJ61: =VLOOKUP(B61,'APR25'!$A$1:G585,5,0) -> 0 | AK61: =VLOOKUP(B61,'MAY25'!$A$1:G978,5,0) -> 0 | AL61: =VLOOKUP(B61,JUNE25!$A$1:G681,5,0) -> 0 | AM61: =VLOOKUP(B61, JULY25!$A$1:$E$544, 5, FALSE) -> 0 | AN61: =VLOOKUP(B61, 'AUG25'!$A$1:$E$540, 5, FALSE) -> 0 | AO61: =VLOOKUP(B61, 'SEP25'!$A$1:$F$520, 6, FALSE) -> - | AP61: =VLOOKUP(B61, 'OCT25'!$A$1:$F$520, 5, FALSE) -> - | AQ61: =VLOOKUP(B61, 'NOV25'!$B$1:$I$616, 5, FALSE) -> - | AR61: =VLOOKUP(B61, 'DEC25'!$A$1:$I$611, 5, FALSE) -> - | AS61: =VLOOKUP(B61, 'JAN26'!$A$1:$I$607, 6, FALSE) -> -
A62: AIRBAGS | B62: MI0060 - W01M586364 AIRBAG 5813K | C62: =-AVERAGE(AL62:AV62) -> 35.25 | D62: -45 | E62: -47 | F62: -39 | G62: -15 | H62: -31 | I62: -43 | J62: -44 | K62: -24 | L62: -39 | M62: -46 | N62: -40 | O62: -51 | P62: -64 | Q62: -42 | R62: -72 | S62: -24 | T62: -51 | V62: -14 | W62: -35 | X62: -28 | Y62: -24 | Z62: -32 | AA62: -51 | AB62: -55 | AC62: -33 | AD62: =VLOOKUP(B62,'OCT24'!$A$1:H1234,6,0) -> -45 | AE62: =VLOOKUP(B62,'NOV24'!$A$1:H619,6,0) -> -46 | AF62: =VLOOKUP(B62,'DEC24'!$A$1:$H$914,5,0) -> -31 | AG62: =VLOOKUP(B62,'JAN25'!$A$1:G690,5,0) -> -23 | AH62: =VLOOKUP(B62,'FEB25'!A$1:G1124,5,0) -> -36 | AI62: =VLOOKUP(B62,'MAR25'!$A$1:G957,5,0) -> -28 | AJ62: =VLOOKUP(B62,'APR25'!$A$1:G586,5,0) -> -45 | AL62: =VLOOKUP(B62,JUNE25!$A$1:G682,5,0) -> -50 | AM62: =VLOOKUP(B62, JULY25!$A$1:$E$544, 5, FALSE) -> -6 | AN62: =VLOOKUP(B62, 'AUG25'!$A$1:$E$540, 5, FALSE) -> -49 | AO62: =VLOOKUP(B62, 'SEP25'!$A$1:$F$520, 6, FALSE) -> -60 | AP62: =VLOOKUP(B62, 'OCT25'!$A$1:$F$520, 5, FALSE) -> -24 | AQ62: =VLOOKUP(B62, 'NOV25'!$B$1:$I$616, 5, FALSE) -> -24 | AR62: =VLOOKUP(B62, 'DEC25'!$A$1:$I$611, 5, FALSE) -> -49 | AS62: =VLOOKUP(B62, 'JAN26'!$A$1:$I$607, 6, FALSE) -> -20
B63: MI0061 - WVA29124 BRAKE PAD ROR | C63: =-AVERAGE(AL63:AV63) -> 0 | D63: -1 | E63: 0 | F63: -2 | G63: 0 | H63: 0 | I63: 0 | J63: 0 | K63: 0 | L63: 0 | M63: 0 | N63: 0 | O63: 0 | P63: 0 | Q63: 0 | R63: 0 | S63: 0 | T63: 0 | U63: 0 | V63: 0 | W63: 0 | X63: 0 | Y63: 0 | Z63: 0 | AA63: 0 | AB63: 0 | AC63: 0 | AD63: =VLOOKUP(B63,'OCT24'!$A$1:H1235,6,0) -> 0 | AE63: =VLOOKUP(B63,'NOV24'!$A$1:H620,6,0) -> 0 | AF63: =VLOOKUP(B63,'DEC24'!$A$1:$H$914,5,0) -> 0 | AG63: =VLOOKUP(B63,'JAN25'!$A$1:G691,5,0) -> 0 | AH63: =VLOOKUP(B63,'FEB25'!A$1:G1125,5,0) -> 0 | AI63: =VLOOKUP(B63,'MAR25'!$A$1:G958,5,0) -> 0 | AJ63: =VLOOKUP(B63,'APR25'!$A$1:G587,5,0) -> 0 | AK63: =VLOOKUP(B63,'MAY25'!$A$1:G980,5,0) -> 0 | AL63: =VLOOKUP(B63,JUNE25!$A$1:G683,5,0) -> 0 | AM63: =VLOOKUP(B63, JULY25!$A$1:$E$544, 5, FALSE) -> 0 | AN63: =VLOOKUP(B63, 'AUG25'!$A$1:$E$540, 5, FALSE) -> 0 | AO63: =VLOOKUP(B63, 'SEP25'!$A$1:$F$520, 6, FALSE) -> - | AP63: =VLOOKUP(B63, 'OCT25'!$A$1:$F$520, 5, FALSE) -> - | AQ63: =VLOOKUP(B63, 'NOV25'!$B$1:$I$616, 5, FALSE) -> - | AR63: =VLOOKUP(B63, 'DEC25'!$A$1:$I$611, 5, FALSE) -> - | AS63: =VLOOKUP(B63, 'JAN26'!$A$1:$I$607, 6, FALSE) -> -
B64: MI0061 - WVA29124 BRAKE PAD ROR | C64: =-AVERAGE(AL64:AV64) -> 0 | AN64: =VLOOKUP(B64, 'AUG25'!$A$1:$E$792, 5, FALSE) -> 0 | AO64: =VLOOKUP(B64, 'SEP25'!$A$1:$F$520, 6, FALSE) -> - | AP64: =VLOOKUP(B64, 'OCT25'!$A$1:$F$520, 5, FALSE) -> - | AQ64: =VLOOKUP(B64, 'NOV25'!$B$1:$I$616, 5, FALSE) -> - | AR64: =VLOOKUP(B64, 'DEC25'!$A$1:$I$611, 5, FALSE) -> - | AS64: =VLOOKUP(B64, 'JAN26'!$A$1:$I$607, 6, FALSE) -> -
B65: MI0062 - U BOLT HOWO | C65: 0 | D65: 0 | E65: 0 | F65: 0 | G65: 0 | H65: 0 | I65: 0 | J65: 0 | K65: 0 | L65: 0 | M65: 0 | N65: 0 | O65: 0 | P65: 0 | Q65: 0 | R65: 0 | S65: 0 | T65: 0 | U65: 0 | V65: 0 | W65: 0 | X65: 0 | Y65: 0 | Z65: 0
B66: MI0063 - W01-358-6226 | C66: 0 | D66: 0 | E66: 0 | F66: 0 | G66: 0 | H66: 0 | I66: 0 | J66: 0 | K66: 0 | L66: 0 | M66: 0 | N66: 0 | O66: 0 | P66: 0 | Q66: 0 | R66: 0 | S66: 0 | T66: 0 | U66: 0 | V66: 0 | W66: 0 | X66: 0 | Y66: 0 | Z66: 0
A67: SPARES | B67: MI0064 - BRAKE SHOE BC36 | C67: =-AVERAGE(AL67:AV67) -> 1.5 | D67: 0 | E67: 0 | F67: 0 | G67: 0 | H67: 0 | I67: -12 | J67: 0 | K67: -3 | L67: 0 | M67: 0 | N67: -2 | O67: 0 | P67: 0 | Q67: 0 | R67: 0 | S67: -9 | T67: 0 | U67: -8 | V67: -12 | W67: -16 | X67: 0 | Y67: 0 | Z67: 0 | AA67: -2 | AB67: -10 | AC67: 0 | AD67: =VLOOKUP(B67,'OCT24'!$A$1:H1238,6,0) -> 0 | AE67: =VLOOKUP(B67,'NOV24'!$A$1:H623,6,0) -> 0 | AF67: =VLOOKUP(B67,'DEC24'!$A$1:$H$914,5,0) -> 0 | AG67: =VLOOKUP(B67,'JAN25'!$A$1:G694,5,0) -> -6 | AH67: =VLOOKUP(B67,'FEB25'!A$1:G1128,5,0) -> 0 | AI67: =VLOOKUP(B67,'MAR25'!$A$1:G961,5,0) -> -4 | AJ67: =VLOOKUP(B67,'APR25'!$A$1:G590,5,0) -> -16 | AK67: =VLOOKUP(B67,'MAY25'!$A$1:G983,5,0) -> 0 | AL67: =VLOOKUP(B67,JUNE25!$A$1:G686,5,0) -> 0 | AM67: =VLOOKUP(B67, JULY25!$A$1:$E$544, 5, FALSE) -> 0 | AN67: =VLOOKUP(B67, 'AUG25'!$A$1:$E$540, 5, FALSE) -> -2 | AO67: =VLOOKUP(B67, 'SEP25'!$A$1:$F$520, 6, FALSE) -> -4 | AP67: =VLOOKUP(B67, 'OCT25'!$A$1:$F$520, 5, FALSE) -> -2 | AQ67: =VLOOKUP(B67, 'NOV25'!$B$1:$I$616, 5, FALSE) -> -1 | AR67: =VLOOKUP(B67, 'DEC25'!$A$1:$I$611, 5, FALSE) -> - | AS67: =VLOOKUP(B67, 'JAN26'!$A$1:$I$607, 6, FALSE) -> -
A68: SPARES | B68: MI0065 - 4515 BRAKE SHOE COMP OR HENDRED | C68: =-AVERAGE(AL68:AV68) -> 24.375 | D68: -18 | E68: -4 | F68: -13 | G68: -26 | H68: -16 | I68: -7 | J68: -12 | K68: 0 | L68: 0 | M68: -21 | N68: -28 | O68: -35 | P68: -27 | Q68: -21 | R68: -6 | S68: -30 | T68: -56 | U68: -4 | W68: -6 | X68: -29 | Y68: -30 | Z68: -8 | AB68: -57 | AC68: -15 | AD68: =VLOOKUP(B68,'OCT24'!$A$1:H1239,6,0) -> 0 | AE68: =VLOOKUP(B68,'NOV24'!$A$1:H624,6,0) -> -6 | AF68: =VLOOKUP(B68,'DEC24'!$A$1:$H$914,5,0) -> -12 | AG68: =VLOOKUP(B68,'JAN25'!$A$1:G695,5,0) -> -9 | AH68: =VLOOKUP(B68,'FEB25'!A$1:G1129,5,0) -> -15 | AI68: =VLOOKUP(B68,'MAR25'!$A$1:G962,5,0) -> -74 | AJ68: =VLOOKUP(B68,'APR25'!$A$1:G591,5,0) -> -51 | AK68: =VLOOKUP(B68,'MAY25'!$A$1:G984,5,0) -> -61 | AL68: =VLOOKUP(B68,JUNE25!$A$1:G687,5,0) -> -15 | AM68: =VLOOKUP(B68, JULY25!$A$1:$E$544, 5, FALSE) -> -3 | AN68: =VLOOKUP(B68, 'AUG25'!$A$1:$E$540, 5, FALSE) -> -18 | AO68: =VLOOKUP(B68, 'SEP25'!$A$1:$F$520, 6, FALSE) -> -2 | AP68: =VLOOKUP(B68, 'OCT25'!$A$1:$F$520, 5, FALSE) -> -34 | AQ68: =VLOOKUP(B68, 'NOV25'!$B$1:$I$616, 5, FALSE) -> -49 | AR68: =VLOOKUP(B68, 'DEC25'!$A$1:$I$611, 5, FALSE) -> -27 | AS68: =VLOOKUP(B68, 'JAN26'!$A$1:$I$607, 6, FALSE) -> -47
B69: MI0066 - W01-M58-8966 | C69: =-AVERAGE(AL69:AV69) -> 36.5 | D69: -38 | E69: -24 | F69: -16 | G69: -14 | H69: -12 | I69: -42 | L69: -21 | M69: -42 | N69: -50 | O69: -43 | P69: -44 | Q69: -30 | R69: -13 | S69: -31 | T69: -9 | U69: -10 | V69: -9 | W69: -15 | X69: -9 | Y69: -18 | Z69: -15 | AA69: -13 | AB69: -17 | AC69: -24 | AD69: =VLOOKUP(B69,'OCT24'!$A$1:H1240,6,0) -> -44 | AE69: =VLOOKUP(B69,'NOV24'!$A$1:H625,6,0) -> -7 | AF69: =VLOOKUP(B69,'DEC24'!$A$1:$H$914,5,0) -> -40 | AG69: =VLOOKUP(B69,'JAN25'!$A$1:G696,5,0) -> -11 | AH69: =VLOOKUP(B69,'FEB25'!A$1:G1130,5,0) -> -39 | AI69: =VLOOKUP(B69,'MAR25'!$A$1:G963,5,0) -> -15 | AJ69: =VLOOKUP(B69,'APR25'!$A$1:G592,5,0) -> -28 | AK69: =VLOOKUP(B69,'MAY25'!$A$1:G985,5,0) -> -35 | AL69: =VLOOKUP(B69,JUNE25!$A$1:G688,5,0) -> -36 | AM69: =VLOOKUP(B69, JULY25!$A$1:$E$544, 5, FALSE) -> -15 | AN69: =VLOOKUP(B69, 'AUG25'!$A$1:$E$540, 5, FALSE) -> -42 | AO69: =VLOOKUP(B69, 'SEP25'!$A$1:$F$520, 6, FALSE) -> -35 | AP69: =VLOOKUP(B69, 'OCT25'!$A$1:$F$520, 5, FALSE) -> -38 | AQ69: =VLOOKUP(B69, 'NOV25'!$B$1:$I$616, 5, FALSE) -> -33 | AR69: =VLOOKUP(B69, 'DEC25'!$A$1:$I$611, 5, FALSE) -> -53 | AS69: =VLOOKUP(B69, 'JAN26'!$A$1:$I$607, 6, FALSE) -> -40
A70: SPARES | B70: MI0067 - HENDRED BRAKE SHOE SPRING LONG | C70: =-AVERAGE(AL70:AV70) -> 107.875 | D70: -57 | E70: -20 | F70: 0 | G70: -25 | H70: -60 | I70: -8 | J70: -140 | K70: -39 | L70: -70 | M70: -7 | N70: -1 | O70: -41 | P70: -188 | Q70: -28 | R70: -54 | S70: -19 | T70: -103 | U70: -30 | V70: -58 | W70: -65 | X70: -152 | Y70: -108 | Z70: -162 | AA70: -84 | AB70: -90 | AC70: -83 | AD70: =VLOOKUP(B70,'OCT24'!$A$1:H1241,6,0) -> -142 | AE70: =VLOOKUP(B70,'NOV24'!$A$1:H626,6,0) -> -148 | AF70: =VLOOKUP(B70,'DEC24'!$A$1:$H$914,5,0) -> -53 | AG70: =VLOOKUP(B70,'JAN25'!$A$1:G697,5,0) -> -120 | AH70: =VLOOKUP(B70,'FEB25'!A$1:G1131,5,0) -> -219 | AI70: =VLOOKUP(B70,'MAR25'!$A$1:G964,5,0) -> -190 | AJ70: =VLOOKUP(B70,'APR25'!$A$1:G593,5,0) -> -206 | AK70: =VLOOKUP(B70,'MAY25'!$A$1:G986,5,0) -> -224 | AL70: =VLOOKUP(B70,JUNE25!$A$1:G689,5,0) -> -212 | AM70: =VLOOKUP(B70, JULY25!$A$1:$E$544, 5, FALSE) -> -75 | AN70: =VLOOKUP(B70, 'AUG25'!$A$1:$E$540, 5, FALSE) -> -59 | AO70: =VLOOKUP(B70, 'SEP25'!$A$1:$F$520, 6, FALSE) -> -29 | AP70: =VLOOKUP(B70, 'OCT25'!$A$1:$F$520, 5, FALSE) -> -8 | AQ70: =VLOOKUP(B70, 'NOV25'!$B$1:$I$616, 5, FALSE) -> -65 | AR70: =VLOOKUP(B70, 'DEC25'!$A$1:$I$611, 5, FALSE) -> -238 | AS70: =VLOOKUP(B70, 'JAN26'!$A$1:$I$607, 6, FALSE) -> -177
A71: SPARES | B71: MI0068 - HENDRED BRAKE SHOE SPRING SHORT | C71: =-AVERAGE(AL71:AV71) -> 205.625 | D71: -18 | E71: -64 | F71: -2 | G71: -84 | H71: -20 | I71: -87 | J71: -88 | K71: -32 | L71: -20 | M71: -36 | N71: -32 | O71: -31 | P71: -70 | Q71: -76 | R71: -77 | S71: -46 | T71: -196 | U71: -40 | V71: -66 | W71: -74 | X71: -232 | Y71: -112 | Z71: -75 | AA71: -106 | AB71: -211 | AC71: -150 | AD71: =VLOOKUP(B71,'OCT24'!$A$1:H1242,6,0) -> -242 | AE71: =VLOOKUP(B71,'NOV24'!$A$1:H627,6,0) -> -210 | AF71: =VLOOKUP(B71,'DEC24'!$A$1:$H$914,5,0) -> -220 | AG71: =VLOOKUP(B71,'JAN25'!$A$1:G698,5,0) -> -178 | AH71: =VLOOKUP(B71,'FEB25'!A$1:G1132,5,0) -> -224 | AI71: =VLOOKUP(B71,'MAR25'!$A$1:G965,5,0) -> -290 | AJ71: =VLOOKUP(B71,'APR25'!$A$1:G594,5,0) -> -248 | AK71: =VLOOKUP(B71,'MAY25'!$A$1:G987,5,0) -> -396 | AL71: =VLOOKUP(B71,JUNE25!$A$1:G690,5,0) -> -310 | AM71: =VLOOKUP(B71, JULY25!$A$1:$E$544, 5, FALSE) -> -228 | AN71: =VLOOKUP(B71, 'AUG25'!$A$1:$E$540, 5, FALSE) -> -168 | AO71: =VLOOKUP(B71, 'SEP25'!$A$1:$F$520, 6, FALSE) -> -79 | AP71: =VLOOKUP(B71, 'OCT25'!$A$1:$F$520, 5, FALSE) -> -93 | AQ71: =VLOOKUP(B71, 'NOV25'!$B$1:$I$616, 5, FALSE) -> -106 | AR71: =VLOOKUP(B71, 'DEC25'!$A$1:$I$611, 5, FALSE) -> -330 | AS71: =VLOOKUP(B71, 'JAN26'!$A$1:$I$607, 6, FALSE) -> -331
B72: MI0069 - BRAKE SHOE ROLLER BPW | C72: =-AVERAGE(AL72:AV72) -> 0 | D72: 0 | E72: -18 | F72: 0 | G72: 0 | H72: 0 | I72: 0 | J72: 0 | K72: 0 | L72: -5 | M72: -2 | N72: -2 | O72: 0 | P72: 0 | Q72: 0 | R72: 0 | S72: 0 | T72: 0 | U72: 0 | V72: -27 | W72: 0 | X72: 0 | Y72: 0 | Z72: 0 | AA72: 0 | AB72: 0 | AC72: 0 | AD72: =VLOOKUP(B72,'OCT24'!$A$1:H1243,6,0) -> 0 | AE72: =VLOOKUP(B72,'NOV24'!$A$1:H628,6,0) -> 0 | AF72: =VLOOKUP(B72,'DEC24'!$A$1:$H$914,5,0) -> 0 | AG72: =VLOOKUP(B72,'JAN25'!$A$1:G699,5,0) -> 0 | AH72: =VLOOKUP(B72,'FEB25'!A$1:G1133,5,0) -> 0 | AI72: =VLOOKUP(B72,'MAR25'!$A$1:G966,5,0) -> 0 | AJ72: =VLOOKUP(B72,'APR25'!$A$1:G595,5,0) -> 0 | AK72: =VLOOKUP(B72,'MAY25'!$A$1:G988,5,0) -> 0 | AL72: =VLOOKUP(B72,JUNE25!$A$1:G691,5,0) -> 0 | AM72: =VLOOKUP(B72, JULY25!$A$1:$E$544, 5, FALSE) -> 0 | AN72: =VLOOKUP(B72, 'AUG25'!$A$1:$E$540, 5, FALSE) -> 0 | AO72: =VLOOKUP(B72, 'SEP25'!$A$1:$F$520, 6, FALSE) -> - | AP72: =VLOOKUP(B72, 'OCT25'!$A$1:$F$520, 5, FALSE) -> - | AQ72: =VLOOKUP(B72, 'NOV25'!$B$1:$I$616, 5, FALSE) -> - | AR72: =VLOOKUP(B72, 'DEC25'!$A$1:$I$611, 5, FALSE) -> - | AS72: =VLOOKUP(B72, 'JAN26'!$A$1:$I$607, 6, FALSE) -> -
A73: SPARES | B73: MI0070 - BRAKE SHOE ROLLER LOCK | C73: =-AVERAGE(AL73:AV73) -> 9.5 | D73: -6 | E73: -1 | F73: 0 | G73: -8 | H73: -14 | I73: -46 | J73: -138 | K73: -4 | L73: -20 | M73: 0 | N73: 0 | O73: 0 | P73: -46 | Q73: -30 | R73: -50 | S73: -1 | T73: -20 | U73: -60 | V73: 0 | W73: -4 | X73: -107 | Y73: -44 | Z73: -45 | AA73: -3 | AB73: 0 | AC73: -65 | AD73: =VLOOKUP(B73,'OCT24'!$A$1:H1244,6,0) -> -40 | AE73: =VLOOKUP(B73,'NOV24'!$A$1:H629,6,0) -> -20 | AF73: =VLOOKUP(B73,'DEC24'!$A$1:$H$914,5,0) -> 0 | AG73: =VLOOKUP(B73,'JAN25'!$A$1:G700,5,0) -> 0 | AH73: =VLOOKUP(B73,'FEB25'!A$1:G1134,5,0) -> 0 | AI73: =VLOOKUP(B73,'MAR25'!$A$1:G967,5,0) -> -2 | AJ73: =VLOOKUP(B73,'APR25'!$A$1:G596,5,0) -> 0 | AK73: =VLOOKUP(B73,'MAY25'!$A$1:G989,5,0) -> 0 | AL73: =VLOOKUP(B73,JUNE25!$A$1:G692,5,0) -> -30 | AM73: =VLOOKUP(B73, JULY25!$A$1:$E$544, 5, FALSE) -> 0 | AN73: =VLOOKUP(B73, 'AUG25'!$A$1:$E$540, 5, FALSE) -> 0 | AO73: =VLOOKUP(B73, 'SEP25'!$A$1:$F$520, 6, FALSE) -> - | AP73: =VLOOKUP(B73, 'OCT25'!$A$1:$F$520, 5, FALSE) -> - | AQ73: =VLOOKUP(B73, 'NOV25'!$B$1:$I$616, 5, FALSE) -> -8 | AR73: =VLOOKUP(B73, 'DEC25'!$A$1:$I$611, 5, FALSE) -> - | AS73: =VLOOKUP(B73, 'JAN26'!$A$1:$I$607, 6, FALSE) -> -
B74: MI0071 - 1858884 | C74: 0 | D74: 0 | E74: 0 | F74: 0 | G74: 0 | H74: 0 | I74: 0 | J74: 0 | K74: 0 | L74: 0 | M74: 0 | N74: 0 | O74: 0 | P74: 0 | Q74: 0 | R74: 0 | S74: 0 | T74: 0 | U74: 0 | V74: 0 | W74: 0 | X74: 0 | Y74: 0 | Z74: 0
A75: SPARES | B75: MI0072 - 8PK2020 / 04.19.077 V BELT SCA P380 BELT TENSION | C75: 0 | D75: 0 | E75: 0 | F75: 0 | G75: 0 | H75: -1 | I75: 0 | J75: 0 | K75: 0 | L75: -1 | M75: -1 | N75: -1 | O75: 0 | P75: 0 | Q75: -2 | R75: 0 | S75: 0 | T75: 0 | U75: 0 | V75: 0 | W75: 0 | X75: 0 | Y75: 0 | Z75: 0
A76: SPARES | B76: MI0073 - 4707 BRAKE LINING | C76: =-AVERAGE(AL76:AV76) -> 3.65625 | D76: -21.5 | E76: -44.25 | F76: -22 | G76: -14.25 | H76: -10.25 | I76: -14.75 | J76: -17.75 | K76: -24.25 | L76: -10.5 | M76: -6.75 | N76: -4.25 | O76: -15 | P76: -7.75 | Q76: -6.75 | R76: -3.25 | S76: -1 | T76: -2 | U76: -2 | V76: -18 | W76: -10.5 | X76: -3.5 | Y76: 0 | Z76: -8.25 | AA76: -2.25 | AB76: -3 | AC76: -4 | AD76: =VLOOKUP(B76,'OCT24'!$A$1:H1247,6,0) -> -3 | AE76: =VLOOKUP(B76,'NOV24'!$A$1:H632,6,0) -> -3.25 | AF76: =VLOOKUP(B76,'DEC24'!$A$1:$H$914,5,0) -> -1.5 | AG76: =VLOOKUP(B76,'JAN25'!$A$1:G703,5,0) -> -8.75 | AH76: =VLOOKUP(B76,'FEB25'!A$1:G1137,5,0) -> -5.5 | AI76: =VLOOKUP(B76,'MAR25'!$A$1:G970,5,0) -> -4 | AJ76: =VLOOKUP(B76,'APR25'!$A$1:G599,5,0) -> -3.75 | AK76: =VLOOKUP(B76,'MAY25'!$A$1:G992,5,0) -> -6.75 | AL76: =VLOOKUP(B76,JUNE25!$A$1:G695,5,0) -> -2.5 | AM76: =VLOOKUP(B76, JULY25!$A$1:$E$544, 5, FALSE) -> -3.25 | AN76: =VLOOKUP(B76, 'AUG25'!$A$1:$E$540, 5, FALSE) -> -4.75 | AO76: =VLOOKUP(B76, 'SEP25'!$A$1:$F$520, 6, FALSE) -> -2 | AP76: =VLOOKUP(B76, 'OCT25'!$A$1:$F$520, 5, FALSE) -> -3 | AQ76: =VLOOKUP(B76, 'NOV25'!$B$1:$I$616, 5, FALSE) -> -7.25 | AR76: =VLOOKUP(B76, 'DEC25'!$A$1:$I$611, 5, FALSE) -> -2.5 | AS76: =VLOOKUP(B76, 'JAN26'!$A$1:$I$607, 6, FALSE) -> -4
B77: MI0074 - 1448933 Oil Cooler | C77: 0 | D77: 0 | E77: 0 | F77: 0 | G77: 0 | H77: 0 | I77: 0 | J77: 0 | K77: 0 | L77: 0 | M77: 0 | N77: 0 | O77: 0 | P77: 0 | Q77: 0 | R77: 0 | S77: 0 | T77: 0 | U77: 0 | V77: 0 | W77: 0 | X77: 0 | Y77: 0 | Z77: 0
B78: MI0075 - 1795526 Oil Cooler Cover | C78: 0 | D78: 0 | E78: 0 | F78: 0 | G78: 0 | H78: 0 | I78: 0 | J78: 0 | K78: 0 | L78: 0 | M78: 0 | N78: 0 | O78: 0 | P78: 0 | Q78: 0 | R78: 0 | S78: 0 | T78: 0 | U78: 0 | V78: 0 | W78: 0 | X78: 0 | Y78: 0 | Z78: 0
B79: MI0076 - OIL COOLER GASKET P380 | C79: 0 | D79: 0 | E79: 0 | F79: 0 | G79: 0 | H79: 0 | I79: 0 | J79: 0 | K79: 0 | L79: 0 | M79: 0 | N79: 0 | O79: 0 | P79: 0 | Q79: 0 | R79: 0 | S79: 0 | T79: 0 | U79: 0 | V79: 0 | W79: 0 | X79: 0 | Y79: 0 | Z79: 0
B80: MI0077 - COMPRESSOR GASKET P380 | C80: 0 | D80: 0 | E80: 0 | F80: 0 | G80: 0 | H80: 0 | I80: 0 | J80: 0 | K80: 0 | L80: 0 | M80: 0 | N80: 0 | O80: 0 | P80: 0 | Q80: 0 | R80: 0 | S80: 0 | T80: 0 | U80: 0 | V80: 0 | W80: 0 | X80: 0 | Y80: 0 | Z80: 0
B81: MI0078 - P50 CROSS JOINT | C81: 0 | D81: 0 | E81: 0 | F81: 0 | G81: 0 | H81: 0 | I81: 0 | J81: 0 | K81: 0 | L81: 0 | M81: 0 | N81: 0 | O81: 0 | P81: 0 | Q81: 0 | R81: 0 | S81: 0 | T81: 0 | U81: 0 | V81: 0 | W81: 0 | X81: 0 | Y81: 0 | Z81: 0
B82: MI0079 - WATER SEPERATOR FILTER WITH HOUSING | C82: 0 | D82: 0 | E82: 0 | F82: 0 | G82: 0 | H82: 0 | I82: 0 | J82: 0 | K82: 0 | L82: 0 | M82: 0 | N82: 0 | O82: 0 | P82: 0 | Q82: 0 | R82: 0 | S82: 0 | T82: 0 | U82: 0 | V82: 0 | W82: 0 | X82: 0 | Y82: 0 | Z82: 0
B83: MI0080 - BPW NUT & BOLT | C83: 0 | D83: 0 | E83: 0 | F83: 0 | G83: 0 | H83: 0 | I83: 0 | J83: 0 | K83: 0 | L83: 0 | M83: 0 | N83: 0 | O83: 0 | P83: 0 | Q83: 0 | R83: 0 | S83: 0 | T83: 0 | U83: 0 | V83: 0 | W83: 0 | X83: 0 | Y83: 0 | Z83: 0
A84: AIRBAGS | B84: MI0081 - W01M587074 AIRBAG | C84: =-AVERAGE(AL84:AV84) -> 31 | D84: -56 | E84: -54 | F84: -46 | G84: -47 | H84: -33 | I84: -58 | J84: -51 | K84: -62 | L84: -36 | M84: -75 | N84: -83 | O84: -40 | P84: -43 | Q84: -38 | R84: -23 | S84: -18 | T84: -8 | U84: -22 | V84: -22 | W84: -10 | X84: -13 | Y84: -10 | Z84: -11 | AA84: -26 | AB84: -23 | AC84: -20 | AD84: =VLOOKUP(B84,'OCT24'!$A$1:H1255,6,0) -> -25 | AE84: =VLOOKUP(B84,'NOV24'!$A$1:H640,6,0) -> -31 | AF84: =VLOOKUP(B84,'DEC24'!$A$1:$H$914,5,0) -> -11 | AG84: =VLOOKUP(B84,'JAN25'!$A$1:G711,5,0) -> -13 | AH84: =VLOOKUP(B84,'FEB25'!A$1:G1145,5,0) -> -14 | AI84: =VLOOKUP(B84,'MAR25'!$A$1:G978,5,0) -> -9 | AJ84: =VLOOKUP(B84,'APR25'!$A$1:G607,5,0) -> -11 | AK84: =VLOOKUP(B84,'MAY25'!$A$1:G1000,5,0) -> -15 | AL84: =VLOOKUP(B84,JUNE25!$A$1:G703,5,0) -> -28 | AM84: =VLOOKUP(B84, JULY25!$A$1:$E$544, 5, FALSE) -> -31 | AN84: =VLOOKUP(B84, 'AUG25'!$A$1:$E$540, 5, FALSE) -> -35 | AO84: =VLOOKUP(B84, 'SEP25'!$A$1:$F$520, 6, FALSE) -> -49 | AP84: =VLOOKUP(B84, 'OCT25'!$A$1:$F$520, 5, FALSE) -> -20 | AQ84: =VLOOKUP(B84, 'NOV25'!$B$1:$I$616, 5, FALSE) -> -17 | AR84: =VLOOKUP(B84, 'DEC25'!$A$1:$I$611, 5, FALSE) -> -30 | AS84: =VLOOKUP(B84, 'JAN26'!$A$1:$I$607, 6, FALSE) -> -38
B85: MI0082 - MMCB BUS FRONT | C85: =-AVERAGE(AL85:AV85) -> 0 | D85: 0 | E85: 0 | F85: 0 | G85: 0 | H85: 0 | I85: 0 | J85: 0 | K85: 0 | L85: 0 | M85: 0 | N85: 0 | O85: 0 | P85: 0 | Q85: 0 | R85: 0 | S85: 0 | T85: 0 | U85: 0 | V85: 0 | W85: 0 | X85: 0 | Y85: 0 | Z85: 0 | AA85: 0 | AB85: 0 | AC85: 0 | AD85: =VLOOKUP(B85,'OCT24'!$A$1:H1256,6,0) -> 0 | AE85: =VLOOKUP(B85,'NOV24'!$A$1:H641,6,0) -> 0 | AF85: =VLOOKUP(B85,'DEC24'!$A$1:$H$914,5,0) -> 0 | AG85: =VLOOKUP(B85,'JAN25'!$A$1:G712,5,0) -> 0 | AH85: =VLOOKUP(B85,'FEB25'!A$1:G1146,5,0) -> 0 | AI85: =VLOOKUP(B85,'MAR25'!$A$1:G979,5,0) -> 0 | AJ85: =VLOOKUP(B85,'APR25'!$A$1:G608,5,0) -> 0 | AK85: =VLOOKUP(B85,'MAY25'!$A$1:G1001,5,0) -> 0 | AL85: =VLOOKUP(B85,JUNE25!$A$1:G704,5,0) -> 0 | AM85: =VLOOKUP(B85, JULY25!$A$1:$E$544, 5, FALSE) -> 0 | AN85: =VLOOKUP(B85, 'AUG25'!$A$1:$E$540, 5, FALSE) -> 0 | AO85: =VLOOKUP(B85, 'SEP25'!$A$1:$F$520, 6, FALSE) -> - | AP85: =VLOOKUP(B85, 'OCT25'!$A$1:$F$520, 5, FALSE) -> - | AQ85: =VLOOKUP(B85, 'NOV25'!$B$1:$I$616, 5, FALSE) -> - | AR85: =VLOOKUP(B85, 'DEC25'!$A$1:$I$611, 5, FALSE) -> - | AS85: =VLOOKUP(B85, 'JAN26'!$A$1:$I$607, 6, FALSE) -> -
B86: MI0083 - MMCB BUS REAR | C86: =-AVERAGE(AL86:AV86) -> 0 | D86: 0 | E86: 0 | F86: 0 | G86: 0 | H86: 0 | I86: 0 | J86: 0 | K86: 0 | L86: 0 | M86: 0 | N86: 0 | O86: 0 | P86: 0 | Q86: 0 | R86: 0 | S86: 0 | T86: 0 | U86: 0 | V86: 0 | W86: 0 | X86: 0 | Y86: 0 | Z86: 0 | AA86: 0 | AB86: 0 | AC86: 0 | AD86: =VLOOKUP(B86,'OCT24'!$A$1:H1257,6,0) -> 0 | AE86: =VLOOKUP(B86,'NOV24'!$A$1:H642,6,0) -> 0 | AF86: =VLOOKUP(B86,'DEC24'!$A$1:$H$914,5,0) -> 0 | AG86: =VLOOKUP(B86,'JAN25'!$A$1:G713,5,0) -> 0 | AH86: =VLOOKUP(B86,'FEB25'!A$1:G1147,5,0) -> 0 | AI86: =VLOOKUP(B86,'MAR25'!$A$1:G980,5,0) -> 0 | AJ86: =VLOOKUP(B86,'APR25'!$A$1:G609,5,0) -> 0 | AK86: =VLOOKUP(B86,'MAY25'!$A$1:G1002,5,0) -> 0 | AL86: =VLOOKUP(B86,JUNE25!$A$1:G705,5,0) -> 0 | AM86: =VLOOKUP(B86, JULY25!$A$1:$E$544, 5, FALSE) -> 0 | AN86: =VLOOKUP(B86, 'AUG25'!$A$1:$E$540, 5, FALSE) -> 0 | AO86: =VLOOKUP(B86, 'SEP25'!$A$1:$F$520, 6, FALSE) -> - | AP86: =VLOOKUP(B86, 'OCT25'!$A$1:$F$520, 5, FALSE) -> - | AQ86: =VLOOKUP(B86, 'NOV25'!$B$1:$I$616, 5, FALSE) -> - | AR86: =VLOOKUP(B86, 'DEC25'!$A$1:$I$611, 5, FALSE) -> - | AS86: =VLOOKUP(B86, 'JAN26'!$A$1:$I$607, 6, FALSE) -> -
A87: TBR | B87: MI0084 - 315/80 R22.5 UNIVERSAL | C87: =-AVERAGE(AL87:AV87) -> 977.42857 | D87: -134 | E87: -377 | F87: -240 | G87: -203 | H87: -166 | I87: -251 | J87: -296 | K87: -339 | L87: -174 | N87: -292 | O87: -237 | P87: -234 | Q87: -339 | R87: -296 | S87: -448 | T87: -455 | U87: -488 | V87: -141 | W87: -353 | X87: -356 | Y87: -420 | Z87: -741 | AA87: -247 | AB87: -374 | AC87: -629 | AD87: =VLOOKUP(B87,'OCT24'!$A$1:H1258,6,0) -> -363 | AE87: =VLOOKUP(B87,'NOV24'!$A$1:H643,6,0) -> -443 | AF87: =VLOOKUP(B87,'DEC24'!$A$1:$H$914,5,0) -> -574 | AG87: =VLOOKUP(B87,'JAN25'!$A$1:G714,5,0) -> -343 | AH87: =VLOOKUP(B87,'FEB25'!A$1:G1148,5,0) -> -963 | AI87: =VLOOKUP(B87,'MAR25'!$A$1:G981,5,0) -> -686 | AK87: =VLOOKUP(B87,'MAY25'!$A$1:G1003,5,0) -> -690 | AL87: =VLOOKUP(B87,JUNE25!$A$1:G706,5,0) -> -699 | AN87: =VLOOKUP(B87, 'AUG25'!$A$1:$E$540, 5, FALSE) -> -635 | AO87: =VLOOKUP(B87, 'SEP25'!$A$1:$F$520, 6, FALSE) -> -1383 | AP87: =VLOOKUP(B87, 'OCT25'!$A$1:$F$520, 5, FALSE) -> -1392 | AQ87: =VLOOKUP(B87, 'NOV25'!$B$1:$I$616, 5, FALSE) -> -1181 | AR87: =VLOOKUP(B87, 'DEC25'!$A$1:$I$611, 5, FALSE) -> -642 | AS87: =VLOOKUP(B87, 'JAN26'!$A$1:$I$607, 6, FALSE) -> -910
A88: TBR | B88: MI0085 - 315/80 R22.5 20PR STEER | C88: =-AVERAGE(AL88:AV88) -> 169.125 | D88: -11 | E88: -55 | F88: -14 | G88: -30 | H88: -58 | I88: -82 | J88: -12 | K88: -21 | L88: -49 | M88: -90 | N88: -51 | O88: -55 | P88: -76 | Q88: -48 | R88: -44 | S88: -52 | T88: -87 | U88: -49 | V88: -46 | W88: -34 | X88: -35 | Y88: -106 | Z88: -71 | AA88: -120 | AB88: -153 | AD88: =VLOOKUP(B88,'OCT24'!$A$1:H1259,6,0) -> -20 | AE88: =VLOOKUP(B88,'NOV24'!$A$1:H644,6,0) -> -66 | AF88: =VLOOKUP(B88,'DEC24'!$A$1:$H$914,5,0) -> -135 | AG88: =VLOOKUP(B88,'JAN25'!$A$1:G715,5,0) -> -63 | AH88: =VLOOKUP(B88,'FEB25'!A$1:G1149,5,0) -> -111 | AI88: =VLOOKUP(B88,'MAR25'!$A$1:G982,5,0) -> -153 | AJ88: =VLOOKUP(B88,'APR25'!$A$1:G611,5,0) -> -129 | AK88: =VLOOKUP(B88,'MAY25'!$A$1:G1004,5,0) -> -121 | AL88: =VLOOKUP(B88,JUNE25!$A$1:G707,5,0) -> -145 | AM88: -100 | AN88: =VLOOKUP(B88, 'AUG25'!$A$1:$E$540, 5, FALSE) -> -142 | AO88: =VLOOKUP(B88, 'SEP25'!$A$1:$F$520, 6, FALSE) -> -177 | AP88: =VLOOKUP(B88, 'OCT25'!$A$1:$F$520, 5, FALSE) -> -296 | AQ88: =VLOOKUP(B88, 'NOV25'!$B$1:$I$616, 5, FALSE) -> -274 | AR88: =VLOOKUP(B88, 'DEC25'!$A$1:$I$611, 5, FALSE) -> -136 | AS88: =VLOOKUP(B88, 'JAN26'!$A$1:$I$607, 6, FALSE) -> -83
A89: TBR | B89: MI0086 - 315/80 R22.5 20PR DIFF | C89: =-AVERAGE(AL89:AV89) -> 313.375 | D89: -120 | E89: -140 | F89: -142 | G89: -168 | H89: -135 | I89: -265 | J89: -334 | K89: -113 | L89: -120 | M89: -134 | N89: -135 | O89: -166 | P89: -155 | Q89: -193 | R89: -111 | S89: -105 | T89: -105 | U89: -63 | V89: -175 | W89: -71 | X89: -132 | Y89: -82 | Z89: -195 | AA89: -91 | AB89: -87 | AC89: -192 | AD89: =VLOOKUP(B89,'OCT24'!$A$1:H1260,6,0) -> -192 | AE89: =VLOOKUP(B89,'NOV24'!$A$1:H645,6,0) -> -140 | AF89: =VLOOKUP(B89,'DEC24'!$A$1:$H$914,5,0) -> -115 | AG89: =VLOOKUP(B89,'JAN25'!$A$1:G716,5,0) -> -186 | AH89: =VLOOKUP(B89,'FEB25'!A$1:G1150,5,0) -> -195 | AI89: =VLOOKUP(B89,'MAR25'!$A$1:G983,5,0) -> -237 | AJ89: =VLOOKUP(B89,'APR25'!$A$1:G612,5,0) -> -311 | AK89: =VLOOKUP(B89,'MAY25'!$A$1:G1005,5,0) -> -254 | AL89: =VLOOKUP(B89,JUNE25!$A$1:G708,5,0) -> -230 | AM89: =VLOOKUP(B89, JULY25!$A$1:$E$544, 5, FALSE) -> -230 | AN89: =VLOOKUP(B89, 'AUG25'!$A$1:$E$540, 5, FALSE) -> -260 | AO89: =VLOOKUP(B89, 'SEP25'!$A$1:$F$520, 6, FALSE) -> -427 | AP89: =VLOOKUP(B89, 'OCT25'!$A$1:$F$520, 5, FALSE) -> -709 | AQ89: =VLOOKUP(B89, 'NOV25'!$B$1:$I$616, 5, FALSE) -> -295 | AR89: =VLOOKUP(B89, 'DEC25'!$A$1:$I$611, 5, FALSE) -> -60 | AS89: =VLOOKUP(B89, 'JAN26'!$A$1:$I$607, 6, FALSE) -> -296
A90: TBR | B90: MI0087 - 385/65 R22.5 20PR SUPER SINGLE | C90: =-AVERAGE(AL90:AV90) -> 221.125 | D90: -368 | E90: -295 | F90: -175 | G90: -262 | H90: -182 | I90: -172 | J90: -129 | L90: -128 | M90: -152 | N90: -208 | O90: -200 | Q90: -193 | R90: -148 | S90: -123 | T90: -66 | U90: -153 | V90: -137 | W90: -119 | X90: -143 | Y90: -162 | Z90: -151 | AA90: -103 | AB90: -17 | AC90: -22 | AD90: =VLOOKUP(B90,'OCT24'!$A$1:H1261,6,0) -> -102 | AE90: =VLOOKUP(B90,'NOV24'!$A$1:H646,6,0) -> -173 | AF90: =VLOOKUP(B90,'DEC24'!$A$1:$H$914,5,0) -> -126 | AG90: =VLOOKUP(B90,'JAN25'!$A$1:G717,5,0) -> -245 | AH90: =VLOOKUP(B90,'FEB25'!A$1:G1151,5,0) -> -127 | AI90: =VLOOKUP(B90,'MAR25'!$A$1:G984,5,0) -> -96 | AJ90: =VLOOKUP(B90,'APR25'!$A$1:G613,5,0) -> -134 | AK90: =VLOOKUP(B90,'MAY25'!$A$1:G1006,5,0) -> -266 | AL90: =VLOOKUP(B90,JUNE25!$A$1:G709,5,0) -> -117 | AM90: =VLOOKUP(B90, JULY25!$A$1:$E$544, 5, FALSE) -> -130 | AN90: =VLOOKUP(B90, 'AUG25'!$A$1:$E$540, 5, FALSE) -> -177 | AO90: =VLOOKUP(B90, 'SEP25'!$A$1:$F$520, 6, FALSE) -> -250 | AP90: =VLOOKUP(B90, 'OCT25'!$A$1:$F$520, 5, FALSE) -> -445 | AQ90: =VLOOKUP(B90, 'NOV25'!$B$1:$I$616, 5, FALSE) -> -293 | AR90: =VLOOKUP(B90, 'DEC25'!$A$1:$I$611, 5, FALSE) -> -217 | AS90: =VLOOKUP(B90, 'JAN26'!$A$1:$I$607, 6, FALSE) -> -140
A91: AIRBAGS | B91: MI0088 - W01M58-9880 AIRBAG | C91: =-AVERAGE(AL91:AV91) -> 0.8 | D91: -1 | E91: -1 | F91: -2 | G91: -2 | H91: 0 | I91: -2 | J91: 0 | K91: 0 | L91: 0 | M91: 0 | N91: 0 | O91: 0 | P91: 0 | Q91: 0 | R91: 0 | S91: -5 | T91: 0 | U91: -4 | V91: -1 | W91: 0 | X91: 0 | Y91: -1 | Z91: 0 | AA91: 0 | AB91: 0 | AC91: 0 | AD91: =VLOOKUP(B91,'OCT24'!$A$1:H1262,6,0) -> 0 | AE91: =VLOOKUP(B91,'NOV24'!$A$1:H647,6,0) -> -3 | AF91: =VLOOKUP(B91,'DEC24'!$A$1:$H$914,5,0) -> -2 | AG91: =VLOOKUP(B91,'JAN25'!$A$1:G718,5,0) -> 0 | AH91: =VLOOKUP(B91,'FEB25'!A$1:G1152,5,0) -> 0 | AI91: =VLOOKUP(B91,'MAR25'!$A$1:G985,5,0) -> 0 | AJ91: =VLOOKUP(B91,'APR25'!$A$1:G614,5,0) -> 0 | AK91: =VLOOKUP(B91,'MAY25'!$A$1:G1007,5,0) -> 0 | AL91: =VLOOKUP(B91,JUNE25!$A$1:G710,5,0) -> 0 | AM91: =VLOOKUP(B91, JULY25!$A$1:$E$544, 5, FALSE) -> -1 | AN91: =VLOOKUP(B91, 'AUG25'!$A$1:$E$540, 5, FALSE) -> 0 | AO91: =VLOOKUP(B91, 'SEP25'!$A$1:$F$520, 6, FALSE) -> -2 | AP91: =VLOOKUP(B91, 'OCT25'!$A$1:$F$520, 5, FALSE) -> - | AQ91: =VLOOKUP(B91, 'NOV25'!$B$1:$I$616, 5, FALSE) -> -1 | AR91: =VLOOKUP(B91, 'DEC25'!$A$1:$I$611, 5, FALSE) -> - | AS91: =VLOOKUP(B91, 'JAN26'!$A$1:$I$607, 6, FALSE) -> -
A92: AIRBAGS | B92: MI0089 - W01M58-8683 AIRBAG | C92: =-AVERAGE(AL92:AV92) -> 2.7142857 | D92: -12 | E92: -3 | F92: 0 | G92: -6 | H92: -7 | I92: -1 | J92: -5 | K92: -1 | L92: 0 | M92: 0 | N92: 0 | O92: 0 | P92: 0 | Q92: 0 | R92: 0 | S92: 0 | T92: 0 | U92: 0 | V92: 0 | W92: 0 | X92: 0 | Y92: 0 | Z92: -6 | AA92: 0 | AB92: 0 | AC92: -1 | AD92: =VLOOKUP(B92,'OCT24'!$A$1:H1263,6,0) -> -1 | AE92: =VLOOKUP(B92,'NOV24'!$A$1:H648,6,0) -> 0 | AF92: =VLOOKUP(B92,'DEC24'!$A$1:$H$914,5,0) -> 0 | AG92: =VLOOKUP(B92,'JAN25'!$A$1:G719,5,0) -> 0 | AH92: =VLOOKUP(B92,'FEB25'!A$1:G1153,5,0) -> 0 | AI92: =VLOOKUP(B92,'MAR25'!$A$1:G986,5,0) -> -1 | AJ92: =VLOOKUP(B92,'APR25'!$A$1:G615,5,0) -> -2 | AK92: =VLOOKUP(B92,'MAY25'!$A$1:G1008,5,0) -> -1 | AL92: =VLOOKUP(B92,JUNE25!$A$1:G711,5,0) -> -1 | AM92: =VLOOKUP(B92, JULY25!$A$1:$E$544, 5, FALSE) -> -11 | AN92: =VLOOKUP(B92, 'AUG25'!$A$1:$E$540, 5, FALSE) -> 0 | AO92: =VLOOKUP(B92, 'SEP25'!$A$1:$F$520, 6, FALSE) -> -3 | AP92: =VLOOKUP(B92, 'OCT25'!$A$1:$F$520, 5, FALSE) -> -1 | AQ92: =VLOOKUP(B92, 'NOV25'!$B$1:$I$616, 5, FALSE) -> - | AR92: =VLOOKUP(B92, 'DEC25'!$A$1:$I$611, 5, FALSE) -> -1 | AS92: =VLOOKUP(B92, 'JAN26'!$A$1:$I$607, 6, FALSE) -> -2
B93: MI0090 - T300 AIR DRIER FILTER | C93: 0 | D93: 0 | E93: -4 | F93: -5 | G93: 0 | H93: 0 | I93: 0 | J93: 0 | K93: 0 | L93: 0 | M93: 0 | N93: 0 | O93: 0 | P93: 0 | Q93: 0 | R93: 0 | S93: 0 | T93: 0 | U93: 0 | V93: 0 | W93: 0 | X93: 0 | Y93: 0 | Z93: 0
A94: SPARES | B94: MI0091 - 32 x 33 WHEEL SPANNER | C94: =-AVERAGE(AL94:AV94) -> 21.285714 | D94: -3 | E94: 0 | F94: 0 | G94: 0 | H94: 0 | I94: 0 | J94: 0 | K94: 0 | L94: 0 | M94: 0 | N94: 0 | O94: 0 | P94: 0 | Q94: 0 | R94: 0 | S94: 0 | T94: 0 | AA94: -22 | AB94: -19 | AC94: -30 | AD94: =VLOOKUP(B94,'OCT24'!$A$1:H1265,6,0) -> -7 | AE94: =VLOOKUP(B94,'NOV24'!$A$1:H650,6,0) -> -16 | AF94: =VLOOKUP(B94,'DEC24'!$A$1:$H$914,5,0) -> -12 | AG94: =VLOOKUP(B94,'JAN25'!$A$1:G721,5,0) -> -20 | AH94: =VLOOKUP(B94,'FEB25'!A$1:G1155,5,0) -> -12 | AI94: =VLOOKUP(B94,'MAR25'!$A$1:G988,5,0) -> -18 | AJ94: =VLOOKUP(B94,'APR25'!$A$1:G617,5,0) -> -57 | AK94: =VLOOKUP(B94,'MAY25'!$A$1:G1010,5,0) -> -17 | AL94: =VLOOKUP(B94,JUNE25!$A$1:G713,5,0) -> -32 | AM94: =VLOOKUP(B94, JULY25!$A$1:$E$544, 5, FALSE) -> -45 | AN94: =VLOOKUP(B94, 'AUG25'!$A$1:$E$540, 5, FALSE) -> -33 | AO94: =VLOOKUP(B94, 'SEP25'!$A$1:$F$520, 6, FALSE) -> -8 | AP94: =VLOOKUP(B94, 'OCT25'!$A$1:$F$520, 5, FALSE) -> -2 | AR94: =VLOOKUP(B94, 'DEC25'!$A$1:$I$611, 5, FALSE) -> -18 | AS94: =VLOOKUP(B94, 'JAN26'!$A$1:$I$607, 6, FALSE) -> -11
B95: MI0093 - HOWO 14 HOLE BRAKE LINING | C95: =-AVERAGE(AL95:AV95) -> 0 | D95: 0 | E95: 0 | F95: 0 | G95: 0 | H95: 0 | I95: 0 | J95: 0 | K95: 0 | L95: 0 | M95: 0 | N95: 0 | O95: 0 | P95: 0 | Q95: 0 | R95: 0 | S95: 0 | T95: 0 | U95: 0 | V95: 0 | W95: 0 | X95: 0 | Y95: 0 | Z95: 0 | AA95: 0 | AB95: 0 | AC95: 0 | AD95: =VLOOKUP(B95,'OCT24'!$A$1:H1267,6,0) -> 0 | AE95: =VLOOKUP(B95,'NOV24'!$A$1:H652,6,0) -> 0 | AF95: =VLOOKUP(B95,'DEC24'!$A$1:$H$914,5,0) -> 0 | AG95: =VLOOKUP(B95,'JAN25'!$A$1:G723,5,0) -> 0 | AH95: =VLOOKUP(B95,'FEB25'!A$1:G1157,5,0) -> 0 | AI95: =VLOOKUP(B95,'MAR25'!$A$1:G990,5,0) -> 0 | AJ95: =VLOOKUP(B95,'APR25'!$A$1:G619,5,0) -> 0 | AK95: =VLOOKUP(B95,'MAY25'!$A$1:G1012,5,0) -> 0 | AL95: =VLOOKUP(B95,JUNE25!$A$1:G715,5,0) -> 0 | AM95: =VLOOKUP(B95, JULY25!$A$1:$E$544, 5, FALSE) -> 0 | AN95: =VLOOKUP(B95, 'AUG25'!$A$1:$E$540, 5, FALSE) -> 0 | AO95: =VLOOKUP(B95, 'SEP25'!$A$1:$F$520, 6, FALSE) -> - | AP95: =VLOOKUP(B95, 'OCT25'!$A$1:$F$520, 5, FALSE) -> - | AQ95: =VLOOKUP(B95, 'NOV25'!$B$1:$I$616, 5, FALSE) -> - | AR95: =VLOOKUP(B95, 'DEC25'!$A$1:$I$611, 5, FALSE) -> - | AS95: =VLOOKUP(B95, 'JAN26'!$A$1:$I$607, 6, FALSE) -> -
A96: GWI | B96: MI0094 - FAW REAR BRAKE LINING | C96: =-AVERAGE(AL96:AV96) -> 14.78125 | D96: -14 | E96: -12 | F96: -18.5 | G96: -13 | H96: -12 | I96: -27.5 | J96: -8 | K96: -19.5 | L96: -10 | M96: -9.5 | N96: -19.5 | O96: -15.5 | P96: -7.75 | Q96: -4 | R96: -3.25 | S96: -14.75 | T96: -3.75 | U96: -25.5 | V96: -8.5 | W96: -4 | X96: -9.5 | Y96: -15.5 | Z96: -10 | AA96: -13.5 | AB96: -11.25 | AD96: =VLOOKUP(B96,'OCT24'!$A$1:H1268,6,0) -> -5.25 | AF96: =VLOOKUP(B96,'DEC24'!$A$1:$H$914,5,0) -> -10.875 | AG96: =VLOOKUP(B96,'JAN25'!$A$1:G724,5,0) -> -6.75 | AH96: =VLOOKUP(B96,'FEB25'!A$1:G1158,5,0) -> -19.25 | AI96: =VLOOKUP(B96,'MAR25'!$A$1:G991,5,0) -> -22 | AJ96: =VLOOKUP(B96,'APR25'!$A$1:G620,5,0) -> -16.5 | AK96: =VLOOKUP(B96,'MAY25'!$A$1:G1013,5,0) -> -12.75 | AL96: =VLOOKUP(B96,JUNE25!$A$1:G716,5,0) -> -22.5 | AM96: =VLOOKUP(B96, JULY25!$A$1:$E$544, 5, FALSE) -> -6 | AN96: =VLOOKUP(B96, 'AUG25'!$A$1:$E$540, 5, FALSE) -> -6 | AO96: =VLOOKUP(B96, 'SEP25'!$A$1:$F$520, 6, FALSE) -> -18 | AP96: =VLOOKUP(B96, 'OCT25'!$A$1:$F$520, 5, FALSE) -> -38.5 | AQ96: =VLOOKUP(B96, 'NOV25'!$B$1:$I$616, 5, FALSE) -> -15 | AR96: =VLOOKUP(B96, 'DEC25'!$A$1:$I$611, 5, FALSE) -> -6.5 | AS96: =VLOOKUP(B96, 'JAN26'!$A$1:$I$607, 6, FALSE) -> -5.75
A97: SPARES | B97: MI0095 - SUZY PIPE RED | C97: =-AVERAGE(AL97:AV97) -> 67.75 | D97: -5 | E97: -7 | F97: -14 | G97: -3 | L97: -42 | M97: -32 | N97: -44 | P97: -48 | Q97: -42 | R97: -55 | S97: -48 | T97: -73 | U97: -58 | V97: -22 | W97: -38 | X97: -3 | Y97: -48 | Z97: -20 | AA97: -34 | AB97: -31 | AC97: -35 | AD97: =VLOOKUP(B97,'OCT24'!$A$1:H1269,6,0) -> -12 | AE97: =VLOOKUP(B97,'NOV24'!$A$1:H654,6,0) -> -48 | AF97: =VLOOKUP(B97,'DEC24'!$A$1:$H$914,5,0) -> -56 | AG97: =VLOOKUP(B97,'JAN25'!$A$1:G725,5,0) -> -37 | AH97: =VLOOKUP(B97,'FEB25'!A$1:G1159,5,0) -> -56 | AI97: =VLOOKUP(B97,'MAR25'!$A$1:G992,5,0) -> -15 | AJ97: =VLOOKUP(B97,'APR25'!$A$1:G621,5,0) -> -29 | AK97: =VLOOKUP(B97,'MAY25'!$A$1:G1014,5,0) -> -40 | AL97: =VLOOKUP(B97,JUNE25!$A$1:G717,5,0) -> -62 | AM97: =VLOOKUP(B97, JULY25!$A$1:$E$544, 5, FALSE) -> -43 | AN97: =VLOOKUP(B97, 'AUG25'!$A$1:$E$540, 5, FALSE) -> -91 | AO97: =VLOOKUP(B97, 'SEP25'!$A$1:$F$520, 6, FALSE) -> -60 | AP97: =VLOOKUP(B97, 'OCT25'!$A$1:$F$520, 5, FALSE) -> -88 | AQ97: =VLOOKUP(B97, 'NOV25'!$B$1:$I$616, 5, FALSE) -> -77 | AR97: =VLOOKUP(B97, 'DEC25'!$A$1:$I$611, 5, FALSE) -> -55 | AS97: =VLOOKUP(B97, 'JAN26'!$A$1:$I$607, 6, FALSE) -> -66
A98: SPARES | B98: MI0096 - SUZY PIPE YELLOW | C98: =-AVERAGE(AL98:AV98) -> 65.75 | D98: -5 | E98: -7 | F98: -13 | G98: -4 | L98: -37 | M98: -41 | N98: -46 | P98: -47 | Q98: -72 | R98: -48 | S98: -47 | T98: -72 | U98: -45 | V98: -21 | W98: -28 | X98: -3 | Y98: -47 | Z98: -54 | AA98: -34 | AB98: -51 | AC98: -14 | AD98: =VLOOKUP(B98,'OCT24'!$A$1:H1270,6,0) -> -10 | AE98: =VLOOKUP(B98,'NOV24'!$A$1:H655,6,0) -> -53 | AF98: =VLOOKUP(B98,'DEC24'!$A$1:$H$914,5,0) -> -50 | AG98: =VLOOKUP(B98,'JAN25'!$A$1:G726,5,0) -> -35 | AH98: =VLOOKUP(B98,'FEB25'!A$1:G1160,5,0) -> -32 | AI98: =VLOOKUP(B98,'MAR25'!$A$1:G993,5,0) -> -18 | AJ98: =VLOOKUP(B98,'APR25'!$A$1:G622,5,0) -> -28 | AK98: =VLOOKUP(B98,'MAY25'!$A$1:G1015,5,0) -> -50 | AL98: =VLOOKUP(B98,JUNE25!$A$1:G718,5,0) -> -66 | AM98: =VLOOKUP(B98, JULY25!$A$1:$E$544, 5, FALSE) -> -48 | AN98: =VLOOKUP(B98, 'AUG25'!$A$1:$E$540, 5, FALSE) -> -104 | AO98: =VLOOKUP(B98, 'SEP25'!$A$1:$F$520, 6, FALSE) -> -70 | AP98: =VLOOKUP(B98, 'OCT25'!$A$1:$F$520, 5, FALSE) -> -76 | AQ98: =VLOOKUP(B98, 'NOV25'!$B$1:$I$616, 5, FALSE) -> -76 | AR98: =VLOOKUP(B98, 'DEC25'!$A$1:$I$611, 5, FALSE) -> -33 | AS98: =VLOOKUP(B98, 'JAN26'!$A$1:$I$607, 6, FALSE) -> -53
A99: SPARES | B99: MI0097 - BC37 BRAKE SHOE | C99: =-AVERAGE(AL99:AV99) -> 5.2 | D99: 0 | E99: -2 | F99: 0 | G99: 0 | H99: 0 | I99: -12 | J99: 0 | K99: 0 | L99: -12 | M99: -2 | N99: -2 | O99: 0 | P99: 0 | Q99: -2 | R99: -2 | S99: 0 | T99: 0 | U99: -1 | V99: 0 | W99: 0 | X99: 0 | Y99: -2 | Z99: 0 | AA99: -2 | AB99: 0 | AC99: -2 | AD99: =VLOOKUP(B99,'OCT24'!$A$1:H1271,6,0) -> 0 | AE99: =VLOOKUP(B99,'NOV24'!$A$1:H656,6,0) -> -2 | AF99: =VLOOKUP(B99,'DEC24'!$A$1:$H$914,5,0) -> -2 | AG99: =VLOOKUP(B99,'JAN25'!$A$1:G727,5,0) -> 0 | AH99: =VLOOKUP(B99,'FEB25'!A$1:G1161,5,0) -> -10 | AI99: =VLOOKUP(B99,'MAR25'!$A$1:G994,5,0) -> 0 | AJ99: =VLOOKUP(B99,'APR25'!$A$1:G623,5,0) -> 0 | AK99: =VLOOKUP(B99,'MAY25'!$A$1:G1016,5,0) -> 0 | AL99: =VLOOKUP(B99,JUNE25!$A$1:G719,5,0) -> 0 | AM99: =VLOOKUP(B99, JULY25!$A$1:$E$544, 5, FALSE) -> 0 | AN99: =VLOOKUP(B99, 'AUG25'!$A$1:$E$540, 5, FALSE) -> 0 | AO99: =VLOOKUP(B99, 'SEP25'!$A$1:$F$520, 6, FALSE) -> - | AP99: =VLOOKUP(B99, 'OCT25'!$A$1:$F$520, 5, FALSE) -> -24 | AQ99: =VLOOKUP(B99, 'NOV25'!$B$1:$I$616, 5, FALSE) -> -2 | AR99: =VLOOKUP(B99, 'DEC25'!$A$1:$I$611, 5, FALSE) -> - | AS99: =VLOOKUP(B99, 'JAN26'!$A$1:$I$607, 6, FALSE) -> -
A100: SPARES | B100: MI0099 - TRAILER SHOCK UP SHORT | C100: =-AVERAGE(AL100:AV100) -> 9.4285714 | D100: -10 | E100: -4 | F100: -20 | G100: -6 | H100: 0 | I100: 0 | J100: -6 | K100: -8 | L100: 0 | M100: -25 | N100: -1 | O100: 0 | P100: -6 | Q100: -1 | R100: 0 | S100: -25 | T100: -14 | U100: 0 | V100: 0 | W100: 0 | X100: 0 | Y100: -20 | Z100: -2 | AA100: -10 | AB100: 0 | AC100: 0 | AD100: =VLOOKUP(B100,'OCT24'!$A$1:H1273,6,0) -> -1 | AE100: =VLOOKUP(B100,'NOV24'!$A$1:H658,6,0) -> 0 | AF100: =VLOOKUP(B100,'DEC24'!$A$1:$H$914,5,0) -> -10 | AG100: =VLOOKUP(B100,'JAN25'!$A$1:G729,5,0) -> -2 | AH100: =VLOOKUP(B100,'FEB25'!A$1:G1163,5,0) -> -2 | AI100: =VLOOKUP(B100,'MAR25'!$A$1:G996,5,0) -> 0 | AJ100: =VLOOKUP(B100,'APR25'!$A$1:G625,5,0) -> 0 | AK100: =VLOOKUP(B100,'MAY25'!$A$1:G1018,5,0) -> 0 | AL100: =VLOOKUP(B100,JUNE25!$A$1:G721,5,0) -> -22 | AM100: =VLOOKUP(B100, JULY25!$A$1:$E$544, 5, FALSE) -> 0 | AN100: =VLOOKUP(B100, 'AUG25'!$A$1:$E$540, 5, FALSE) -> -9 | AO100: =VLOOKUP(B100, 'SEP25'!$A$1:$F$520, 6, FALSE) -> -1 | AP100: =VLOOKUP(B100, 'OCT25'!$A$1:$F$520, 5, FALSE) -> -13 | AQ100: =VLOOKUP(B100, 'NOV25'!$B$1:$I$616, 5, FALSE) -> - | AR100: =VLOOKUP(B100, 'DEC25'!$A$1:$I$611, 5, FALSE) -> -12 | AS100: =VLOOKUP(B100, 'JAN26'!$A$1:$I$607, 6, FALSE) -> -9
...

Sheet TBR
B1: TBR 230PC HC
B2: Updated 0n
B3: =TODAY() -> 46188 | AA3: 3 | AB3: 4
F4: =TODAY()+3 -> 46191 | J4: =F4+31 -> 46222 | N4: =J4+31 -> 46253 | R4: =N4+28 -> 46281 | V4: =R4+30 -> 46311 | Z4: Procurement | AE4: Management | AJ4: 0.5 | AK4: 30 | AM4: 0.3 | AO4: FEB | AP4: FEB | AQ4: FEB | AR4: FEB | AS4: MAR | AT4: MAR | AU4: MAR | AV4: MAR | AW4: MAR | AX4: APR | AY4: APR | AZ4: APR | BA4: APR | BB4: APR | BC4: APR | BD4: APR | BE4: APR | BF4: APR | BG4: APR | BH4: APR | BI4: APR | BJ4: APR | BK4: APR | BL4: APR | BM4: APR | BN4: MAY | BO4: MAY | BP4: MAY | BQ4: JUNE
A5: S.No | B5: Part No. / Description | C5: Opening Stock | D5: Avg Con | E5: INFLOW TOTAL | F5: OB | G5: Inflow | H5: Actual sale | I5: Closing Stock | J5: OB | K5: Inflow | L5: Actual sale | M5: Closing Stock | N5: OB | O5: Inflow | P5: Actual sale | Q5: Closing Stock | R5: OB | S5: Inflow | T5: Actual sale | U5: Closing Stock | V5: OB | W5: Inflow | X5: Actual sale | Y5: Closing Stock | Z5: Stk (in Months) | AA5: Min Stk (In Months) | AB5: Max Stk (In Months) | AC5: Requirement (In Months) | AD5: Requirements (Qty) | AE5: FINAL QTY | AF5: RS PRICE | AG5: RB PRICE | AH5: FDK PRICE | AI5: TRSN PRICE | AJ5: ROADSHINE | AK5: FEDRIK | AL5: THREE A | AM5: ROYALBLACK | AN5: REMARKS | AO5: RS EX-635/25 2HC | AP5: RS EX-644/25 2HC | AQ5: RS 2HC EX-689 WITH tent belts | AR5: RS 2HC EX-672 WTH SPARES | AS5: B - FDK CAX-1109 4HC WtH RB PCR | AT5: RS EX-714/25 2HC WITH PCR | AU5: RB 2HC JT5001C WITH PCR | AV5: RS EX-726 1HC WITH SPARES | AW5: RS EX-741/25 3HC WITH PCR | AX5: FDK 3HC CAX-1017 + RODS | AY5: TRANSTON T25I801 1HC | AZ5: RS 2HC EX-672 WTH SPARES | BA5: RS EX-701/25 3HC with spare in1 | BB5: RB JT5001A 3HC PCR | BC5: RS EX-750/25 2HC WITH LINING | BD5: TS T25I811 4HC WITH RODS | BE5: FDK CAX-1216 2HC WIT RODS | BF5: RB T5112A 5HC WITH PCR | BG5: RS 1HC EX-036/26 WITH CARGO BELTS | BH5: RS 2HC EX-022/26 WITH SPARE | BI5: FDK 4HC CAX-W-113 WITH RODS | BJ5: RB 1 HC 0114A WITH PCR | BK5: RB 1 HC 0114B WITH PCR | BL5: RS 2HC EX-035/26 WIT TARPULIN | BM5: RB DEC ORDER | BN5: RS BALANCE DEC ORDER | BO5: FDK BALANCE ORDER | BP5: RS JAN ORDER | BQ5: RB JAN ORDER
A6: RS602 - RS600 -FA808 | B6: MI0084 - 315/80 R22.5 UNIVERSAL | C6: =VLOOKUP(B6,'JAN26'!$A$1:I909,8,0) -> 644 | D6: =VLOOKUP(B6,AVE!B$1:GB3496,2,0) -> 977.42857 | E6: =G6+K6+O6+S6 -> 7887 | F6: =IF(C6<0,0,C6) -> 644 | G6: =SUM(AO6:AR6) -> 943 | H6: =D6 -> 977.42857 | I6: =(F6+G6)-H6 -> 609.57143 | J6: =IF(I6<0,0,I6) -> 609.57143 | K6: =SUM(AS6:AW6) -> 1353 | L6: =H6 -> 977.42857 | M6: =(J6+K6)-L6 -> 985.14286 | N6: =IF(M6<0,0,M6) -> 985.14286 | O6: =SUM(AX6:BM6) -> 4266 | P6: =L6 -> 977.42857 | Q6: =(N6+O6)-P6 -> 4273.7143 | R6: =IF(Q6<0,0,Q6) -> 4273.7143 | S6: =SUM(BN6:BP6) -> 1325 | T6: =P6 -> 977.42857 | U6: =(R6+S6)-T6 -> 4621.2857 | V6: =IF(U6<0,0,U6) -> 4621.2857 | W6: =SUM(BQ6) -> 510 | X6: =T6 -> 977.42857 | Y6: =(V6+W6)-X6 -> 4153.8571 | Z6: =IF(Y6<0,0,Y6/D6) -> 4.2497808 | AA6: 4 | AB6: =AA6+4 -> 8 | AC6: =IF(IF(Z6>AA6,AB6-Z6,AB6-Z6)<0,0,IF(Z6>AA6,AB6-Z6,AB6-Z6)) -> 3.7502192 | AD6: =(AC6*D6) -> 3665.5714 | AE6: 5000 | AF6: 101.5 | AG6: 95 | AH6: 91 | AI6: 90 | AJ6: 600 | AK6: 200 | AM6: 300 | AO6: 250 | AP6: 118 | AQ6: 325 | AR6: 250 | AS6: 530 | AT6: 403 | AU6: 20 | AV6: 150 | AW6: 250 | AX6: 430 | AY6: 50 | BA6: 425 | BB6: 480 | BC6: =17+250 -> 267 | BD6: =100+100+100+244 -> 544 | BF6: 480 | BG6: 100 | BH6: 104 | BI6: 295 | BJ6: 240 | BK6: 240 | BL6: =200+191 -> 391 | BM6: 220 | BN6: 705 | BP6: 620 | BQ6: 510
A7: RS612 - RD801 -FD758 | B7: MI0086 - 315/80 R22.5 20PR DIFF | C7: =VLOOKUP(B7,'JAN26'!$A$1:I910,8,0) -> 151 | D7: =VLOOKUP(B7,AVE!B$1:GB3497,2,0) -> 313.375 | E7: =G7+K7+O7+S7 -> 2610 | F7: =IF(C7<0,0,C7) -> 151 | G7: =SUM(AO7:AR7) -> 330 | H7: =D7 -> 313.375 | I7: =(F7+G7)-H7 -> 167.625 | J7: =IF(I7<0,0,I7) -> 167.625 | K7: =SUM(AS7:AW7) -> 560 | L7: =H7 -> 313.375 | M7: =(J7+K7)-L7 -> 414.25 | N7: =IF(M7<0,0,M7) -> 414.25 | O7: =SUM(AX7:BM7) -> 850 | P7: =L7 -> 313.375 | Q7: =(N7+O7)-P7 -> 950.875 | R7: =IF(Q7<0,0,Q7) -> 950.875 | S7: =SUM(BN7:BP7) -> 870 | T7: =P7 -> 313.375 | U7: =(R7+S7)-T7 -> 1507.5 | V7: =IF(U7<0,0,U7) -> 1507.5 | W7: =SUM(BQ7) -> 440 | X7: =T7 -> 313.375 | Y7: =(V7+W7)-X7 -> 1634.125 | Z7: =IF(Y7<0,0,Y7/D7) -> 5.2145991 | AA7: 4 | AB7: =AA7+4 -> 8 | AC7: =IF(IF(Z7>AA7,AB7-Z7,AB7-Z7)<0,0,IF(Z7>AA7,AB7-Z7,AB7-Z7)) -> 2.7854009 | AD7: =(AC7*D7) -> 872.875 | AE7: 1000 | AF7: 107.5 | AG7: 104 | AI7: 104 | AJ7: 250 | AM7: 150 | AO7: 128 | AP7: =52+86 -> 138 | AR7: 64 | AU7: 360 | AV7: 100 | AW7: 100 | BF7: 360 | BG7: 150 | BH7: 250 | BM7: 90 | BN7: 450 | BO7: 120 | BP7: 300 | BQ7: 440
A8: FA626 - RS631+ | B8: MI0087 - 385/65 R22.5 20PR SUPER SINGLE | C8: =VLOOKUP(B8,'JAN26'!$A$1:I911,8,0) -> 94 | D8: =VLOOKUP(B8,AVE!B$1:GB3498,2,0) -> 221.125 | E8: =G8+K8+O8+S8 -> 1943 | F8: =IF(C8<0,0,C8) -> 94 | G8: =SUM(AO8:AR8) -> 184 | H8: =D8 -> 221.125 | I8: =(F8+G8)-H8 -> 56.875 | J8: =IF(I8<0,0,I8) -> 56.875 | K8: =SUM(AS8:AW8) -> 460 | L8: =H8 -> 221.125 | M8: =(J8+K8)-L8 -> 295.75 | N8: =IF(M8<0,0,M8) -> 295.75 | O8: =SUM(AX8:BM8) -> 929 | P8: =L8 -> 221.125 | Q8: =(N8+O8)-P8 -> 1003.625 | R8: =IF(Q8<0,0,Q8) -> 1003.625 | S8: =SUM(BN8:BP8) -> 370 | T8: =P8 -> 221.125 | U8: =(R8+S8)-T8 -> 1152.5 | V8: =IF(U8<0,0,U8) -> 1152.5 | W8: =SUM(BQ8) -> 0 | X8: =T8 -> 221.125 | Y8: =(V8+W8)-X8 -> 931.375 | Z8: =IF(Y8<0,0,Y8/D8) -> 4.2119842 | AA8: 4 | AB8: =AA8+4 -> 8 | AC8: =IF(IF(Z8>AA8,AB8-Z8,AB8-Z8)<0,0,IF(Z8>AA8,AB8-Z8,AB8-Z8)) -> 3.7880158 | AD8: =(AC8*D8) -> 837.625 | AE8: 700 | AF8: 133 | AG8: 130 | AH8: 121 | AJ8: 250 | AK8: =150+240 -> 390 | AO8: 100 | AQ8: 84 | AS8: 200 | AT8: 80 | AW8: 180 | BA8: 135 | BB8: 60 | BE8: 100 | BF8: 4 | BH8: 120 | BI8: 310 | BM8: 200 | BN8: 120 | BP8: 250
A9: RS620 - RS201 | B9: MI0085 - 315/80 R22.5 20PR STEER | C9: =VLOOKUP(B9,'JAN26'!$A$1:I912,8,0) -> 51 | D9: =VLOOKUP(B9,AVE!B$1:GB3499,2,0) -> 169.125 | E9: =G9+K9+O9+S9 -> 1330 | F9: =IF(C9<0,0,C9) -> 51 | G9: =SUM(AO9:AR9) -> 180 | H9: =D9 -> 169.125 | I9: =(F9+G9)-H9 -> 61.875 | J9: =IF(I9<0,0,I9) -> 61.875 | K9: =SUM(AS9:AW9) -> 137 | L9: =H9 -> 169.125 | M9: =(J9+K9)-L9 -> 29.75 | N9: =IF(M9<0,0,M9) -> 29.75 | O9: =SUM(AX9:BM9) -> 673 | P9: =L9 -> 169.125 | Q9: =(N9+O9)-P9 -> 533.625 | R9: =IF(Q9<0,0,Q9) -> 533.625 | S9: =SUM(BN9:BP9) -> 340 | T9: =P9 -> 169.125 | U9: =(R9+S9)-T9 -> 704.5 | V9: =IF(U9<0,0,U9) -> 704.5 | W9: =SUM(BQ9) -> 280 | X9: =T9 -> 169.125 | Y9: =(V9+W9)-X9 -> 815.375 | Z9: =IF(Y9<0,0,Y9/D9) -> 4.8211382 | AA9: 4 | AB9: =AA9+4 -> 8 | AC9: =IF(IF(Z9>AA9,AB9-Z9,AB9-Z9)<0,0,IF(Z9>AA9,AB9-Z9,AB9-Z9)) -> 3.1788618 | AD9: =(AC9*D9) -> 537.625 | AE9: 500 | AF9: 102 | AG9: 95 | AJ9: 300 | AK9: 100 | AP9: 80 | AR9: 100 | AU9: =250-BB9 -> 70 | AW9: 67 | AX9: 80 | BB9: 180 | BC9: 233 | BM9: 180 | BP9: 340 | BQ9: 280
A10: RS PRO | B10: MI0644 - RD951 DS315/80R22.5 DIFF TYRE | C10: =VLOOKUP(B10,'JAN26'!$A$1:I913,8,0) -> 98 | D10: =VLOOKUP(B10,AVE!B$1:GB3500,2,0) -> 46 | E10: =G10+K10+O10+S10 -> 160 | F10: =IF(C10<0,0,C10) -> 98 | G10: =SUM(AO10:AR10) -> 0 | H10: =D10 -> 46 | I10: =(F10+G10)-H10 -> 52 | J10: =IF(I10<0,0,I10) -> 52 | K10: =SUM(AS10:AW10) -> 0 | L10: =H10 -> 46 | M10: =(J10+K10)-L10 -> 6 | N10: =IF(M10<0,0,M10) -> 6 | O10: =SUM(AX10:BM10) -> 0 | P10: =L10 -> 46 | Q10: =(N10+O10)-P10 -> -40 | R10: =IF(Q10<0,0,Q10) -> 0 | S10: =SUM(BN10:BP10) -> 160 | T10: =P10 -> 46 | U10: =(R10+S10)-T10 -> 114 | V10: =IF(U10<0,0,U10) -> 114 | W10: =SUM(BQ10) -> 0 | X10: =T10 -> 46 | Y10: =(V10+W10)-X10 -> 68 | Z10: =IF(Y10<0,0,Y10/D10) -> 1.4782609 | AA10: 4 | AB10: =AA10+4 -> 8 | AC10: =IF(IF(Z10>AA10,AB10-Z10,AB10-Z10)<0,0,IF(Z10>AA10,AB10-Z10,AB10-Z10)) -> 6.5217391 | AD10: =(AC10*D10) -> 300 | AE10: 300 | AF10: 144 | AJ10: 160 | AN10: ROADSHINE PRO | BP10: 160
A11: RS201 | B11: MI0281 - 385/55R22.5 STEER TYRE | C11: =VLOOKUP(B11,'JAN26'!$A$1:I914,8,0) -> 27 | D11: =VLOOKUP(B11,AVE!B$1:GB3501,2,0) -> 39.125 | E11: =G11+K11+O11+S11 -> 224 | F11: =IF(C11<0,0,C11) -> 27 | G11: =SUM(AO11:AR11) -> 0 | H11: =D11 -> 39.125 | I11: =(F11+G11)-H11 -> -12.125 | J11: =IF(I11<0,0,I11) -> 0 | K11: =SUM(AS11:AW11) -> 224 | L11: =H11 -> 39.125 | M11: =(J11+K11)-L11 -> 184.875 | N11: =IF(M11<0,0,M11) -> 184.875 | O11: =SUM(AX11:BM11) -> 0 | P11: =L11 -> 39.125 | Q11: =(N11+O11)-P11 -> 145.75 | R11: =IF(Q11<0,0,Q11) -> 145.75 | S11: =SUM(BN11:BP11) -> 0 | T11: =P11 -> 39.125 | U11: =(R11+S11)-T11 -> 106.625 | V11: =IF(U11<0,0,U11) -> 106.625 | W11: =SUM(BQ11) -> 0 | X11: =T11 -> 39.125 | Y11: =(V11+W11)-X11 -> 67.5 | Z11: =IF(Y11<0,0,Y11/D11) -> 1.7252396 | AA11: 4 | AB11: =AA11+4 -> 8 | AC11: =IF(IF(Z11>AA11,AB11-Z11,AB11-Z11)<0,0,IF(Z11>AA11,AB11-Z11,AB11-Z11)) -> 6.2747604 | AD11: =(AC11*D11) -> 245.5 | AE11: 250 | AG11: 138 | AH11: 143 | AK11: 50 | AS11: 200 | AU11: 24
A12: RS637 | B12: MI0571 - 315/80R22.5 RS637+ DIFF TYRE | C12: =VLOOKUP(B12,'JAN26'!$A$1:I915,8,0) -> 58 | D12: =VLOOKUP(B12,AVE!B$1:GB3502,2,0) -> 36.125 | E12: =G12+K12+O12+S12 -> 0 | F12: =IF(C12<0,0,C12) -> 58 | G12: =SUM(AO12:AR12) -> 0 | H12: =D12 -> 36.125 | I12: =(F12+G12)-H12 -> 21.875 | J12: =IF(I12<0,0,I12) -> 21.875 | K12: =SUM(AS12:AW12) -> 0 | L12: =H12 -> 36.125 | M12: =(J12+K12)-L12 -> -14.25 | N12: =IF(M12<0,0,M12) -> 0 | O12: =SUM(AX12:BM12) -> 0 | P12: =L12 -> 36.125 | Q12: =(N12+O12)-P12 -> -36.125 | R12: =IF(Q12<0,0,Q12) -> 0 | S12: =SUM(BN12:BP12) -> 0 | T12: =P12 -> 36.125 | U12: =(R12+S12)-T12 -> -36.125 | V12: =IF(U12<0,0,U12) -> 0 | W12: =SUM(BQ12) -> 0 | X12: =T12 -> 36.125 | Y12: =(V12+W12)-X12 -> -36.125 | Z12: =IF(Y12<0,0,Y12/D12) -> 0 | AA12: 4 | AB12: =AA12+4 -> 8 | AC12: =IF(IF(Z12>AA12,AB12-Z12,AB12-Z12)<0,0,IF(Z12>AA12,AB12-Z12,AB12-Z12)) -> 8 | AD12: =(AC12*D12) -> 289 | AE12: 200 | AH12: 115 | AK12: 125
A13: RS201 | B13: MI0211 - 385/65R22.5 FRONT TYRE | C13: 0 | D13: =VLOOKUP(B13,AVE!B$1:GB3503,2,0) -> 0 | E13: =G13+K13+O13+S13 -> 194 | F13: =IF(C13<0,0,C13) -> 0 | G13: =SUM(AO13:AR13) -> 0 | H13: =D13 -> 0 | I13: =(F13+G13)-H13 -> 0 | J13: =IF(I13<0,0,I13) -> 0 | K13: =SUM(AS13:AW13) -> 0 | L13: =H13 -> 0 | M13: =(J13+K13)-L13 -> 0 | N13: =IF(M13<0,0,M13) -> 0 | O13: =SUM(AX13:BM13) -> 194 | P13: =L13 -> 0 | Q13: =(N13+O13)-P13 -> 194 | R13: =IF(Q13<0,0,Q13) -> 194 | S13: =SUM(BN13:BP13) -> 0 | T13: =P13 -> 0 | U13: =(R13+S13)-T13 -> 194 | V13: =IF(U13<0,0,U13) -> 194 | W13: =SUM(BQ13) -> 316 | X13: =T13 -> 0 | Y13: =(V13+W13)-X13 -> 510 | Z13: 0 | AA13: 4 | AB13: =AA13+4 -> 8 | AC13: =IF(IF(Z13>AA13,AB13-Z13,AB13-Z13)<0,0,IF(Z13>AA13,AB13-Z13,AB13-Z13)) -> 8 | AD13: =(AC13*D13) -> 0 | AE13: 300 | AG13: 130 | AM13: 200 | AN13: ROYAL BLACK / FEDRIK | BF13: 194 | BQ13: 316
B14: MI0635 - 12.00R20 DIFF TYRE TTF | C14: =VLOOKUP(B14,'JAN26'!$A$1:I916,8,0) -> 1 | D14: =VLOOKUP(B14,AVE!B$1:GB3504,2,0) -> 36.8 | E14: =G14+K14+O14+S14 -> 290 | F14: =IF(C14<0,0,C14) -> 1 | G14: =SUM(AO14:AR14) -> 0 | H14: =D14 -> 36.8 | I14: =(F14+G14)-H14 -> -35.8 | J14: =IF(I14<0,0,I14) -> 0 | K14: =SUM(AS14:AW14) -> 0 | L14: =H14 -> 36.8 | M14: =(J14+K14)-L14 -> -36.8 | N14: =IF(M14<0,0,M14) -> 0 | O14: =SUM(AX14:BM14) -> 290 | P14: =L14 -> 36.8 | Q14: =(N14+O14)-P14 -> 253.2 | R14: =IF(Q14<0,0,Q14) -> 253.2 | S14: =SUM(BN14:BP14) -> 0 | T14: =P14 -> 36.8 | U14: =(R14+S14)-T14 -> 216.4 | V14: =IF(U14<0,0,U14) -> 216.4 | W14: =SUM(BQ14) -> 0 | X14: =T14 -> 36.8 | Y14: =(V14+W14)-X14 -> 179.6 | Z14: =IF(Y14<0,0,Y14/D14) -> 4.8804348 | AA14: 4 | AB14: =AA14+4 -> 8 | AC14: =IF(IF(Z14>AA14,AB14-Z14,AB14-Z14)<0,0,IF(Z14>AA14,AB14-Z14,AB14-Z14)) -> 3.1195652 | AD14: =(AC14*D14) -> 114.8 | AE14: 200 | AF14: 163 | AI14: 136 | AL14: 100 | AN14: WE NEED IN MAXZEZ, NEED BETTER THEN SAFERUN // 100PC 3 BLOCK PATTERN | AY14: 140 | BD14: =14+136 -> 150
B15: MI0416 - 295/80 R22.5 UNIVERSAL TYRE | C15: =VLOOKUP(B15,'JAN26'!$A$1:I917,8,0) -> 42 | D15: =VLOOKUP(B15,AVE!B$1:GB3505,2,0) -> 21.5 | E15: =G15+K15+O15+S15 -> 150 | F15: =IF(C15<0,0,C15) -> 42 | G15: =SUM(AO15:AR15) -> 0 | H15: =D15 -> 21.5 | I15: =(F15+G15)-H15 -> 20.5 | J15: =IF(I15<0,0,I15) -> 20.5 | K15: =SUM(AS15:AW15) -> 0 | L15: =H15 -> 21.5 | M15: =(J15+K15)-L15 -> -1 | N15: =IF(M15<0,0,M15) -> 0 | O15: =SUM(AX15:BM15) -> 100 | P15: =L15 -> 21.5 | Q15: =(N15+O15)-P15 -> 78.5 | R15: =IF(Q15<0,0,Q15) -> 78.5 | S15: =SUM(BN15:BP15) -> 50 | T15: =P15 -> 21.5 | U15: =(R15+S15)-T15 -> 107 | V15: =IF(U15<0,0,U15) -> 107 | W15: =SUM(BQ15) -> 0 | X15: =T15 -> 21.5 | Y15: =(V15+W15)-X15 -> 85.5 | Z15: =IF(Y15<0,0,Y15/D15) -> 3.9767442 | AA15: 4 | AB15: =AA15+4 -> 8 | AC15: =IF(IF(Z15>AA15,AB15-Z15,AB15-Z15)<0,0,IF(Z15>AA15,AB15-Z15,AB15-Z15)) -> 4.0232558 | AD15: =(AC15*D15) -> 86.5 | AE15: 100 | AF15: 101 | AH15: 92 | AK15: 30 | AN15: 100PC GET FROM LOWER QUOTE | BE15: 100 | BO15: 50
B16: MI0295 - 12.00R20 UNIVERSAL TYRE | C16: =VLOOKUP(B16,'JAN26'!$A$1:I918,8,0) -> 30 | D16: =VLOOKUP(B16,AVE!B$1:GB3506,2,0) -> 32.666667 | E16: =G16+K16+O16+S16 -> 200 | F16: =IF(C16<0,0,C16) -> 30 | G16: =SUM(AO16:AR16) -> 0 | H16: =D16 -> 32.666667 | I16: =(F16+G16)-H16 -> -2.6666667 | J16: =IF(I16<0,0,I16) -> 0 | K16: =SUM(AS16:AW16) -> 0 | L16: =H16 -> 32.666667 | M16: =(J16+K16)-L16 -> -32.666667 | N16: =IF(M16<0,0,M16) -> 0 | O16: =SUM(AX16:BM16) -> 200 | P16: =L16 -> 32.666667 | Q16: =(N16+O16)-P16 -> 167.33333 | R16: =IF(Q16<0,0,Q16) -> 167.33333 | S16: =SUM(BN16:BP16) -> 0 | T16: =P16 -> 32.666667 | U16: =(R16+S16)-T16 -> 134.66667 | V16: =IF(U16<0,0,U16) -> 134.66667 | W16: =SUM(BQ16) -> 0 | X16: =T16 -> 32.666667 | Y16: =(V16+W16)-X16 -> 102 | Z16: =IF(Y16<0,0,Y16/D16) -> 3.122449 | AA16: 4 | AB16: =AA16+4 -> 8 | AC16: =IF(IF(Z16>AA16,AB16-Z16,AB16-Z16)<0,0,IF(Z16>AA16,AB16-Z16,AB16-Z16)) -> 4.877551 | AD16: =(AC16*D16) -> 159.33333 | AE16: 200 | AF16: 143 | AI16: 131 | AL16: 100 | AN16: CHECK WITH RS / RB / TS / FDR | BD16: =100+100 -> 200
B17: MI0256 - 295/80 R22.5 STEER | C17: =VLOOKUP(B17,'JAN26'!$A$1:I919,8,0) -> 46 | D17: =VLOOKUP(B17,AVE!B$1:GB3507,2,0) -> 17.4 | E17: =G17+K17+O17+S17 -> 80 | F17: =IF(C17<0,0,C17) -> 46 | G17: =SUM(AO17:AR17) -> 0 | H17: =D17 -> 17.4 | I17: =(F17+G17)-H17 -> 28.6 | J17: =IF(I17<0,0,I17) -> 28.6 | K17: =SUM(AS17:AW17) -> 0 | L17: =H17 -> 17.4 | M17: =(J17+K17)-L17 -> 11.2 | N17: =IF(M17<0,0,M17) -> 11.2 | O17: =SUM(AX17:BM17) -> 80 | P17: =L17 -> 17.4 | Q17: =(N17+O17)-P17 -> 73.8 | R17: =IF(Q17<0,0,Q17) -> 73.8 | S17: =SUM(BN17:BP17) -> 0 | T17: =P17 -> 17.4 | U17: =(R17+S17)-T17 -> 56.4 | V17: =IF(U17<0,0,U17) -> 56.4 | W17: =SUM(BQ17) -> 0 | X17: =T17 -> 17.4 | Y17: =(V17+W17)-X17 -> 39 | Z17: =IF(Y17<0,0,Y17/D17) -> 2.2413793 | AA17: 4 | AB17: =AA17+4 -> 8 | AC17: =IF(IF(Z17>AA17,AB17-Z17,AB17-Z17)<0,0,IF(Z17>AA17,AB17-Z17,AB17-Z17)) -> 5.7586207 | AD17: =(AC17*D17) -> 100.2 | AE17: 100 | AF17: 104 | AG17: 100 | AH17: 100 | AN17: CHECK PRICE WITH RB | AY17: 30 | BE17: 50
A18: TTF | B18: MI0280 - 10.00R20 UNIVERSAL TYRE | C18: =VLOOKUP(B18,'JAN26'!$A$1:I920,8,0) -> 82 | D18: =VLOOKUP(B18,AVE!B$1:GB3508,2,0) -> 14 | E18: =G18+K18+O18+S18 -> 0 | F18: =IF(C18<0,0,C18) -> 82 | G18: =SUM(AO18:AR18) -> 0 | H18: =D18 -> 14 | I18: =(F18+G18)-H18 -> 68 | J18: =IF(I18<0,0,I18) -> 68 | K18: =SUM(AS18:AW18) -> 0 | L18: =H18 -> 14 | M18: =(J18+K18)-L18 -> 54 | N18: =IF(M18<0,0,M18) -> 54 | O18: =SUM(AX18:BM18) -> 0 | P18: =L18 -> 14 | Q18: =(N18+O18)-P18 -> 40 | R18: =IF(Q18<0,0,Q18) -> 40 | S18: =SUM(BN18:BP18) -> 0 | T18: =P18 -> 14 | U18: =(R18+S18)-T18 -> 26 | V18: =IF(U18<0,0,U18) -> 26 | W18: =SUM(BQ18) -> 0 | X18: =T18 -> 14 | Y18: =(V18+W18)-X18 -> 12 | Z18: =IF(Y18<0,0,Y18/D18) -> 0.85714286 | AA18: 4 | AB18: =AA18+4 -> 8 | AC18: =IF(IF(Z18>AA18,AB18-Z18,AB18-Z18)<0,0,IF(Z18>AA18,AB18-Z18,AB18-Z18)) -> 7.1428571 | AD18: =(AC18*D18) -> 100 | AE18: 100 | AF18: 111 | AG18: 120 | AH18: 116 | AI18: 105
A19: TTF | B19: MI0280 - 10.00R20 DIFF | AE19: 50
B20: MI0257 - 295/80 R22.5 DIFF | C20: 0 | D20: =VLOOKUP(B20,AVE!B$1:GB3509,2,0) -> 8 | E20: =G20+K20+O20+S20 -> 130 | F20: =IF(C20<0,0,C20) -> 0 | G20: =SUM(AO20:AR20) -> 0 | H20: =D20 -> 8 | I20: =(F20+G20)-H20 -> -8 | J20: =IF(I20<0,0,I20) -> 0 | K20: =SUM(AS20:AW20) -> 0 | L20: =H20 -> 8 | M20: =(J20+K20)-L20 -> -8 | N20: =IF(M20<0,0,M20) -> 0 | O20: =SUM(AX20:BM20) -> 130 | P20: =L20 -> 8 | Q20: =(N20+O20)-P20 -> 122 | R20: =IF(Q20<0,0,Q20) -> 122 | S20: =SUM(BN20:BP20) -> 0 | T20: =P20 -> 8 | U20: =(R20+S20)-T20 -> 114 | V20: =IF(U20<0,0,U20) -> 114 | W20: =SUM(BQ20) -> 0 | X20: =T20 -> 8 | Y20: =(V20+W20)-X20 -> 106 | Z20: =IF(Y20<0,0,Y20/D20) -> 13.25 | AA20: 4 | AB20: =AA20+4 -> 8 | AC20: =IF(IF(Z20>AA20,AB20-Z20,AB20-Z20)<0,0,IF(Z20>AA20,AB20-Z20,AB20-Z20)) -> 0 | AD20: =(AC20*D20) -> 0 | AF20: 113 | AG20: 108 | AH20: 100 | AN20: 50PC GET FROM LOWER QUOTE | BE20: 50 | BF20: 40 | BI20: 40
A21: RS602 | B21: MI0272 - 11R22.5 TYRE UNIVERSAL | C21: =VLOOKUP(B21,'JAN26'!$A$1:I922,8,0) -> 68 | D21: =VLOOKUP(B21,AVE!B$1:GB3510,2,0) -> 20.25 | E21: =G21+K21+O21+S21 -> 100 | F21: =IF(C21<0,0,C21) -> 68 | G21: =SUM(AO21:AR21) -> 0 | H21: =D21 -> 20.25 | I21: =(F21+G21)-H21 -> 47.75 | J21: =IF(I21<0,0,I21) -> 47.75 | K21: =SUM(AS21:AW21) -> 0 | L21: =H21 -> 20.25 | M21: =(J21+K21)-L21 -> 27.5 | N21: =IF(M21<0,0,M21) -> 27.5 | O21: =SUM(AX21:BM21) -> 100 | P21: =L21 -> 20.25 | Q21: =(N21+O21)-P21 -> 107.25 | R21: =IF(Q21<0,0,Q21) -> 107.25 | S21: =SUM(BN21:BP21) -> 0 | T21: =P21 -> 20.25 | U21: =(R21+S21)-T21 -> 87 | V21: =IF(U21<0,0,U21) -> 87 | W21: =SUM(BQ21) -> 30 | X21: =T21 -> 20.25 | Y21: =(V21+W21)-X21 -> 96.75 | Z21: =IF(Y21<0,0,Y21/D21) -> 4.7777778 | AA21: 4 | AB21: =AA21+4 -> 8 | AC21: =IF(IF(Z21>AA21,AB21-Z21,AB21-Z21)<0,0,IF(Z21>AA21,AB21-Z21,AB21-Z21)) -> 3.2222222 | AD21: =(AC21*D21) -> 65.25 | AE21: 50 | AF21: 104 | AG21: 86 | AN21: GET LOWER PRICE | BF21: 90 | BM21: 10 | BQ21: 30
A22: UNIVERSAL | B22: MI0637 - DSR188 DS - 8.25R20 TTF TYRE | C22: 0 | D22: =VLOOKUP(B22,AVE!B$1:GB3511,2,0) -> 5.3333333 | E22: =G22+K22+O22+S22 -> 70 | F22: =IF(C22<0,0,C22) -> 0 | G22: =SUM(AO22:AR22) -> 0 | H22: =D22 -> 5.3333333 | I22: =(F22+G22)-H22 -> -5.3333333 | J22: =IF(I22<0,0,I22) -> 0 | K22: =SUM(AS22:AW22) -> 20 | L22: =H22 -> 5.3333333 | M22: =(J22+K22)-L22 -> 14.666667 | N22: =IF(M22<0,0,M22) -> 14.666667 | O22: =SUM(AX22:BM22) -> 50 | P22: =L22 -> 5.3333333 | Q22: =(N22+O22)-P22 -> 59.333333 | R22: =IF(Q22<0,0,Q22) -> 59.333333 | S22: =SUM(BN22:BP22) -> 0 | T22: =P22 -> 5.3333333 | U22: =(R22+S22)-T22 -> 54 | V22: =IF(U22<0,0,U22) -> 54 | W22: =SUM(BQ22) -> 0 | X22: =T22 -> 5.3333333 | Y22: =(V22+W22)-X22 -> 48.666667 | Z22: =IF(Y22<0,0,Y22/D22) -> 9.125 | AA22: 4 | AB22: =AA22+4 -> 8 | AC22: =IF(IF(Z22>AA22,AB22-Z22,AB22-Z22)<0,0,IF(Z22>AA22,AB22-Z22,AB22-Z22)) -> 0 | AD22: =(AC22*D22) -> 0 | AF22: 97 | AG22: 93 | AH22: 80 | AS22: 20 | BI22: 50
A23: UNIVERSAL | B23: MI0275 - 12R22.5 TYRE | C23: 0 | D23: =VLOOKUP(B23,AVE!B$1:GB3512,2,0) -> 7.2857143 | E23: =G23+K23+O23+S23 -> 10 | F23: =IF(C23<0,0,C23) -> 0 | G23: =SUM(AO23:AR23) -> 0 | H23: =D23 -> 7.2857143 | I23: =(F23+G23)-H23 -> -7.2857143 | J23: =IF(I23<0,0,I23) -> 0 | K23: =SUM(AS23:AW23) -> 0 | L23: =H23 -> 7.2857143 | M23: =(J23+K23)-L23 -> -7.2857143 | N23: =IF(M23<0,0,M23) -> 0 | O23: =SUM(AX23:BM23) -> 10 | P23: =L23 -> 7.2857143 | Q23: =(N23+O23)-P23 -> 2.7142857 | R23: =IF(Q23<0,0,Q23) -> 2.7142857 | S23: =SUM(BN23:BP23) -> 0 | T23: =P23 -> 7.2857143 | U23: =(R23+S23)-T23 -> -4.5714286 | V23: =IF(U23<0,0,U23) -> 0 | W23: =SUM(BQ23) -> 0 | X23: =T23 -> 7.2857143 | Y23: =(V23+W23)-X23 -> -7.2857143 | Z23: =IF(Y23<0,0,Y23/D23) -> 0 | AA23: 4 | AB23: =AA23+4 -> 8 | AC23: =IF(IF(Z23>AA23,AB23-Z23,AB23-Z23)<0,0,IF(Z23>AA23,AB23-Z23,AB23-Z23)) -> 8 | AD23: =(AC23*D23) -> 58.285714 | AE23: 50 | AF23: 106 | AG23: 119 | AH23: 104 | AI23: 108 | BI23: 10
B24: MI0444 - 12.00R24 UNIVERSAL TYRE | C24: =VLOOKUP(B24,'JAN26'!$A$1:I925,8,0) -> 34 | D24: =VLOOKUP(B24,AVE!B$1:GB3513,2,0) -> 10 | E24: =G24+K24+O24+S24 -> 0 | F24: =IF(C24<0,0,C24) -> 34 | G24: =SUM(AO24:AR24) -> 0 | H24: =D24 -> 10 | I24: =(F24+G24)-H24 -> 24 | J24: =IF(I24<0,0,I24) -> 24 | K24: =SUM(AS24:AW24) -> 0 | L24: =H24 -> 10 | M24: =(J24+K24)-L24 -> 14 | N24: =IF(M24<0,0,M24) -> 14 | O24: =SUM(AX24:BM24) -> 0 | P24: =L24 -> 10 | Q24: =(N24+O24)-P24 -> 4 | R24: =IF(Q24<0,0,Q24) -> 4 | S24: =SUM(BN24:BP24) -> 0 | T24: =P24 -> 10 | U24: =(R24+S24)-T24 -> -6 | V24: =IF(U24<0,0,U24) -> 0 | W24: =SUM(BQ24) -> 0 | X24: =T24 -> 10 | Y24: =(V24+W24)-X24 -> -10 | Z24: =IF(Y24<0,0,Y24/D24) -> 0 | AA24: 4 | AB24: =AA24+4 -> 8 | AC24: =IF(IF(Z24>AA24,AB24-Z24,AB24-Z24)<0,0,IF(Z24>AA24,AB24-Z24,AB24-Z24)) -> 8 | AD24: =(AC24*D24) -> 80 | AE24: 0 | AF24: 148 | AG24: 140 | AH24: 131 | AI24: 126
A25: RS201 | B25: MI0273 - 275/70 R22.5 TYRE | C25: =VLOOKUP(B25,'JAN26'!$A$1:I926,8,0) -> 23 | D25: =VLOOKUP(B25,AVE!B$1:GB3514,2,0) -> 6 | E25: =G25+K25+O25+S25 -> 30 | F25: =IF(C25<0,0,C25) -> 23 | G25: =SUM(AO25:AR25) -> 0 | H25: =D25 -> 6 | I25: =(F25+G25)-H25 -> 17 | J25: =IF(I25<0,0,I25) -> 17 | K25: =SUM(AS25:AW25) -> 0 | L25: =H25 -> 6 | M25: =(J25+K25)-L25 -> 11 | N25: =IF(M25<0,0,M25) -> 11 | O25: =SUM(AX25:BM25) -> 0 | P25: =L25 -> 6 | Q25: =(N25+O25)-P25 -> 5 | R25: =IF(Q25<0,0,Q25) -> 5 | S25: =SUM(BN25:BP25) -> 30 | T25: =P25 -> 6 | U25: =(R25+S25)-T25 -> 29 | V25: =IF(U25<0,0,U25) -> 29 | W25: =SUM(BQ25) -> 0 | X25: =T25 -> 6 | Y25: =(V25+W25)-X25 -> 23 | Z25: =IF(Y25<0,0,Y25/D25) -> 3.8333333 | AA25: 4 | AB25: =AA25+4 -> 8 | AC25: =IF(IF(Z25>AA25,AB25-Z25,AB25-Z25)<0,0,IF(Z25>AA25,AB25-Z25,AB25-Z25)) -> 4.1666667 | AD25: =(AC25*D25) -> 25 | AE25: 30 | AF25: 96 | AG25: 95 | AH25: 94 | AN25: NEXT TIME 18 PLY... | BO25: 30
A26: RS602 TTF | B26: MI0294 - 11.00R20 UNIVERSAL TYRE | C26: =VLOOKUP(B26,'JAN26'!$A$1:I927,8,0) -> 9 | D26: =VLOOKUP(B26,AVE!B$1:GB3515,2,0) -> 6.8 | E26: =G26+K26+O26+S26 -> 30 | F26: =IF(C26<0,0,C26) -> 9 | G26: =SUM(AO26:AR26) -> 0 | H26: =D26 -> 6.8 | I26: =(F26+G26)-H26 -> 2.2 | J26: =IF(I26<0,0,I26) -> 2.2 | K26: =SUM(AS26:AW26) -> 30 | L26: =H26 -> 6.8 | M26: =(J26+K26)-L26 -> 25.4 | N26: =IF(M26<0,0,M26) -> 25.4 | O26: =SUM(AX26:BM26) -> 0 | P26: =L26 -> 6.8 | Q26: =(N26+O26)-P26 -> 18.6 | R26: =IF(Q26<0,0,Q26) -> 18.6 | S26: =SUM(BN26:BP26) -> 0 | T26: =P26 -> 6.8 | U26: =(R26+S26)-T26 -> 11.8 | V26: =IF(U26<0,0,U26) -> 11.8 | W26: =SUM(BQ26) -> 0 | X26: =T26 -> 6.8 | Y26: =(V26+W26)-X26 -> 5 | Z26: =IF(Y26<0,0,Y26/D26) -> 0.73529412 | AA26: 4 | AB26: =AA26+4 -> 8 | AC26: =IF(IF(Z26>AA26,AB26-Z26,AB26-Z26)<0,0,IF(Z26>AA26,AB26-Z26,AB26-Z26)) -> 7.2647059 | AD26: =(AC26*D26) -> 49.4 | AE26: 50 | AF26: 124 | AH26: 132 | AN26: GET LOWER PRICE | AW26: 30
B27: MI0543 - 9.00R20 UNIVERSAL TYRE | C27: =VLOOKUP(B27,'JAN26'!$A$1:I928,8,0) -> 24 | D27: =VLOOKUP(B27,AVE!B$1:GB3516,2,0) -> 4.4285714 | E27: =G27+K27+O27+S27 -> 0 | F27: =IF(C27<0,0,C27) -> 24 | G27: =SUM(AO27:AR27) -> 0 | H27: =D27 -> 4.4285714 | I27: =(F27+G27)-H27 -> 19.571429 | J27: =IF(I27<0,0,I27) -> 19.571429 | K27: =SUM(AS27:AW27) -> 0 | L27: =H27 -> 4.4285714 | M27: =(J27+K27)-L27 -> 15.142857 | N27: =IF(M27<0,0,M27) -> 15.142857 | O27: =SUM(AX27:BM27) -> 0 | P27: =L27 -> 4.4285714 | Q27: =(N27+O27)-P27 -> 10.714286 | R27: =IF(Q27<0,0,Q27) -> 10.714286 | S27: =SUM(BN27:BP27) -> 0 | T27: =P27 -> 4.4285714 | U27: =(R27+S27)-T27 -> 6.2857143 | V27: =IF(U27<0,0,U27) -> 6.2857143 | W27: =SUM(BQ27) -> 0 | X27: =T27 -> 4.4285714 | Y27: =(V27+W27)-X27 -> 1.8571429 | Z27: =IF(Y27<0,0,Y27/D27) -> 0.41935484 | AA27: 4 | AB27: =AA27+4 -> 8 | AC27: =IF(IF(Z27>AA27,AB27-Z27,AB27-Z27)<0,0,IF(Z27>AA27,AB27-Z27,AB27-Z27)) -> 7.5806452 | AD27: =(AC27*D27) -> 33.571429 | AE27: 40
A28: TTF | B28: MI0452 - 17.5-25-20PR E3/L3 OTR TYRE | C28: =VLOOKUP(B28,'JAN26'!$A$1:I929,8,0) -> 23 | D28: =VLOOKUP(B28,AVE!B$1:GB3517,2,0) -> 3.6 | E28: =G28+K28+O28+S28 -> 10 | F28: =IF(C28<0,0,C28) -> 23 | G28: =SUM(AO28:AR28) -> 0 | H28: =D28 -> 3.6 | I28: =(F28+G28)-H28 -> 19.4 | J28: =IF(I28<0,0,I28) -> 19.4 | K28: =SUM(AS28:AW28) -> 0 | L28: =H28 -> 3.6 | M28: =(J28+K28)-L28 -> 15.8 | N28: =IF(M28<0,0,M28) -> 15.8 | O28: =SUM(AX28:BM28) -> 0 | P28: =L28 -> 3.6 | Q28: =(N28+O28)-P28 -> 12.2 | R28: =IF(Q28<0,0,Q28) -> 12.2 | S28: =SUM(BN28:BP28) -> 10 | T28: =P28 -> 3.6 | U28: =(R28+S28)-T28 -> 18.6 | V28: =IF(U28<0,0,U28) -> 18.6 | W28: =SUM(BQ28) -> 0 | X28: =T28 -> 3.6 | Y28: =(V28+W28)-X28 -> 15 | Z28: =IF(Y28<0,0,Y28/D28) -> 4.1666667 | AA28: 4 | AB28: =AA28+4 -> 8 | AC28: =IF(IF(Z28>AA28,AB28-Z28,AB28-Z28)<0,0,IF(Z28>AA28,AB28-Z28,AB28-Z28)) -> 3.8333333 | AD28: =(AC28*D28) -> 13.8 | AE28: 20 | AF28: 276 | AH28: 255 | AI28: 187 | BO28: 10
B29: MI0452 - 23.5-25-24 E3/L3 OTR TYRE | C29: =VLOOKUP(B29,'JAN26'!$A$1:I930,8,0) -> 3 | D29: =VLOOKUP(B29,AVE!B$1:GB3518,2,0) -> 2.25 | E29: =G29+K29+O29+S29 -> 0 | F29: =IF(C29<0,0,C29) -> 3 | G29: =SUM(AO29:AR29) -> 0 | H29: =D29 -> 2.25 | I29: =(F29+G29)-H29 -> 0.75 | J29: =IF(I29<0,0,I29) -> 0.75 | K29: =SUM(AS29:AW29) -> 0 | L29: =H29 -> 2.25 | M29: =(J29+K29)-L29 -> -1.5 | N29: =IF(M29<0,0,M29) -> 0 | O29: =SUM(AX29:BM29) -> 0 | P29: =L29 -> 2.25 | Q29: =(N29+O29)-P29 -> -2.25 | R29: =IF(Q29<0,0,Q29) -> 0 | S29: =SUM(BN29:BP29) -> 0 | T29: =P29 -> 2.25 | U29: =(R29+S29)-T29 -> -2.25 | V29: =IF(U29<0,0,U29) -> 0 | W29: =SUM(BQ29) -> 0 | X29: =T29 -> 2.25 | Y29: =(V29+W29)-X29 -> -2.25 | Z29: =IF(Y29<0,0,Y29/D29) -> 0 | AA29: 4 | AB29: =AA29+4 -> 8 | AC29: =IF(IF(Z29>AA29,AB29-Z29,AB29-Z29)<0,0,IF(Z29>AA29,AB29-Z29,AB29-Z29)) -> 8 | AD29: =(AC29*D29) -> 18 | AE29: 4
B30: 29.5R25 | C30: 0 | G30: =SUM(AO30:AR30) -> 0 | K30: =SUM(AS30:AW30) -> 0 | O30: =SUM(AX30:BM30) -> 4 | S30: =SUM(BN30:BP30) -> 0 | W30: =SUM(BQ30) -> 0 | AA30: 4 | AB30: =AA30+4 -> 8 | BE30: 4
B31: 14.00-25 TTF | C31: 0 | E31: =G31+K31+O31+S31 -> 4 | G31: =SUM(AO31:AR31) -> 0 | K31: =SUM(AS31:AW31) -> 0 | O31: =SUM(AX31:BM31) -> 4 | S31: =SUM(BN31:BP31) -> 0 | W31: =SUM(BQ31) -> 0 | AA31: 4 | AB31: =AA31+4 -> 8 | AX31: 4
K32: =SUM(AS32:AW32) -> 0 | O32: =SUM(AX32:BM32) -> 0 | S32: =SUM(BN32:BP32) -> 0 | W32: =SUM(BQ32) -> 0
B33: PROCESS TIME (Check, Prepare Inquiry) | C33: 30 | S33: =SUM(BO33:BP33) -> 0
B34: PRODUCTION | C34: 30 | AC34: TBR | AD34: =SUM(AD6:AD31) -> 7652.3369 | AE34: =SUM(AE6:AE31) -> 9244 | AH34: =SUM(AH6:AH31) -> 1674 | AJ34: =SUM(AJ6:AJ31) -> 1560 | AK34: =SUM(AK6:AK31) -> 895 | AL34: =SUM(AL6:AL31) -> 200 | AM34: =SUM(AM6:AM31) -> 650
B35: TRANSIT china to DSM Port | C35: 60 | AC35: CTR | AD35: =AD34/240 -> 31.884737 | AE35: =AE34/240 -> 38.516667 | AJ35: =AJ34/230 -> 6.7826087 | AK35: =AK34/230 -> 3.8913043 | AL35: =AL34/230 -> 0.86956522 | AM35: =AM34/230 -> 2.826087
B36: ROAD TRANSPORT, DSM port to LSK | C36: 30
B37: TOTAL | C37: =SUM(C33:C36) -> 150
B38: MONTHS | C38: =C37/30 -> 5

Sheet LTR
B1: LTR 700PC HC
B2: Updated 0n
B3: =TODAY() -> 46188
F4: =TODAY()+3 -> 46191 | J4: =F4+31 -> 46222 | N4: =J4+31 -> 46253 | R4: =N4+30 -> 46283 | V4: Procurement | AA4: Management | AG4: FEB | AH4: FEB | AI4: MAR | AJ4: APR | AK4: APR | AL4: APR | AM4: APR | AN4: APR | AO4: APR | AP4: APR | AQ4: APR | AR4: MAY | AS4: MAY | AT4: MAY
A5: S.No | B5: Part No. / Description | C5: Opening Stock | D5: Avg Con | E5: INFLOW TOTAL | F5: OB | G5: Inflow | H5: Actual sale | I5: Closing Stock | J5: OB | K5: Inflow | L5: Actual sale | M5: Closing Stock | N5: OB | O5: Inflow | P5: Actual sale | Q5: Closing Stock | R5: OB | S5: Inflow | T5: Actual sale | U5: Closing Stock | V5: Stk (in Months) | W5: Min Stk (In Months) | X5: Max Stk (In Months) | Y5: Requirement (In Months) | Z5: Requirements (Qty) | AA5: FINAL QTY | AB5: REMARKS | AC5: RS PRICE | AD5: RB PRICE | AE5: FDK PRICE | AF5: TRSN PRICE | AG5: RS EX-644/25 2HC | AH5: RS 2HC EX-689 WITH tent belts | AI5: RS EX-741/25 3HC WITH PCR | AJ5: RS 2HC EX-672 WTH SPARES | AK5: FDK 3HC CAX-1017 + RODS | AL5: RS EX-701/25 3HC with spare in1 | AM5: TS T25I811 4HC WITH RODS | AN5: FDK CAX-1216 2HC WIT RODS | AO5: JY 4HC JY2513-2601 RODS PADS RIMS | AP5: RB DEC ORDER | AQ5: FDK 4HC CAX-W-113 WITH RODS | AR5: FDK BALANCE ORDER | AS5: RB JAN ORDER | AT5: RS JAN ORDER
A6: universal | B6: MI0359 - 7.00R16 TYRE | C6: =VLOOKUP(B6,'JAN26'!$A$1:I909,8,0) -> 542 | D6: =VLOOKUP(B6,AVE!B$1:GB3520,2,0) -> 96.75 | E6: =G6+K6+O6+S6 -> 450 | F6: =IF(C6<0,0,C6) -> 542 | G6: =SUM(AG6:AH6) -> 0 | H6: =D6 -> 96.75 | I6: =(F6+G6)-H6 -> 445.25 | J6: =IF(I6<0,0,I6) -> 445.25 | K6: =SUM(AI6) -> 0 | L6: =H6 -> 96.75 | M6: =(J6+K6)-L6 -> 348.5 | N6: =IF(M6<0,0,M6) -> 348.5 | O6: =SUM(AJ6:AQ6) -> 300 | P6: =L6 -> 96.75 | Q6: =(N6+O6)-P6 -> 551.75 | R6: =IF(Q6<0,0,Q6) -> 551.75 | S6: =SUM(AR6:AT6) -> 150 | T6: =P6 -> 96.75 | U6: =(R6+S6)-T6 -> 605 | V6: =IF(U6<0,0,U6/D6) -> 6.25323 | W6: 6 | X6: 12 | Y6: =IF(IF(V6>W6,X6-V6,X6-V6)<0,0,IF(V6>W6,X6-V6,X6-V6)) -> 5.74677 | Z6: =(Y6*D6) -> 556 | AA6: 500 | AD6: 53 | AE6: 49 | AK6: 300 | AR6: 150
A7: HIGHWAY | B7: MI0230 - 9.50R17.5 TYRE | C7: =VLOOKUP(B7,'JAN26'!$A$1:I910,8,0) -> 522 | D7: =VLOOKUP(B7,AVE!B$1:GB3521,2,0) -> 116.625 | E7: =G7+K7+O7+S7 -> 969 | F7: =IF(C7<0,0,C7) -> 522 | G7: =SUM(AG7:AH7) -> 246 | H7: =D7 -> 116.625 | I7: =(F7+G7)-H7 -> 651.375 | J7: =IF(I7<0,0,I7) -> 651.375 | K7: =SUM(AI7) -> 100 | L7: =H7 -> 116.625 | M7: =(J7+K7)-L7 -> 634.75 | N7: =IF(M7<0,0,M7) -> 634.75 | O7: =SUM(AJ7:AQ7) -> 623 | P7: =L7 -> 116.625 | Q7: =(N7+O7)-P7 -> 1141.125 | R7: =IF(Q7<0,0,Q7) -> 1141.125 | S7: =SUM(AR7:AT7) -> 0 | T7: =P7 -> 116.625 | U7: =(R7+S7)-T7 -> 1024.5 | V7: =IF(U7<0,0,U7/D7) -> 8.7845659 | W7: 6 | X7: 12 | Y7: =IF(IF(V7>W7,X7-V7,X7-V7)<0,0,IF(V7>W7,X7-V7,X7-V7)) -> 3.2154341 | Z7: =(Y7*D7) -> 375 | AA7: 400 | AB7: rs / rb | AC7: US$65.00 | AD7: 68 | AE7: 65 | AG7: 73 | AH7: 173 | AI7: 100 | AJ7: 173 | AL7: 250 | AQ7: 200
A8: universal TTF | B8: MI0286 - 7.50R16 TYRE | C8: =VLOOKUP(B8,'JAN26'!$A$1:I911,8,0) -> 596 | D8: =VLOOKUP(B8,AVE!B$1:GB3522,2,0) -> 112.5 | E8: =G8+K8+O8+S8 -> 790 | F8: =IF(C8<0,0,C8) -> 596 | G8: =SUM(AG8:AH8) -> 0 | H8: =D8 -> 112.5 | I8: =(F8+G8)-H8 -> 483.5 | J8: =IF(I8<0,0,I8) -> 483.5 | K8: =SUM(AI8) -> 0 | L8: =H8 -> 112.5 | M8: =(J8+K8)-L8 -> 371 | N8: =IF(M8<0,0,M8) -> 371 | O8: =SUM(AJ8:AQ8) -> 790 | P8: =L8 -> 112.5 | Q8: =(N8+O8)-P8 -> 1048.5 | R8: =IF(Q8<0,0,Q8) -> 1048.5 | S8: =SUM(AR8:AT8) -> 0 | T8: =P8 -> 112.5 | U8: =(R8+S8)-T8 -> 936 | V8: =IF(U8<0,0,U8/D8) -> 8.32 | W8: 6 | X8: 12 | Y8: =IF(IF(V8>W8,X8-V8,X8-V8)<0,0,IF(V8>W8,X8-V8,X8-V8)) -> 3.68 | Z8: =(Y8*D8) -> 414 | AA8: 400 | AB8: fdk | AC8: US$58.00 | AD8: 63 | AE8: 54 | AK8: 400 | AN8: 250 | AQ8: 140
A9: HIGHWAY | B9: MI0285 - 215/75 R17.5 TYRE | C9: =VLOOKUP(B9,'JAN26'!$A$1:I912,8,0) -> 377 | D9: =VLOOKUP(B9,AVE!B$1:GB3523,2,0) -> 40.5 | E9: =G9+K9+O9+S9 -> 120 | F9: =IF(C9<0,0,C9) -> 377 | G9: =SUM(AG9:AH9) -> 120 | H9: =D9 -> 40.5 | I9: =(F9+G9)-H9 -> 456.5 | J9: =IF(I9<0,0,I9) -> 456.5 | K9: =SUM(AI9) -> 0 | L9: =H9 -> 40.5 | M9: =(J9+K9)-L9 -> 416 | N9: =IF(M9<0,0,M9) -> 416 | O9: =SUM(AJ9:AQ9) -> 0 | P9: =L9 -> 40.5 | Q9: =(N9+O9)-P9 -> 375.5 | R9: =IF(Q9<0,0,Q9) -> 375.5 | S9: =SUM(AR9:AT9) -> 0 | T9: =P9 -> 40.5 | U9: =(R9+S9)-T9 -> 335 | V9: =IF(U9<0,0,U9/D9) -> 8.2716049 | W9: 6 | X9: 12 | Y9: =IF(IF(V9>W9,X9-V9,X9-V9)<0,0,IF(V9>W9,X9-V9,X9-V9)) -> 3.7283951 | Z9: =(Y9*D9) -> 151 | AA9: 150 | AB9: roadshine / fedrik / rb | AC9: US$52.00 | AD9: 53 | AE9: 55 | AG9: 120
A10: HIGHWAY | B10: MI0570 - 225/80R17.5 TYRE TL | C10: =VLOOKUP(B10,'JAN26'!$A$1:I913,8,0) -> 211 | D10: =VLOOKUP(B10,AVE!B$1:GB3524,2,0) -> 53 | E10: =G10+K10+O10+S10 -> 350 | F10: =IF(C10<0,0,C10) -> 211 | G10: =SUM(AG10:AH10) -> 200 | H10: =D10 -> 53 | I10: =(F10+G10)-H10 -> 358 | J10: =IF(I10<0,0,I10) -> 358 | K10: =SUM(AI10) -> 100 | L10: =H10 -> 53 | M10: =(J10+K10)-L10 -> 405 | N10: =IF(M10<0,0,M10) -> 405 | O10: =SUM(AJ10:AQ10) -> 0 | P10: =L10 -> 53 | Q10: =(N10+O10)-P10 -> 352 | R10: =IF(Q10<0,0,Q10) -> 352 | S10: =SUM(AR10:AT10) -> 50 | T10: =P10 -> 53 | U10: =(R10+S10)-T10 -> 349 | V10: =IF(U10<0,0,U10/D10) -> 6.5849057 | W10: 6 | X10: 12 | Y10: =IF(IF(V10>W10,X10-V10,X10-V10)<0,0,IF(V10>W10,X10-V10,X10-V10)) -> 5.4150943 | Z10: =(Y10*D10) -> 287 | AA10: 300 | AB10: rs | AC10: US$58.00 | AE10: 65 | AG10: 200 | AI10: 100 | AT10: 50
A11: UNIversal TTF | B11: MI0363 - 8.25R16 TYRES WITH TUBE | C11: =VLOOKUP(B11,'JAN26'!$A$1:I914,8,0) -> 327 | D11: =VLOOKUP(B11,AVE!B$1:GB3525,2,0) -> 26.25 | E11: =G11+K11+O11+S11 -> 80 | F11: =IF(C11<0,0,C11) -> 327 | G11: =SUM(AG11:AH11) -> 0 | H11: =D11 -> 26.25 | I11: =(F11+G11)-H11 -> 300.75 | J11: =IF(I11<0,0,I11) -> 300.75 | K11: =SUM(AI11) -> 0 | L11: =H11 -> 26.25 | M11: =(J11+K11)-L11 -> 274.5 | N11: =IF(M11<0,0,M11) -> 274.5 | O11: =SUM(AJ11:AQ11) -> 80 | P11: =L11 -> 26.25 | Q11: =(N11+O11)-P11 -> 328.25 | R11: =IF(Q11<0,0,Q11) -> 328.25 | S11: =SUM(AR11:AT11) -> 0 | T11: =P11 -> 26.25 | U11: =(R11+S11)-T11 -> 302 | V11: =IF(U11<0,0,U11/D11) -> 11.504762 | W11: 6 | X11: 12 | Y11: =IF(IF(V11>W11,X11-V11,X11-V11)<0,0,IF(V11>W11,X11-V11,X11-V11)) -> 0.4952381 | Z11: =(Y11*D11) -> 13 | AB11: fdr | AC11: US$71.00 | AD11: 71 | AE11: 67 | AN11: 50 | AQ11: 30
A12: HIGHWAY | B12: MI0662 - 205/75R17.5 TYRE PCR | C12: =VLOOKUP(B12,'JAN26'!$A$1:I915,8,0) -> 93 | D12: =VLOOKUP(B12,AVE!B$1:GB3526,2,0) -> 14.857143 | E12: =G12+K12+O12+S12 -> 100 | F12: =IF(C12<0,0,C12) -> 93 | G12: =SUM(AG12:AH12) -> 0 | H12: =D12 -> 14.857143 | I12: =(F12+G12)-H12 -> 78.142857 | J12: =IF(I12<0,0,I12) -> 78.142857 | K12: =SUM(AI12) -> 0 | L12: =H12 -> 14.857143 | M12: =(J12+K12)-L12 -> 63.285714 | N12: =IF(M12<0,0,M12) -> 63.285714 | O12: =SUM(AJ12:AQ12) -> 100 | P12: =L12 -> 14.857143 | Q12: =(N12+O12)-P12 -> 148.42857 | R12: =IF(Q12<0,0,Q12) -> 148.42857 | S12: =SUM(AR12:AT12) -> 0 | T12: =P12 -> 14.857143 | U12: =(R12+S12)-T12 -> 133.57143 | V12: =IF(U12<0,0,U12/D12) -> 8.9903846 | W12: 6 | X12: 12 | Y12: =IF(IF(V12>W12,X12-V12,X12-V12)<0,0,IF(V12>W12,X12-V12,X12-V12)) -> 3.0096154 | Z12: =(Y12*D12) -> 44.714286 | AA12: 50 | AN12: 100
A13: HIGHWAY | B13: MI0299 - 235/75R17.5 TYRE | C13: =VLOOKUP(B13,'JAN26'!$A$1:I916,8,0) -> 65 | D13: =VLOOKUP(B13,AVE!B$1:GB3527,2,0) -> 21.625 | E13: =G13+K13+O13+S13 -> 200 | F13: =IF(C13<0,0,C13) -> 65 | G13: =SUM(AG13:AH13) -> 0 | H13: =D13 -> 21.625 | I13: =(F13+G13)-H13 -> 43.375 | J13: =IF(I13<0,0,I13) -> 43.375 | K13: =SUM(AI13) -> 0 | L13: =H13 -> 21.625 | M13: =(J13+K13)-L13 -> 21.75 | N13: =IF(M13<0,0,M13) -> 21.75 | O13: =SUM(AJ13:AQ13) -> 200 | P13: =L13 -> 21.625 | Q13: =(N13+O13)-P13 -> 200.125 | R13: =IF(Q13<0,0,Q13) -> 200.125 | S13: =SUM(AR13:AT13) -> 0 | T13: =P13 -> 21.625 | U13: =(R13+S13)-T13 -> 178.5 | V13: =IF(U13<0,0,U13/D13) -> 8.2543353 | W13: 6 | X13: 12 | Y13: =IF(IF(V13>W13,X13-V13,X13-V13)<0,0,IF(V13>W13,X13-V13,X13-V13)) -> 3.7456647 | Z13: =(Y13*D13) -> 81 | AA13: 100 | AC13: US$60.00 | AL13: 100 | AM13: =90+10 -> 100
A14: HIGHWAY | B14: MI0446 - 265/70R19.5 PCR TYRE | C14: =VLOOKUP(B14,'JAN26'!$A$1:I917,8,0) -> 91 | D14: =VLOOKUP(B14,AVE!B$1:GB3528,2,0) -> 17 | E14: =G14+K14+O14+S14 -> 80 | F14: =IF(C14<0,0,C14) -> 91 | G14: =SUM(AG14:AH14) -> 0 | H14: =D14 -> 17 | I14: =(F14+G14)-H14 -> 74 | J14: =IF(I14<0,0,I14) -> 74 | K14: =SUM(AI14) -> 0 | L14: =H14 -> 17 | M14: =(J14+K14)-L14 -> 57 | N14: =IF(M14<0,0,M14) -> 57 | O14: =SUM(AJ14:AQ14) -> 40 | P14: =L14 -> 17 | Q14: =(N14+O14)-P14 -> 80 | R14: =IF(Q14<0,0,Q14) -> 80 | S14: =SUM(AR14:AT14) -> 40 | T14: =P14 -> 17 | U14: =(R14+S14)-T14 -> 103 | V14: =IF(U14<0,0,U14/D14) -> 6.0588235 | W14: 6 | X14: 12 | Y14: =IF(IF(V14>W14,X14-V14,X14-V14)<0,0,IF(V14>W14,X14-V14,X14-V14)) -> 5.9411765 | Z14: =(Y14*D14) -> 101 | AA14: 100 | AC14: US$79.00 | AD14: 73 | AE14: 79 | AP14: 40 | AS14: 40
A15: HIGHWAY | B15: MI0577 - 285/70R19.5 PCR TYRE | C15: =VLOOKUP(B15,'JAN26'!$A$1:I918,8,0) -> 102 | D15: =VLOOKUP(B15,AVE!B$1:GB3529,2,0) -> 6.5714286 | E15: =G15+K15+O15+S15 -> 0 | F15: =IF(C15<0,0,C15) -> 102 | G15: =SUM(AG15:AH15) -> 0 | H15: =D15 -> 6.5714286 | I15: =(F15+G15)-H15 -> 95.428571 | J15: =IF(I15<0,0,I15) -> 95.428571 | K15: =SUM(AI15) -> 0 | L15: =H15 -> 6.5714286 | M15: =(J15+K15)-L15 -> 88.857143 | N15: =IF(M15<0,0,M15) -> 88.857143 | O15: =SUM(AJ15:AQ15) -> 0 | P15: =L15 -> 6.5714286 | Q15: =(N15+O15)-P15 -> 82.285714 | R15: =IF(Q15<0,0,Q15) -> 82.285714 | S15: =SUM(AR15:AT15) -> 0 | T15: =P15 -> 6.5714286 | U15: =(R15+S15)-T15 -> 75.714286 | V15: =IF(U15<0,0,U15/D15) -> 11.521739 | W15: 6 | X15: 12 | Y15: =IF(IF(V15>W15,X15-V15,X15-V15)<0,0,IF(V15>W15,X15-V15,X15-V15)) -> 0.47826087 | Z15: =(Y15*D15) -> 3.1428571
A16: DIFF | B16: MI0679 - 215/75R17.5 DIFF TYRE | C16: =VLOOKUP(B16,'JAN26'!$A$1:I919,8,0) -> 51 | D16: =VLOOKUP(B16,AVE!B$1:GB3530,2,0) -> 2.25 | E16: =G16+K16+O16+S16 -> 50 | F16: =IF(C16<0,0,C16) -> 51 | G16: =SUM(AG16:AH16) -> 0 | H16: =D16 -> 2.25 | I16: =(F16+G16)-H16 -> 48.75 | J16: =IF(I16<0,0,I16) -> 48.75 | K16: =SUM(AI16) -> 0 | L16: =H16 -> 2.25 | M16: =(J16+K16)-L16 -> 46.5 | N16: =IF(M16<0,0,M16) -> 46.5 | O16: =SUM(AJ16:AQ16) -> 50 | P16: =L16 -> 2.25 | Q16: =(N16+O16)-P16 -> 94.25 | R16: =IF(Q16<0,0,Q16) -> 94.25 | S16: =SUM(AR16:AT16) -> 0 | T16: =P16 -> 2.25 | U16: =(R16+S16)-T16 -> 92 | V16: =IF(U16<0,0,U16/D16) -> 40.888889 | W16: 6 | X16: 12 | Y16: =IF(IF(V16>W16,X16-V16,X16-V16)<0,0,IF(V16>W16,X16-V16,X16-V16)) -> 0 | Z16: =(Y16*D16) -> 0 | AM16: 50
A17: DIFF | B17: MI0680 - 9.50R17.5 DIFF TYRE | C17: =VLOOKUP(B17,'JAN26'!$A$1:I920,8,0) -> 6 | D17: =VLOOKUP(B17,AVE!B$1:GB3531,2,0) -> 7.3333333 | E17: =G17+K17+O17+S17 -> 100 | F17: =IF(C17<0,0,C17) -> 6 | G17: =SUM(AG17:AH17) -> 0 | H17: =D17 -> 7.3333333 | I17: =(F17+G17)-H17 -> -1.3333333 | J17: =IF(I17<0,0,I17) -> 0 | K17: =SUM(AI17) -> 0 | L17: =H17 -> 7.3333333 | M17: =(J17+K17)-L17 -> -7.3333333 | N17: =IF(M17<0,0,M17) -> 0 | O17: =SUM(AJ17:AQ17) -> 100 | P17: =L17 -> 7.3333333 | Q17: =(N17+O17)-P17 -> 92.666667 | R17: =IF(Q17<0,0,Q17) -> 92.666667 | S17: =SUM(AR17:AT17) -> 0 | T17: =P17 -> 7.3333333 | U17: =(R17+S17)-T17 -> 85.333333 | V17: =IF(U17<0,0,U17/D17) -> 11.636364 | W17: 6 | X17: 12 | Y17: =IF(IF(V17>W17,X17-V17,X17-V17)<0,0,IF(V17>W17,X17-V17,X17-V17)) -> 0.36363636 | Z17: =(Y17*D17) -> 2.6666667 | AQ17: 100
A18: HIGHWAY | B18: MI0681 - 7.00R15LT TUBELESS HIGHWAY TYRE | C18: =VLOOKUP(B18,'JAN26'!$A$1:I921,8,0) -> 29 | D18: =VLOOKUP(B18,AVE!B$1:GB3532,2,0) -> 6 | E18: =G18+K18+O18+S18 -> 0 | F18: =IF(C18<0,0,C18) -> 29 | G18: =SUM(AG18:AH18) -> 0 | H18: =D18 -> 6 | I18: =(F18+G18)-H18 -> 23 | J18: =IF(I18<0,0,I18) -> 23 | K18: =SUM(AI18) -> 0 | L18: =H18 -> 6 | M18: =(J18+K18)-L18 -> 17 | N18: =IF(M18<0,0,M18) -> 17 | O18: =SUM(AJ18:AQ18) -> 0 | P18: =L18 -> 6 | Q18: =(N18+O18)-P18 -> 11 | R18: =IF(Q18<0,0,Q18) -> 11 | S18: =SUM(AR18:AT18) -> 0 | T18: =P18 -> 6 | U18: =(R18+S18)-T18 -> 5 | V18: =IF(U18<0,0,U18/D18) -> 0.83333333 | W18: 6 | X18: 12 | Y18: =IF(IF(V18>W18,X18-V18,X18-V18)<0,0,IF(V18>W18,X18-V18,X18-V18)) -> 11.166667 | Z18: =(Y18*D18) -> 67 | AA18: 100
A19: Pads | B19: MI0575 - 29174-GOLD BRAKE PAD | C19: =VLOOKUP(B19,'JAN26'!$A$1:I922,8,0) -> 345 | D19: =VLOOKUP(B19,AVE!B$1:GB3533,2,0) -> 59.625 | E19: =G19+K19+O19+S19 -> 250 | F19: =IF(C19<0,0,C19) -> 345 | G19: =SUM(AG19:AH19) -> 0 | H19: =D19 -> 59.625 | I19: =(F19+G19)-H19 -> 285.375 | J19: =IF(I19<0,0,I19) -> 285.375 | K19: =SUM(AI19) -> 0 | L19: =H19 -> 59.625 | M19: =(J19+K19)-L19 -> 225.75 | N19: =IF(M19<0,0,M19) -> 225.75 | O19: =SUM(AJ19:AQ19) -> 250 | P19: =L19 -> 59.625 | Q19: =(N19+O19)-P19 -> 416.125 | R19: =IF(Q19<0,0,Q19) -> 416.125 | S19: =SUM(AR19:AT19) -> 0 | T19: =P19 -> 59.625 | U19: =(R19+S19)-T19 -> 356.5 | V19: =IF(U19<0,0,U19/D19) -> 5.9790356 | W19: 6 | X19: 12 | Y19: =IF(IF(V19>W19,X19-V19,X19-V19)<0,0,IF(V19>W19,X19-V19,X19-V19)) -> 6.0209644 | Z19: =(Y19*D19) -> 359 | AA19: 400 | AC19: 23.1 | AO19: 250
A20: Pads | B20: MI0209 - WVA29174-SNP | C20: =VLOOKUP(B20,'JAN26'!$A$1:I923,8,0) -> 108 | D20: =VLOOKUP(B20,AVE!B$1:GB3534,2,0) -> 38.285714 | E20: =G20+K20+O20+S20 -> 150 | F20: =IF(C20<0,0,C20) -> 108 | G20: =SUM(AG20:AH20) -> 0 | H20: =D20 -> 38.285714 | I20: =(F20+G20)-H20 -> 69.714286 | J20: =IF(I20<0,0,I20) -> 69.714286 | K20: =SUM(AI20) -> 0 | L20: =H20 -> 38.285714 | M20: =(J20+K20)-L20 -> 31.428571 | N20: =IF(M20<0,0,M20) -> 31.428571 | O20: =SUM(AJ20:AQ20) -> 150 | P20: =L20 -> 38.285714 | Q20: =(N20+O20)-P20 -> 143.14286 | R20: =IF(Q20<0,0,Q20) -> 143.14286 | S20: =SUM(AR20:AT20) -> 0 | T20: =P20 -> 38.285714 | U20: =(R20+S20)-T20 -> 104.85714 | V20: =IF(U20<0,0,U20/D20) -> 2.738806 | W20: 6 | X20: 12 | Y20: =IF(IF(V20>W20,X20-V20,X20-V20)<0,0,IF(V20>W20,X20-V20,X20-V20)) -> 9.261194 | Z20: =(Y20*D20) -> 354.57143 | AA20: 400 | AC20: 19.5 | AO20: 150
A21: Pads | B21: MI0210 - WVA29087-SNP | C21: =VLOOKUP(B21,'JAN26'!$A$1:I924,8,0) -> 232 | D21: =VLOOKUP(B21,AVE!B$1:GB3535,2,0) -> 6.5 | E21: =G21+K21+O21+S21 -> 0 | F21: =IF(C21<0,0,C21) -> 232 | G21: =SUM(AG21:AH21) -> 0 | H21: =D21 -> 6.5 | I21: =(F21+G21)-H21 -> 225.5 | J21: =IF(I21<0,0,I21) -> 225.5 | K21: =SUM(AI21) -> 0 | L21: =H21 -> 6.5 | M21: =(J21+K21)-L21 -> 219 | N21: =IF(M21<0,0,M21) -> 219 | O21: =SUM(AJ21:AQ21) -> 0 | P21: =L21 -> 6.5 | Q21: =(N21+O21)-P21 -> 212.5 | R21: =IF(Q21<0,0,Q21) -> 212.5 | S21: =SUM(AR21:AT21) -> 0 | T21: =P21 -> 6.5 | U21: =(R21+S21)-T21 -> 206 | V21: =IF(U21<0,0,U21/D21) -> 31.692308 | W21: 6 | X21: 12 | Y21: =IF(IF(V21>W21,X21-V21,X21-V21)<0,0,IF(V21>W21,X21-V21,X21-V21)) -> 0 | Z21: =(Y21*D21) -> 0
A22: Pads | B22: MI0576 - 29087-GOLD BRAKE PAD | C22: =VLOOKUP(B22,'JAN26'!$A$1:I925,8,0) -> 135 | D22: =VLOOKUP(B22,AVE!B$1:GB3536,2,0) -> 10.8 | E22: =G22+K22+O22+S22 -> 0 | F22: =IF(C22<0,0,C22) -> 135 | G22: =SUM(AG22:AH22) -> 0 | H22: =D22 -> 10.8 | I22: =(F22+G22)-H22 -> 124.2 | J22: =IF(I22<0,0,I22) -> 124.2 | K22: =SUM(AI22) -> 0 | L22: =H22 -> 10.8 | M22: =(J22+K22)-L22 -> 113.4 | N22: =IF(M22<0,0,M22) -> 113.4 | O22: =SUM(AJ22:AQ22) -> 0 | P22: =L22 -> 10.8 | Q22: =(N22+O22)-P22 -> 102.6 | R22: =IF(Q22<0,0,Q22) -> 102.6 | S22: =SUM(AR22:AT22) -> 0 | T22: =P22 -> 10.8 | U22: =(R22+S22)-T22 -> 91.8 | V22: =IF(U22<0,0,U22/D22) -> 8.5 | W22: 6 | X22: 12 | Y22: =IF(IF(V22>W22,X22-V22,X22-V22)<0,0,IF(V22>W22,X22-V22,X22-V22)) -> 3.5 | Z22: =(Y22*D22) -> 37.8 | AA22: 50
A23: Pads | B23: MI0138 - WVA29177 | C23: =VLOOKUP(B23,'JAN26'!$A$1:I926,8,0) -> 8 | D23: =VLOOKUP(B23,AVE!B$1:GB3537,2,0) -> 9.8333333 | E23: =G23+K23+O23+S23 -> 100 | F23: =IF(C23<0,0,C23) -> 8 | G23: =SUM(AG23:AH23) -> 0 | H23: =D23 -> 9.8333333 | I23: =(F23+G23)-H23 -> -1.8333333 | J23: =IF(I23<0,0,I23) -> 0 | K23: =SUM(AI23) -> 0 | L23: =H23 -> 9.8333333 | M23: =(J23+K23)-L23 -> -9.8333333 | N23: =IF(M23<0,0,M23) -> 0 | O23: =SUM(AJ23:AQ23) -> 100 | P23: =L23 -> 9.8333333 | Q23: =(N23+O23)-P23 -> 90.166667 | R23: =IF(Q23<0,0,Q23) -> 90.166667 | S23: =SUM(AR23:AT23) -> 0 | T23: =P23 -> 9.8333333 | U23: =(R23+S23)-T23 -> 80.333333 | V23: =IF(U23<0,0,U23/D23) -> 8.1694915 | W23: 6 | X23: 12 | Y23: =IF(IF(V23>W23,X23-V23,X23-V23)<0,0,IF(V23>W23,X23-V23,X23-V23)) -> 3.8305085 | Z23: =(Y23*D23) -> 37.666667 | AA23: 50 | AB23: 200 extra box mahant | AC23: 19.5 | AO23: 100
A24: Pads | B24: MI0743 - WVA29173 | C24: =VLOOKUP(B24,'JAN26'!$A$1:I927,8,0) -> 4 | D24: =VLOOKUP(B24,AVE!B$1:GB3538,2,0) -> 4.5 | E24: =G24+K24+O24+S24 -> 100 | F24: =IF(C24<0,0,C24) -> 4 | G24: =SUM(AG24:AH24) -> 0 | H24: =D24 -> 4.5 | I24: =(F24+G24)-H24 -> -0.5 | J24: =IF(I24<0,0,I24) -> 0 | K24: =SUM(AI24) -> 0 | L24: =H24 -> 4.5 | M24: =(J24+K24)-L24 -> -4.5 | N24: =IF(M24<0,0,M24) -> 0 | O24: =SUM(AJ24:AQ24) -> 100 | P24: =L24 -> 4.5 | Q24: =(N24+O24)-P24 -> 95.5 | R24: =IF(Q24<0,0,Q24) -> 95.5 | S24: =SUM(AR24:AT24) -> 0 | T24: =P24 -> 4.5 | U24: =(R24+S24)-T24 -> 91 | V24: =IF(U24<0,0,U24/D24) -> 20.222222 | W24: 6 | X24: 12 | Y24: =IF(IF(V24>W24,X24-V24,X24-V24)<0,0,IF(V24>W24,X24-V24,X24-V24)) -> 0 | Z24: =(Y24*D24) -> 0 | AC24: 19.5 | AO24: 100
A25: Pads | B25: WVA 29228 | C25: 0 | D25: =VLOOKUP(B25,AVE!B$1:GB3539,2,0) -> #N/A | G25: =SUM(AG25:AH25) -> 0 | K25: =SUM(AI25) -> 0 | O25: =SUM(AJ25:AQ25) -> 50 | S25: =SUM(AR25:AT25) -> 0 | W25: 6 | X25: 12 | AO25: 50
A26: TUBE | B26: MI0718 - TUBE ONLY 10.00R20 | C26: =VLOOKUP(B26,'JAN26'!$A$1:I929,8,0) -> 100 | D26: =VLOOKUP(B26,AVE!B$1:GB3540,2,0) -> 16.666667 | E26: =G26+K26+O26+S26 -> 200 | F26: =IF(C26<0,0,C26) -> 100 | G26: =SUM(AG26:AH26) -> 0 | H26: =D26 -> 16.666667 | I26: =(F26+G26)-H26 -> 83.333333 | J26: =IF(I26<0,0,I26) -> 83.333333 | K26: =SUM(AI26) -> 0 | L26: =H26 -> 16.666667 | M26: =(J26+K26)-L26 -> 66.666667 | N26: =IF(M26<0,0,M26) -> 66.666667 | O26: =SUM(AJ26:AQ26) -> 200 | P26: =L26 -> 16.666667 | Q26: =(N26+O26)-P26 -> 250 | R26: =IF(Q26<0,0,Q26) -> 250 | S26: =SUM(AR26:AT26) -> 0 | T26: =P26 -> 16.666667 | U26: =(R26+S26)-T26 -> 233.33333 | V26: =IF(U26<0,0,U26/D26) -> 14 | W26: 6 | X26: 12 | Y26: =IF(IF(V26>W26,X26-V26,X26-V26)<0,0,IF(V26>W26,X26-V26,X26-V26)) -> 0 | Z26: =(Y26*D26) -> 0 | AE26: 7.5 | AQ26: 200
A27: TUBE | B27: MI0663 - TUBE ONLY 12.00R20 | C27: 0 | D27: =VLOOKUP(B27,AVE!B$1:GB3541,2,0) -> 10.125 | E27: =G27+K27+O27+S27 -> 300 | F27: =IF(C27<0,0,C27) -> 0 | G27: =SUM(AG27:AH27) -> 0 | H27: =D27 -> 10.125 | I27: =(F27+G27)-H27 -> -10.125 | J27: =IF(I27<0,0,I27) -> 0 | K27: =SUM(AI27) -> 0 | L27: =H27 -> 10.125 | M27: =(J27+K27)-L27 -> -10.125 | N27: =IF(M27<0,0,M27) -> 0 | O27: =SUM(AJ27:AQ27) -> 300 | P27: =L27 -> 10.125 | Q27: =(N27+O27)-P27 -> 289.875 | R27: =IF(Q27<0,0,Q27) -> 289.875 | S27: =SUM(AR27:AT27) -> 0 | T27: =P27 -> 10.125 | U27: =(R27+S27)-T27 -> 279.75 | V27: =IF(U27<0,0,U27/D27) -> 27.62963 | W27: 6 | X27: 12 | Y27: =IF(IF(V27>W27,X27-V27,X27-V27)<0,0,IF(V27>W27,X27-V27,X27-V27)) -> 0 | Z27: =(Y27*D27) -> 0 | AC27: 11.5 | AN27: 300
A28: TUBE | B28: MI0740 - TUBE ONLY 7.00R16 | C28: =VLOOKUP(B28,'JAN26'!$A$1:I931,8,0) -> 380 | D28: =VLOOKUP(B28,AVE!B$1:GB3542,2,0) -> 35 | E28: =G28+K28+O28+S28 -> 150 | F28: =IF(C28<0,0,C28) -> 380 | G28: =SUM(AG28:AH28) -> 0 | H28: =D28 -> 35 | I28: =(F28+G28)-H28 -> 345 | J28: =IF(I28<0,0,I28) -> 345 | K28: =SUM(AI28) -> 0 | L28: =H28 -> 35 | M28: =(J28+K28)-L28 -> 310 | N28: =IF(M28<0,0,M28) -> 310 | O28: =SUM(AJ28:AQ28) -> 150 | P28: =L28 -> 35 | Q28: =(N28+O28)-P28 -> 425 | R28: =IF(Q28<0,0,Q28) -> 425 | S28: =SUM(AR28:AT28) -> 0 | T28: =P28 -> 35 | U28: =(R28+S28)-T28 -> 390 | V28: =IF(U28<0,0,U28/D28) -> 11.142857 | W28: 6 | X28: 12 | Y28: =IF(IF(V28>W28,X28-V28,X28-V28)<0,0,IF(V28>W28,X28-V28,X28-V28)) -> 0.85714286 | Z28: =(Y28*D28) -> 30 | AQ28: 150
A29: TUBE | B29: MI0741 - TUBE ONLY 7.50R16 | C29: =VLOOKUP(B29,'JAN26'!$A$1:I932,8,0) -> 407 | D29: =VLOOKUP(B29,AVE!B$1:GB3543,2,0) -> 21 | E29: =G29+K29+O29+S29 -> 50 | F29: =IF(C29<0,0,C29) -> 407 | G29: =SUM(AG29:AH29) -> 0 | H29: =D29 -> 21 | I29: =(F29+G29)-H29 -> 386 | J29: =IF(I29<0,0,I29) -> 386 | K29: =SUM(AI29) -> 0 | L29: =H29 -> 21 | M29: =(J29+K29)-L29 -> 365 | N29: =IF(M29<0,0,M29) -> 365 | O29: =SUM(AJ29:AQ29) -> 50 | P29: =L29 -> 21 | Q29: =(N29+O29)-P29 -> 394 | R29: =IF(Q29<0,0,Q29) -> 394 | S29: =SUM(AR29:AT29) -> 0 | T29: =P29 -> 21 | U29: =(R29+S29)-T29 -> 373 | V29: =IF(U29<0,0,U29/D29) -> 17.761905 | W29: 6 | X29: 12 | Y29: =IF(IF(V29>W29,X29-V29,X29-V29)<0,0,IF(V29>W29,X29-V29,X29-V29)) -> 0 | Z29: =(Y29*D29) -> 0 | AE29: 4 | AQ29: 50
A30: TUBE | B30: MI0742 - TUBE ONLY 8.25R16 | C30: =VLOOKUP(B30,'JAN26'!$A$1:I933,8,0) -> 424 | D30: =VLOOKUP(B30,AVE!B$1:GB3544,2,0) -> 15.333333 | E30: =G30+K30+O30+S30 -> 0 | F30: =IF(C30<0,0,C30) -> 424 | G30: =SUM(AG30:AH30) -> 0 | H30: =D30 -> 15.333333 | I30: =(F30+G30)-H30 -> 408.66667 | J30: =IF(I30<0,0,I30) -> 408.66667 | K30: =SUM(AI30) -> 0 | L30: =H30 -> 15.333333 | M30: =(J30+K30)-L30 -> 393.33333 | N30: =IF(M30<0,0,M30) -> 393.33333 | O30: =SUM(AJ30:AQ30) -> 0 | P30: =L30 -> 15.333333 | Q30: =(N30+O30)-P30 -> 378 | R30: =IF(Q30<0,0,Q30) -> 378 | S30: =SUM(AR30:AT30) -> 0 | T30: =P30 -> 15.333333 | U30: =(R30+S30)-T30 -> 362.66667 | V30: =IF(U30<0,0,U30/D30) -> 23.652174 | W30: 6 | X30: 12 | Y30: =IF(IF(V30>W30,X30-V30,X30-V30)<0,0,IF(V30>W30,X30-V30,X30-V30)) -> 0 | Z30: =(Y30*D30) -> 0
A31: TUBE | B31: MI0844 - TUBE ONLY 8.25 R20 | D31: =VLOOKUP(B31,AVE!B$1:GB3545,2,0) -> 0 | G31: =SUM(AG31:AH31) -> 0 | K31: =SUM(AI31) -> 0 | O31: =SUM(AJ31:AQ31) -> 0 | S31: =SUM(AR31:AT31) -> 0 | W31: 6 | X31: 12
A32: DIFF | B32: MI0359 - 7.00R16 TYRE | C32: 0 | E32: =G32+K32+O32+S32 -> 25 | G32: =SUM(AG32:AH32) -> 0 | K32: =SUM(AI32) -> 0 | O32: =SUM(AJ32:AQ32) -> 25 | S32: =SUM(AR32:AT32) -> 0 | W32: 6 | X32: 12 | Z32: =(Y32*D32) -> 0 | AE32: 56 | AK32: 25
A33: DIFF | B33: MI0286 - 7.50R16 TYRE | C33: 0 | E33: =G33+K33+O33+S33 -> 25 | G33: =SUM(AG33:AH33) -> 0 | K33: =SUM(AI33) -> 0 | O33: =SUM(AJ33:AQ33) -> 25 | S33: =SUM(AR33:AT33) -> 0 | W33: 6 | X33: 12 | AK33: 25
A34: CONTAINER | E34: =G34+K34+O34+S34 -> 0 | G34: =SUM(AG34:AH34) -> 0 | K34: =SUM(AI34) -> 0 | O34: =SUM(AJ34:AQ34) -> 0 | S34: =SUM(AR34:AT34) -> 0 | W34: 6 | X34: 12
K35: =SUM(AG35:AH35) -> 0 | O35: =SUM(AJ35:AQ35) -> 0 | S35: =SUM(AO35) -> 0
Z37: TOTAL
B38: PROCESS TIME | C38: 30
B39: PRODUCTION | C39: 30
B40: TRANSIT | C40: 45
B41: ROAD TRANSPORT | C41: 30
B42: TOTAL | C42: =SUM(C38:C41) -> 135
B43: MONTHS | C43: =C42/30 -> 4.5
B45: LTR + 1 TYRE
B46: PCR + PCR

Sheet PCR
B1: PCR - DOUBLE
B2: Updated 0n
B3: =TODAY() -> 46188
F4: =TODAY()+3 -> 46191 | J4: =F4+31 -> 46222 | N4: =J4+31 -> 46253 | R4: =N4+30 -> 46283 | V4: Procurement | AA4: Management | AE4: FEB | AF4: FEB | AG4: MAR | AH4: MAR | AI4: MAR | AJ4: MAR | AK4: APR | AL4: APR | AM4: APR | AN4: APR | AO4: APR | AP4: APR | AQ4: MAY | AR4: MAY | AS4: MAY
A5: S.No | B5: Part No. / Description | C5: Opening Stock | D5: Avg Con | E5: INFLOW TOTAL | F5: OB | G5: Inflow | H5: Actual sale | I5: Closing Stock | J5: OB | K5: Inflow | L5: Actual sale | M5: Closing Stock | N5: OB | O5: Inflow | P5: Actual sale | Q5: Closing Stock | R5: OB | S5: Inflow | T5: Actual sale | U5: Closing Stock | V5: Stk (in Months) | W5: Min Stk (In Months) | X5: Max Stk (In Months) | Y5: Requirement (In Months) | Z5: Requirements (Qty) | AA5: FINAL QTY | AB5: RS PRICE | AC5: RB PRICE | AD5: TRSN PRICE | AE5: RS EX-635/25 2HC | AF5: RS EX-644/25 2HC | AG5: B - FDK CAX-1109 4HC WtH RB PCR | AH5: RS EX-714/25 2HC WITH PCR | AI5: RB 2HC JT5001C WITH PCR | AJ5: RS EX-741/25 3HC WITH PCR | AK5: RS EX-701/25 3HC with spare in1 | AL5: RB JT5001A 3HC PCR | AM5: TRANSTON T25I801 1HC | AN5: RB T5112A 5HC WITH PCR | AO5: RB 1 HC 0114A WITH PCR | AP5: RB 1 HC 0114B WITH PCR | AQ5: RB DEC ORDER | AR5: RS BALANCE DEC ORDER | AS5: RB JAN ORDER
B6: MI0340 - 185/70R14 TYRE | C6: =VLOOKUP(B6,'JAN26'!$A$1:I909,8,0) -> 6597 | D6: =VLOOKUP(B6,AVE!B$1:GB3522,2,0) -> 937.625 | E6: =G6+K6+O6+S6 -> 4598 | F6: =IF(C6<0,0,C6) -> 6597 | G6: =SUM(AE6:AF6) -> 751 | H6: =D6 -> 937.625 | I6: =(F6+G6)-H6 -> 6410.375 | J6: =IF(I6<0,0,I6) -> 6410.375 | K6: =SUM(AG6:AJ6) -> 2050 | L6: =H6 -> 937.625 | M6: =(J6+K6)-L6 -> 7522.75 | N6: =IF(M6<0,0,M6) -> 7522.75 | O6: =SUM(AK6:AP6) -> 1797 | P6: =L6 -> 937.625 | Q6: =(N6+O6)-P6 -> 8382.125 | R6: =IF(Q6<0,0,Q6) -> 8382.125 | S6: =SUM(AQ6:AS6) -> 0 | T6: =P6 -> 937.625 | U6: =(R6+S6)-T6 -> 7444.5 | V6: =IF(U6<0,0,U6/D6) -> 7.9397414 | W6: 6 | X6: =W6+6 -> 12 | Y6: =IF(IF(V6>W6,X6-V6,X6-V6)<0,0,IF(V6>W6,X6-V6,X6-V6)) -> 4.0602586 | Z6: =(Y6*D6) -> 3807 | AA6: 4000 | AB6: 16 | AC6: 16.14 | AF6: =565+186 -> 751 | AG6: 500 | AH6: 800 | AI6: 350 | AJ6: =70+300+30 -> 400 | AK6: 600 | AL6: 250 | AM6: 610 | AO6: 167 | AP6: 170
B7: MI0332 - 195/65R15 TYRE | C7: =VLOOKUP(B7,'JAN26'!$A$1:I910,8,0) -> 945 | D7: =VLOOKUP(B7,AVE!B$1:GB3523,2,0) -> 285.625 | E7: =G7+K7+O7+S7 -> 1470 | F7: =IF(C7<0,0,C7) -> 945 | G7: =SUM(AE7:AF7) -> 0 | H7: =D7 -> 285.625 | I7: =(F7+G7)-H7 -> 659.375 | J7: =IF(I7<0,0,I7) -> 659.375 | K7: =SUM(AG7:AJ7) -> 1100 | L7: =H7 -> 285.625 | M7: =(J7+K7)-L7 -> 1473.75 | N7: =IF(M7<0,0,M7) -> 1473.75 | O7: =SUM(AK7:AP7) -> 370 | P7: =L7 -> 285.625 | Q7: =(N7+O7)-P7 -> 1558.125 | R7: =IF(Q7<0,0,Q7) -> 1558.125 | S7: =SUM(AQ7:AS7) -> 0 | T7: =P7 -> 285.625 | U7: =(R7+S7)-T7 -> 1272.5 | V7: =IF(U7<0,0,U7/D7) -> 4.4551422 | W7: 6 | X7: =W7+6 -> 12 | Y7: =IF(IF(V7>W7,X7-V7,X7-V7)<0,0,IF(V7>W7,X7-V7,X7-V7)) -> 7.5448578 | Z7: =(Y7*D7) -> 2155 | AA7: 2000 | AB7: 17.5 | AC7: 17.02 | AG7: 700 | AI7: 400 | AL7: 370
